Workbook

Sheet README
A1: README — how this workbook is organised
A3: 25 sheets, grouped into 6 colour-coded families (tab colour = group). Start with START_HERE, then NAVIGATION_MAP for the full clickable index. This page is the one-stop explanation of what every sheet is and why it's coloured the way it is -- see CHANGELOG for what changed and when.
A5: Navigate
A6: =HYPERLINK("#START_HERE!A1","START_HERE") | B6: Landing page: what this workbook is, where to start.
A7: =HYPERLINK("#NAVIGATION_MAP!A1","NAVIGATION_MAP") | B7: Full sheet index with hyperlinks, one row per sheet, coloured by group.
A8: =HYPERLINK("#LISTS!A1","LISTS") | B8: Raw dropdown/reference lists used by data validation elsewhere.
A10: Overview
A11: =HYPERLINK("#DASHBOARD!A1","DASHBOARD") | B11: Top-line charts: Top-15 OFFER by S, Tier split, Category averages, full 50-item rank profile (with the item-7 spike explainer).
A12: =HYPERLINK("#DASHBOARD_2!A1","DASHBOARD_2") | B12: Secondary dashboard views.
A14: Live review / input
A15: =HYPERLINK("#EVALUATION_WORKSPACE!A1","EVALUATION_WORKSPACE") | B15: Main interaction sheet -- static rank read-only, reviewer input starts at STATUS columns.
A16: =HYPERLINK("#EVALUATION_INPUT!A1","EVALUATION_INPUT") | B16: Raw bidder input capture, feeds EVALUATION_WORKSPACE.
A17: =HYPERLINK("#NEGOTIATION_AGENDA!A1","NEGOTIATION_AGENDA") | B17: Talking points generated from low-status / high-S items, for negotiation prep.
A19: Rankings & trace
A20: =HYPERLINK("#OFFER_RANKING!A1","OFFER_RANKING") | B20: Static BT ranking of all 50 OFFER items -- the SSOT for OFFER importance.
A21: =HYPERLINK("#RTM_RANKING!A1","RTM_RANKING") | B21: Static BT ranking of all 722 RTM requirements -- the SSOT for RTM importance.
A22: =HYPERLINK("#RTM_CROSSWALK!A1","RTM_CROSSWALK") | B22: One row per OFFER<->RTM relationship (up to 66 per item) -- the full link detail behind OFFER_RANKING's condensed 'Primary RTMs' summary.
A23: =HYPERLINK("#RTM_REVIEW_QUEUE!A1","RTM_REVIEW_QUEUE") | B23: RTM rows flagged for reviewer attention, ordered by priority.
A24: =HYPERLINK("#RTM_LOOKUP!A1","RTM_LOOKUP") | B24: Pick one RTM, see everything about it on one screen.
A25: =HYPERLINK("#DOMAIN_SUMMARY!A1","DOMAIN_SUMMARY") | B25: RTM counts/tiers/avg S rolled up by Domain (22 domains).
A26: =HYPERLINK("#CLUSTERS!A1","CLUSTERS") | B26: The 8 classification clusters (C1-C8) and their member OFFER items.
A28: Reference / canonical
A29: =HYPERLINK("#OFFER_CANONICAL!A1","OFFER_CANONICAL") | B29: Original hand-curated source data for all 50 OFFER items -- read-only upstream of OFFER_RANKING.
A30: =HYPERLINK("#STANDARDS!A1","STANDARDS") | B30: Codes/standards register -- which RTM/OFFER items cite which external standard.
A31: =HYPERLINK("#DELIVERABLES!A1","DELIVERABLES") | B31: Per-OFFER-item evidence/fulfilment expectations.
A32: =HYPERLINK("#TAXONOMY!A1","TAXONOMY") | B32: Controlled vocabularies used throughout (Requirement Type, EPIC evidence-types, disposition, etc.) -- the single place these are DEFINED, reused elsewhere.
A33: =HYPERLINK("#COMPLIANCE_LEGEND!A1","COMPLIANCE_LEGEND") | B33: STATUS colour/label legend used on EVALUATION_WORKSPACE.
A34: =HYPERLINK("#WEIGHTS_METHOD!A1","WEIGHTS_METHOD") | B34: The 7 frozen BT weights (L/R/P/F/Q/LC/C), how Weighted S/BT Win %/BT λ are built, and the weight-sensitivity scenarios (static + live toggle).
A36: Governance / QC
A37: =HYPERLINK("#QUALITY_CHECKS!A1","QUALITY_CHECKS") | B37: Automated formula-integrity and cross-reference checks over the whole workbook.
A38: =HYPERLINK("#AUDIT_NOTES!A1","AUDIT_NOTES") | B38: Free-text audit trail of judgement calls made during data curation.
A39: =HYPERLINK("#DMAIC_AUDIT!A1","DMAIC_AUDIT") | B39: DMAIC-cycle traceability for this evaluation process itself.
A40: =HYPERLINK("#CODING_HANDOVER!A1","CODING_HANDOVER") | B40: Technical handover notes for whoever maintains this workbook next.

Sheet CHANGELOG
A1: CHANGELOG
A3: Version | B3: Major changes
A4: v8 | B4: DELIVERABLES!F evidence text rewritten from generic boilerplate to per-item RTM cross-reference + EPIC-keyed evidence type.
A5: v9 | B5: Full 722 RTM / 50 OFFER value-weighted Pareto and Focus Score analysis added to the HTML Navigator (Domain/Category/Cluster, for both RTM and OFFER).
A6: v10 | B6: RTM_CROSSWALK: added a real header row (row 4 was blank), fixed a misleading dark-navy fill on row 5 that looked like a header, added AutoFilter/frozen panes, and colour-coded relation types (Direct/Supporting/Broad/Contextual).
A7: v11 | B7: RTM_CROSSWALK: added headers for columns M/N (QC check, Source basis); rewrote 233 of 377 rows (62%) of column L from generic boilerplate to genuinely per-row text.
A8: v12 | B8: Excel window/zoom defaults set for 16:9 full-screen opening; per-sheet autozoom by column-count.
A9: v13 | B9: Tab-colour taxonomy: all 25 sheets assigned to 6 named groups; NAVIGATION_MAP extended with a colour-swatch legend column.
A10: v14 | B10: Nav-row column-clipping fixed across multiple sheets; Cost=70% weight-sensitivity scenario (static table) added to WEIGHTS_METHOD.
A11: v15 | B11: Technical Depth (EVALUATION_WORKSPACE R/X) colour-coded (soft pink/orange/green), deliberately paler than STATUS.
A12: v16 | B12: Gate column (Yes/No) recoloured to reuse the exact T0 Gate red across EVALUATION_WORKSPACE/OFFER_RANKING/RTM_RANKING; DASHBOARD's rank-profile chart got a callout explaining the item-7 spike (OFFER-09's S=55.67 entering rank 7, right after the 6 gate-precedence items).
A13: v17 | B13: STANDARDS!B lazy-boilerplate fixed (26 of 44 rows, grounded in linked RTM data); weight-dimension (L/R/P/F/Q/LC/C) colour legend + header comments added to OFFER_RANKING/RTM_RANKING/WEIGHTS_METHOD; all 7 raw dimension columns given a uniform 0-3 heatmap (previously only 3 of 7 had any colour) on both ranking sheets; live Cost-weight scenario toggle added (dropdown + formula-driven re-rank, no macro); new CATEGORY_FOCUS sheet (per-category top-ranked 'hidden champions' + Category x Cluster density heat maps, RTM and OFFER); README + this CHANGELOG sheet added.

Sheet START_HERE
A1: QPS OFFER evaluation workbook — v18 DMAIC-ready
A2: Use this workbook to rank fixed OFFER requirements, enter bidder evidence, and produce negotiation topics without mixing static importance with live review status.
A3: =HYPERLINK("#START_HERE!A1","Start") | B3: =HYPERLINK("#DASHBOARD!A1","Dashboard") | C3: =HYPERLINK("#EVALUATION_WORKSPACE!A1","Workspace") | D3: =HYPERLINK("#NEGOTIATION_AGENDA!A1","Agenda") | E3: =HYPERLINK("#OFFER_RANKING!A1","Ranking") | F3: =HYPERLINK("#RTM_CROSSWALK!A1","Crosswalk") | G3: =HYPERLINK("#QUALITY_CHECKS!A1","Quality") | H3: =HYPERLINK("#DMAIC_AUDIT!A1","DMAIC") | I3: =HYPERLINK("#CODING_HANDOVER!A1","Handover") | J3: =HYPERLINK("#RTM_RANKING!A1","RTM Rank") | K3: =HYPERLINK("#RTM_LOOKUP!A1","RTM Lookup") | L3: =HYPERLINK("#DASHBOARD_2!A1","Filter view") | M3: =HYPERLINK("#CLUSTERS!A1","Clusters") | N3: =HYPERLINK("#TAXONOMY!A1","Taxonomy")
A5: Step | B5: Sheet | C5: Purpose | D5: Action
A6: 1 | B6: =HYPERLINK("#DASHBOARD!A1","DASHBOARD") | C6: Read ranking shape and visual summary. | D6: No editing. Use for review meetings.
A7: 2 | B7: =HYPERLINK("#EVALUATION_WORKSPACE!A1","EVALUATION_WORKSPACE") | C7: Main reviewer workspace for Bidder A/B. | D7: Enter STATUS, Technical Depth, Source/Location, negotiation flag and comments.
A8: 3 | B8: =HYPERLINK("#NEGOTIATION_AGENDA!A1","NEGOTIATION_AGENDA") | C8: Filter the automatically mirrored A/B rows. | D8: Focus on RFI / missing / negotiation / not available rows.
A9: 4 | B9: =HYPERLINK("#OFFER_RANKING!A1","OFFER_RANKING") | C9: Audit static BT importance. | D9: Filter by tier, category, dimension, phase, standard or RTM.
A10: 5 | B10: =HYPERLINK("#RTM_CROSSWALK!A1","RTM_CROSSWALK") | C10: Check OFFER↔RTM linkage. | D10: Use relation type to separate direct evidence from broad context.
A11: 6 | B11: =HYPERLINK("#QUALITY_CHECKS!A1","QUALITY_CHECKS") | C11: Monitor workbook health. | D11: Check counts, TBDs, missing sources and flags before sharing.
A12: 7 | B12: =HYPERLINK("#DMAIC_AUDIT!A1","DMAIC_AUDIT") | C12: See what changed and why. | D12: Use as change log and governance record.
A13: 8 | B13: =HYPERLINK("#CODING_HANDOVER!A1","CODING_HANDOVER") | C13: Reproduction instructions. | D13: Copy to coding agent for deterministic rebuild.
A14: 9 | B14: =HYPERLINK("#RTM_RANKING!A1","RTM_RANKING") | C14: Audit RTM-only static importance (722 requirements, identical weights, no OFFER data). | D14: Cross-check against OFFER_RANKING and RTM_CROSSWALK for consistency.
A15: 10 | B15: =HYPERLINK("#RTM_LOOKUP!A1","RTM_LOOKUP") | C15: Look up any single RTM by ID and see every field for it in one place, incl. its OFFER cross-links and (if in the priority queue) its disposition. | D15: Fastest way to answer 'what does RTM-### actually require and what counts as evidence?' during a review meeting.
A16: 11 | B16: =HYPERLINK("#DASHBOARD_2!A1","DASHBOARD_2") | C16: Pick a Domain and/or Cluster and see live counts (total, by tier, average Weighted S) for that slice. | D16: Use before assigning review workload -- see which slice is biggest before diving into row-level detail.
A17: 12 | B17: =HYPERLINK("#CLUSTERS!A1","CLUSTERS") | C17: Reference: which of the 50 OFFER items sit in each of the 8 thematic clusters (C1-C8). Filter aid only -- not a ranking. | D17: Cross-check with DASHBOARD_2's Cluster picker.
A18: 13 | B18: =HYPERLINK("#TAXONOMY!A1","TAXONOMY") | C18: Reference: Requirement Type (SYSTEM/PROJECT/SAFETY) definitions, lifecycle supergroups, and the OFFER disposition vocabulary. | D18: Read once before using the Type/Category columns or the Disposition column.
A19: BT win % Human-readable head-to-head reading of the same ranking: 100 × (wins + 0.5 × ties) / (N − 1) against every other item on the list -- same order as Weighted S, just expressed as a win rate instead of a 0-100 score. Use win % when briefing a non-technical audience; use Weighted S when you need to defend a specific number.
A23: Negotiation flag | B23: Per-bidder issue marker: negotiation, RFI, not available, clarification. | C23: Drives agenda and follow-up.
A26: Control principle: OFFER ranking is static/cold and bidder-independent. Evaluation status, depth, source location and negotiation flags are live review inputs. Do not change the weighting or 0–3 classifications during a live evaluation round unless the panel formally approves a controlled rerun.
A33: Note: EVALUATION_INPUT is retained as the previous interaction sheet for traceability. Use EVALUATION_WORKSPACE as the current main interaction sheet because it adds per-bidder comments, review indices, board topics and closure notes.
A39: How to read the colour on this page (and where the other legends live)
B40: Pale green box | C40: Supporting definition / explanation -- background you don't need to act on, just understand.
B41: Pale yellow box | C41: Operational note or caution -- something to actually do or watch for (e.g. which sheet to use).
B42: Pale blue box | C42: Cross-reference / pointer to another sheet.
A44: This page's colours are the ONLY workbook-wide, decorative kind. Everywhere else, colour carries specific meaning and has its own dedicated legend, not repeated here: STATUS colours (pink/orange/green review flags) -> COMPLIANCE_LEGEND. Weight-dimension colours (L/R/P/F/Q/LC/C headers + row heatmaps) -> WEIGHTS_METHOD. Sheet-tab colours (which of the 6 groups a tab belongs to) -> NAVIGATION_MAP or README. Cluster colours (C1-C8) -> CLUSTERS. RTM_CROSSWALK relation-type colours (Direct/Supporting/Broad/Contextual) -> the note on that sheet itself.

Sheet DASHBOARD
A1: OFFER BT dashboard | N1: Auditable chart source data
A2: Embedded plots are linked to auditable source data at the right.
A3: =HYPERLINK("#START_HERE!A1","Start") | B3: =HYPERLINK("#DASHBOARD!A1","Dashboard") | C3: =HYPERLINK("#OFFER_RANKING!A1","Ranking") | D3: =HYPERLINK("#EVALUATION_INPUT!A1","Evaluate") | E3: =HYPERLINK("#OFFER_CANONICAL!A1","Canonical") | F3: =HYPERLINK("#RTM_CROSSWALK!A1","Crosswalk") | G3: =HYPERLINK("#WEIGHTS_METHOD!A1","Method") | N3: Offer | O3: Weighted S | Q3: Tier | R3: Count | T3: Category | U3: Count | V3: Average S | X3: Rank | Y3: Weighted S | Z3: BT λ
N4: OFFER-02 | O4: 54 | Q4: T0 Gate | R4: 6 | T4: Compliance / Quality | U4: 6 | V4: 37.444 | X4: 1 | Y4: 54 | Z4: 100
A5: OFFER items 50 Canonical OFFER-01…50 | D5: Gate items 6 Admissibility precedence | G5: Primary items 10 Top non-gate band | J5: Mean Weighted S 28.9 Frozen composite | N5: OFFER-48 | O5: 42.667 | Q5: T1 Primary | R5: 10 | T5: Reliability / RAM / Service | U5: 8 | V5: 33.833 | X5: 2 | Y5: 42.667 | Z5: 79.437
N6: OFFER-01 | O6: 32 | Q6: T2 Secondary | R6: 16 | T6: Controls / Software / Management | U6: 10 | V6: 30.067 | X6: 3 | Y6: 32 | Z6: 48.911
N7: OFFER-03 | O7: 32 | Q7: T3 Contextual | R7: 18 | T7: Performance / Process / Utilities | U7: 15 | V7: 27.933 | X7: 4 | Y7: 32 | Z7: 48.911
N8: OFFER-47 | O8: 32 | T8: Configuration / Layout / Support | U8: 11 | V8: 20.848 | X8: 5 | Y8: 32 | Z8: 48.911
N9: OFFER-49 | O9: 32 | X9: 6 | Y9: 32 | Z9: 48.911
N10: OFFER-09 | O10: 55.667 | X10: 7 | Y10: 55.667 | Z10: 32.555
N11: OFFER-42 | O11: 46.333 | X11: 8 | Y11: 46.333 | Z11: 28.053
N12: OFFER-20 | O12: 46 | X12: 9 | Y12: 46 | Z12: 22.688
N13: OFFER-34 | O13: 46 | X13: 10 | Y13: 46 | Z13: 22.688
N14: OFFER-29 | O14: 45 | X14: 11 | Y14: 45 | Z14: 18.544
N15: OFFER-04 | O15: 44 | X15: 12 | Y15: 44 | Z15: 15.285
N16: OFFER-05 | O16: 44 | X16: 13 | Y16: 44 | Z16: 15.285
N17: OFFER-27 | O17: 41.333 | X17: 14 | Y17: 41.333 | Z17: 12.684
N18: OFFER-33 | O18: 38.667 | X18: 15 | Y18: 38.667 | Z18: 10.584
X19: 16 | Y19: 38.667 | Z19: 10.584
X20: 17 | Y20: 36 | Z20: 8.369
X21: 18 | Y21: 36 | Z21: 8.369
X22: 19 | Y22: 35.667 | Z22: 7.046
X23: 20 | Y23: 32.667 | Z23: 5.946
X24: 21 | Y24: 32.667 | Z24: 5.946
X25: 22 | Y25: 32 | Z25: 4.756
X26: 23 | Y26: 32 | Z26: 4.756
X27: 24 | Y27: 31.667 | Z27: 4.028
X28: 25 | Y28: 29.333 | Z28: 3.607
X29: 26 | Y29: 26.667 | Z29: 3.23
X30: 27 | Y30: 24 | Z30: 2.193
... X50: 47 | Y50: 14.333 | Z50: 0.219
A51: BT MLE converged in 301 iterations (final relative change 9.51E-11). This convergence confirms numerical stability; it does not create new engineering judgement. | X51: 48 | Y51: 12 | Z51: 0.181
X52: 49 | Y52: 10.667 | Z52: 0.147
X53: 50 | Y53: 6.333 | Z53: 0.117
A56: Why does the Weighted S line spike at item 7, above item 1? Ranks 1-6 are the six T0 Gate items -- pinned to the TOP of the official rank by gate precedence, regardless of their own S score (54 / 42.7 / 32 / 32 / 32 / 32 -- all comparatively low). Rank 7 is the first non-gated item, OFFER-09 "LN2 Techno-Economic Evaluation (CAPEX/OPEX)" (T1 Primary), and it holds the single highest Weighted S of all 50 OFFER items: 55.67 -- higher even than the #1-ranked gate item. So the S-line dips through the low-S gate items, then jumps sharply upward exactly where the top-value item finally appears. This is expected behaviour, not a data error: gate items must rank first by policy (pass/fail compliance), independent of how much technical/value weight they carry -- see WEIGHTS_METHOD for the gate-precedence rule.

Sheet DASHBOARD_2
A1: Filter view — by Domain or Cluster
A2: Pick a Domain and/or a Cluster below; the counts update live. This is a filter aid over the same 722 RTMs in RTM_RANKING -- for row-level detail, use RTM_RANKING's own AutoFilter after picking your slice here, or open RTM_LOOKUP for one specific RTM.
A3: =HYPERLINK("#START_HERE!A1","Start") | B3: =HYPERLINK("#DASHBOARD!A1","Dashboard") | C3: =HYPERLINK("#RTM_LOOKUP!A1","RTM Lookup") | D3: =HYPERLINK("#DASHBOARD_2!A1","Filter view") | E3: =HYPERLINK("#RTM_REVIEW_QUEUE!A1","Queue") | F3: =HYPERLINK("#RTM_RANKING!A1","Ranking") | G3: =HYPERLINK("#DOMAIN_SUMMARY!A1","Domains") | H3: =HYPERLINK("#CLUSTERS!A1","Clusters") | I3: =HYPERLINK("#TAXONOMY!A1","Taxonomy")
A5: Domain | B5: (ALL) | C5: Domain criteria (helper): | D5: =IF(B5="(ALL)","*",B5)
A6: Cluster | B6: (ALL) | C6: Cluster criteria (helper): | D6: =IF(B6="(ALL)","*","*"&B6&" —*")
A8: Live counts for this slice
A9: Matching RTMs | B9: =COUNTIFS(RTM_RANKING!$E$6:$E$728,$D$5,RTM_RANKING!$I$6:$I$728,$D$6)
A10: of which T0 Gate | B10: =COUNTIFS(RTM_RANKING!$E$6:$E$728,$D$5,RTM_RANKING!$I$6:$I$728,$D$6,RTM_RANKING!$D$6:$D$728,"T0 Gate")
A11: of which T1 Primary | B11: =COUNTIFS(RTM_RANKING!$E$6:$E$728,$D$5,RTM_RANKING!$I$6:$I$728,$D$6,RTM_RANKING!$D$6:$D$728,"T1 Primary")
A12: of which T2 Secondary | B12: =COUNTIFS(RTM_RANKING!$E$6:$E$728,$D$5,RTM_RANKING!$I$6:$I$728,$D$6,RTM_RANKING!$D$6:$D$728,"T2 Secondary")
A13: of which T3 Contextual | B13: =COUNTIFS(RTM_RANKING!$E$6:$E$728,$D$5,RTM_RANKING!$I$6:$I$728,$D$6,RTM_RANKING!$D$6:$D$728,"T3 Contextual")
A14: Average Weighted S | B14: =IFERROR(ROUND(AVERAGEIFS(RTM_RANKING!$V$6:$V$728,RTM_RANKING!$E$6:$E$728,$D$5,RTM_RANKING!$I$6:$I$728,$D$6),2),"n/a")
A16: RTM-side charts (mirrors DASHBOARD's OFFER-side charts) + crosswalk coverage
A17: Chart data below is auto-computed (COUNTIF/COUNTIFS off RTM_RANKING) -- not for manual editing.
A18: Tier | B18: RTM count | D18: Coverage | E18: RTM count
A19: T0 Gate | B19: =COUNTIF(RTM_RANKING!$D$6:$D$727,"T0 Gate") | D19: Linked | E19: =COUNTIFS(RTM_RANKING!$AG$6:$AG$727,"<>Not linked to an OFFER item",RTM_RANKING!$AG$6:$AG$727,"<>")
A20: T1 Primary | B20: =COUNTIF(RTM_RANKING!$D$6:$D$727,"T1 Primary") | D20: Not linked | E20: =COUNTIF(RTM_RANKING!$AG$6:$AG$727,"Not linked to an OFFER item")
A21: T2 Secondary | B21: =COUNTIF(RTM_RANKING!$D$6:$D$727,"T2 Secondary")
A22: T3 Contextual | B22: =COUNTIF(RTM_RANKING!$D$6:$D$727,"T3 Contextual") | D22: Tier | E22: Linked | F22: Not linked
D23: T0 Gate | E23: =COUNTIFS(RTM_RANKING!$D$6:$D$727,"T0 Gate",RTM_RANKING!$AG$6:$AG$727,"<>Not linked to an OFFER item",RTM_RANKING!$AG$6:$AG$727,"<>") | F23: =COUNTIFS(RTM_RANKING!$D$6:$D$727,"T0 Gate",RTM_RANKING!$AG$6:$AG$727,"Not linked to an OFFER item")
D24: T1 Primary | E24: =COUNTIFS(RTM_RANKING!$D$6:$D$727,"T1 Primary",RTM_RANKING!$AG$6:$AG$727,"<>Not linked to an OFFER item",RTM_RANKING!$AG$6:$AG$727,"<>") | F24: =COUNTIFS(RTM_RANKING!$D$6:$D$727,"T1 Primary",RTM_RANKING!$AG$6:$AG$727,"Not linked to an OFFER item")
D25: T2 Secondary | E25: =COUNTIFS(RTM_RANKING!$D$6:$D$727,"T2 Secondary",RTM_RANKING!$AG$6:$AG$727,"<>Not linked to an OFFER item",RTM_RANKING!$AG$6:$AG$727,"<>") | F25: =COUNTIFS(RTM_RANKING!$D$6:$D$727,"T2 Secondary",RTM_RANKING!$AG$6:$AG$727,"Not linked to an OFFER item")
D26: T3 Contextual | E26: =COUNTIFS(RTM_RANKING!$D$6:$D$727,"T3 Contextual",RTM_RANKING!$AG$6:$AG$727,"<>Not linked to an OFFER item",RTM_RANKING!$AG$6:$AG$727,"<>") | F26: =COUNTIFS(RTM_RANKING!$D$6:$D$727,"T3 Contextual",RTM_RANKING!$AG$6:$AG$727,"Not linked to an OFFER item")
A28: Coverage read: 293 of 722 RTMs (41%) have a direct RTM_CROSSWALK link to at least one OFFER item; 429 (59%) do not. That is expected, not a defect -- OFFER items are the bidder's own response document, so many RTMs (procedural/administrative requirements, or ones no OFFER section happens to address in prose) will never get a direct textual link even in a fully compliant bid. The number worth watching is the T0 Gate row below: 21 of 43 T0 Gate RTMs (49%) have NO direct OFFER link -- for a Gate requirement specifically, that means compliance for that item is resting on EVALUATION_WORKSPACE's manual review, not on a traceable OFFER-text citation. Worth a reviewer pass on just those 21 before sign-off, not a workbook defect to fix.
A95: Review-completion rollup (RTM_REVIEW_QUEUE)
A96: 0 of 289 priority-queue RTMs (0%) have a Disposition recorded (anything other than blank/TBD); 289 (100%) are still awaiting a reviewer decision. This is the single project-level 'how far along is this evaluation' number the per-item STATUS/Disposition fields never rolled up into one place before -- same pattern as the crosswalk-coverage callout above, applied to review completion instead of RTM<->OFFER linkage. Re-run build_workbook_v20.py's Section 7 (or a future refresh) any time RTM_REVIEW_QUEUE!Disposition values change, to keep this number current -- it is a snapshot, not a live formula, so it can drift if the workbook is edited without a rebuild.

Sheet RTM_LOOKUP
A1: RTM Lookup — enter any RTM ID
A2: Type an RTM ID (e.g. RTM-693) in the yellow box. Every field for that requirement pulls in below, across all 722 canonical RTMs -- not just the 289 in the priority queue.
A3: =HYPERLINK("#START_HERE!A1","Start") | B3: =HYPERLINK("#DASHBOARD!A1","Dashboard") | C3: =HYPERLINK("#RTM_LOOKUP!A1","RTM Lookup") | D3: =HYPERLINK("#DASHBOARD_2!A1","Filter view") | E3: =HYPERLINK("#RTM_REVIEW_QUEUE!A1","Queue") | F3: =HYPERLINK("#RTM_RANKING!A1","Ranking") | G3: =HYPERLINK("#DOMAIN_SUMMARY!A1","Domains") | H3: =HYPERLINK("#CLUSTERS!A1","Clusters") | I3: =HYPERLINK("#TAXONOMY!A1","Taxonomy")
A5: RTM ID: | B5: RTM-693 | C5: Format: RTM-### (3 digits, e.g. RTM-001, RTM-693). If the box below shows #N/A, check the ID exists on RTM_RANKING.
A7: Field | B7: Value
A8: Rank (of 722) | B8: =IFERROR(INDEX(RTM_RANKING!$A$6:$A$728,MATCH($B$5,RTM_RANKING!$B$6:$B$728,0)),"— RTM ID not found —")
A9: Gate (T0?) | B9: =IFERROR(INDEX(RTM_RANKING!$C$6:$C$728,MATCH($B$5,RTM_RANKING!$B$6:$B$728,0)),"— RTM ID not found —")
A10: Tier | B10: =IFERROR(INDEX(RTM_RANKING!$D$6:$D$728,MATCH($B$5,RTM_RANKING!$B$6:$B$728,0)),"— RTM ID not found —")
A11: Domain | B11: =IFERROR(INDEX(RTM_RANKING!$E$6:$E$728,MATCH($B$5,RTM_RANKING!$B$6:$B$728,0)),"— RTM ID not found —")
A12: Requirement Type | B12: =IFERROR(INDEX(RTM_RANKING!$F$6:$F$728,MATCH($B$5,RTM_RANKING!$B$6:$B$728,0)),"— RTM ID not found —")
A13: Category | B13: =IFERROR(INDEX(RTM_RANKING!$G$6:$G$728,MATCH($B$5,RTM_RANKING!$B$6:$B$728,0)),"— RTM ID not found —")
A14: Subcategory | B14: =IFERROR(INDEX(RTM_RANKING!$H$6:$H$728,MATCH($B$5,RTM_RANKING!$B$6:$B$728,0)),"— RTM ID not found —")
A15: Cluster | B15: =IFERROR(INDEX(RTM_RANKING!$I$6:$I$728,MATCH($B$5,RTM_RANKING!$B$6:$B$728,0)),"— RTM ID not found —")
A16: PDF page | B16: =IFERROR(INDEX(RTM_RANKING!$J$6:$J$728,MATCH($B$5,RTM_RANKING!$B$6:$B$728,0)),"— RTM ID not found —")
A17: Section | B17: =IFERROR(INDEX(RTM_RANKING!$K$6:$K$728,MATCH($B$5,RTM_RANKING!$B$6:$B$728,0)),"— RTM ID not found —")
A18: Section title | B18: =IFERROR(INDEX(RTM_RANKING!$L$6:$L$728,MATCH($B$5,RTM_RANKING!$B$6:$B$728,0)),"— RTM ID not found —")
A19: Shall statement | B19: =IFERROR(INDEX(RTM_RANKING!$M$6:$M$728,MATCH($B$5,RTM_RANKING!$B$6:$B$728,0)),"— RTM ID not found —")
A20: Full verbatim requirement | B20: =IFERROR(INDEX(RTM_RANKING!$N$6:$N$728,MATCH($B$5,RTM_RANKING!$B$6:$B$728,0)),"— RTM ID not found —")
A21: Weighted S | B21: =IFERROR(INDEX(RTM_RANKING!$V$6:$V$728,MATCH($B$5,RTM_RANKING!$B$6:$B$728,0)),"— RTM ID not found —")
A22: BT Win % | B22: =IFERROR(INDEX(RTM_RANKING!$W$6:$W$728,MATCH($B$5,RTM_RANKING!$B$6:$B$728,0)),"— RTM ID not found —")
A23: Primary dimension | B23: =IFERROR(INDEX(RTM_RANKING!$Y$6:$Y$728,MATCH($B$5,RTM_RANKING!$B$6:$B$728,0)),"— RTM ID not found —")
A24: Actual explicit code / standard | B24: =IFERROR(INDEX(RTM_RANKING!$AA$6:$AA$728,MATCH($B$5,RTM_RANKING!$B$6:$B$728,0)),"— RTM ID not found —")
A25: Evidence / measurability | B25: =IFERROR(INDEX(RTM_RANKING!$AC$6:$AC$728,MATCH($B$5,RTM_RANKING!$B$6:$B$728,0)),"— RTM ID not found —")
A26: Explicit deliverable / proof | B26: =IFERROR(INDEX(RTM_RANKING!$AD$6:$AD$728,MATCH($B$5,RTM_RANKING!$B$6:$B$728,0)),"— RTM ID not found —")
A27: Applicable phase(s) | B27: =IFERROR(INDEX(RTM_RANKING!$AE$6:$AE$728,MATCH($B$5,RTM_RANKING!$B$6:$B$728,0)),"— RTM ID not found —")
A28: Evidence basis / review | B28: =IFERROR(INDEX(RTM_RANKING!$AF$6:$AF$728,MATCH($B$5,RTM_RANKING!$B$6:$B$728,0)),"— RTM ID not found —")
A29: Linked OFFER items (crosswalk) | B29: =IFERROR(INDEX(RTM_RANKING!$AG$6:$AG$728,MATCH($B$5,RTM_RANKING!$B$6:$B$728,0)),"— RTM ID not found —")
A30: Note: if the verbatim text above still looks cut off (a handful of items run to 25+ bullets), the full text is always in RTM_RANKING!N for this RTM ID, or widen row 20 further.
A31: Reviewer disposition for this RTM (from RTM_REVIEW_QUEUE, if it's in the priority subset)
A32: Disposition | B32: =IFERROR(INDEX(RTM_REVIEW_QUEUE!$U$6:$U$294,MATCH($B$5,RTM_REVIEW_QUEUE!$B$6:$B$294,0)),"— not in the priority queue —")
A33: Comments | B33: =IFERROR(INDEX(RTM_REVIEW_QUEUE!$V$6:$V$294,MATCH($B$5,RTM_REVIEW_QUEUE!$B$6:$B$294,0)),"— not in the priority queue —")
A34: Cross-link / check to perform | B34: =IFERROR(INDEX(RTM_REVIEW_QUEUE!$W$6:$W$294,MATCH($B$5,RTM_REVIEW_QUEUE!$B$6:$B$294,0)),"— not in the priority queue —")

Sheet COMPLIANCE_LEGEND
A1: Compliance status legend
A2: Dropdown conventions used in EVALUATION_INPUT.
A3: =HYPERLINK("#START_HERE!A1","Start") | B3: =HYPERLINK("#DASHBOARD!A1","Dashboard") | C3: =HYPERLINK("#OFFER_RANKING!A1","Ranking") | D3: =HYPERLINK("#EVALUATION_INPUT!A1","Evaluate") | E3: =HYPERLINK("#OFFER_CANONICAL!A1","Canonical") | F3: =HYPERLINK("#RTM_CROSSWALK!A1","Crosswalk") | G3: =HYPERLINK("#WEIGHTS_METHOD!A1","Method")
A5: Status | B5: Definition | C5: Example | D5: Deviation | E5: Next steps | F5: Who resolves
A6: OK | B6: Fulfills requirements | C6: Requested: 100, Provided: 500 | D6: +400 (overperformance) | E6: Nothing
A7: OK/Minor | B7: Either OK or minor; evaluated as very low risk and can be closed | E7: Nothing
A8: NOK | B8: Does not fulfill requirements | C8: Requested: 4, Provided: 3 | D8: -1 (25% shortfall) | E8: Decide whether to enforce or relax original requirement
A9: MISS | B9: Required information missing | C9: No mention about it | D9: Unknown | E9: Follow-up needed
A10: Minor disc. | B10: Does not fully fulfill requirements, but can be resolved during contract performance | E10: Likely solvable without management intervention | F10: ACR level
A11: Major disc. | B11: Seems like a NOK but can be resolved during contract performance | E11: Likely solvable with management intervention | F11: Management level
A12: ERROR | B12: Misinterpretation of requirement | C12: Response does not match intent | D12: Major error | E12: Clarify with supplier
A13: TBD | B13: Not yet evaluated (default state) | E13: Evaluate
A16: How to read the colours in this workbook
A17: STATUS (this table, above) | B17: Green/pink/orange/purple/yellow, per-value as shown above. | D17: EVALUATION_WORKSPACE!Q6:Q55, W6:W55 (live, driven by the dropdown) · QUALITY_CHECKS!D6:D17 (health-check OK/CHECK/OPEN)
A18: Tier (T0 Gate / T1 / T2 / T3) | B18: Pale red / orange / yellow / green -- a SEPARATE colour system from STATUS, do not read them against each other. | D18: EVALUATION_WORKSPACE!B6:B55 and every Tier column on RTM_RANKING, OFFER_RANKING, RTM_REVIEW_QUEUE
A19: Cluster (C1-C8) | B19: New (Phase 9): soft blue/teal/lavender/mauve/tan tones, one per cluster, deliberately kept out of the STATUS and Tier hue families so none of the three systems gets misread against another. | D19: CLUSTERS!A6:A13 (exact) · RTM_RANKING!I6:I727 and RTM_REVIEW_QUEUE!G6:G294 (conditional, matches the cluster id inside the longer cell text, incl. "Inferred:" rows)
A20: Soft cream fill = safe to type/select here | B20: New (Phase 9): manual-entry cells that had no visual cue before a value was entered now carry a light cream base fill, so the invitation to edit is visible up front, not just after a STATUS is picked. White/no-fill cells elsewhere are formulas or reference text -- not meant to be edited directly. | D20: EVALUATION_WORKSPACE!R,S,U,X,Y,AA,AD,AE,AF (rows 6-55). v20: extended to RTM_REVIEW_QUEUE!Comments and NEGOTIATION_AGENDA!Reviewer Comment, plus a new Comment column added to QUALITY_CHECKS (previously had none). DMAIC_AUDIT/AUDIT_NOTES deliberately left as-is -- both are structured audit logs, not live reviewer-input sheets.
A21: Technical Depth (A_/B_, EVALUATION_WORKSPACE!R,X) | B21: Soft pink=0.4 declarative / soft orange=0.7 partial / soft green=1.0 fully substantiated -- same weak->strong direction as STATUS's pink/orange/green, deliberately paler so it doesn't read as an actual STATUS value next to the STATUS column beside it.
A23: Primary vs. Supporting RTM, and Review flag -- formal definitions
A24: Both fields are hand-curated per OFFER item (OFFER_CANONICAL!primary_rtm_ids / supporting_context_rtm_ids / review_flag), not formula- or rule-derived -- no code branch assigns either. Documented here per GBO's explicit request so this is captured rather than left inferred.
A26: Field | B26: Definition | C26: Example
A27: Primary RTM(s) | B27: The RTM(s) that an OFFER item's response text is actually, centrally answering -- the requirement(s) the offer was written to address. | C27: OFFER-01's primary RTM is RTM-001 (the general-responsibility clause its text directly confirms).
A28: Supporting RTM(s) | B28: RTMs in the same contract section as the OFFER item that get pulled in as context, but are not what the offer text is centrally about -- background/section-mates, not the primary evidence basis. | C28: Section-mates of RTM-001 under §4.13 that are relevant context but not individually answered.
A29: Review flag | B29: Reviewer note on whether the Primary/Supporting split (or the crosswalk coverage generally) needs a second look before being trusted as-is. Standardised (v20) to 5 controlled values -- see the review_flag dropdown on OFFER_CANONICAL/EVALUATION_WORKSPACE/OFFER_RANKING for the live list and colours. | C29: "Review — breadth" = the OFFER text plausibly covers more RTMs than the direct link captures.

Sheet EVALUATION_WORKSPACE
A1: Evaluation workspace — 2 bidders, evidence first
A2: Main interaction sheet. The static rank is read-only; reviewer input starts at the STATUS columns for Bidder A and Bidder B.
A3: =HYPERLINK("#START_HERE!A1","Start") | B3: =HYPERLINK("#DASHBOARD!A1","Dashboard") | C3: =HYPERLINK("#EVALUATION_WORKSPACE!A1","Workspace") | D3: =HYPERLINK("#NEGOTIATION_AGENDA!A1","Agenda") | E3: =HYPERLINK("#OFFER_RANKING!A1","Ranking") | F3: =HYPERLINK("#RTM_CROSSWALK!A1","Crosswalk") | G3: =HYPERLINK("#QUALITY_CHECKS!A1","Quality") | H3: =HYPERLINK("#DMAIC_AUDIT!A1","DMAIC") | I3: =HYPERLINK("#CODING_HANDOVER!A1","Handover")
AC4: Formula-driven -- fills itself in once A_STATUS/B_STATUS are set; nothing fabricated while both are TBD.
A5: Rank | B5: Tier | C5: OFFER ID | D5: Title | E5: Section | F5: Category | G5: Primary Dim | H5: Weighted S | I5: BT Win % | J5: Gate | K5: Evidence / measurability | L5: Explicit deliverable / proof | M5: Applicable phase(s) | N5: Primary RTMs | O5: Supporting RTMs | P5: Review flag | Q5: A_STATUS | R5: A_Technical Depth | S5: A_Source / Location | T5: A_Negotiation | U5: A_Reviewer Comment | V5: A_Review Index | W5: B_STATUS | X5: B_Technical Depth | Y5: B_Source / Location | Z5: B_Negotiation | AA5: B_Reviewer Comment | AB5: B_Review Index | AC5: Z_comment (auto A vs B synthesis) | AD5: Board / Negotiation Topic | AE5: Owner | AF5: Closure / Decision Note
A6: 1 | B6: T0 Gate | C6: OFFER-02 | D6: Assumptions, Deviations & Additions Register | E6: §4.1 | F6: Compliance / Quality | G6: Reliability | H6: 54 | I6: 100 | J6: Yes | K6: Submit and review the named deliverable with RTM traceability and approval status; RAM/maintenance substantiation and recovery/failure-response evidence; Document review, inspection, certification, audit or traceable QC record | L6: Offer response: Assumptions, Deviations & Additions Register | M6: L0 Tender / Offer; L1 Conceptual Design; L2 Detailed Design | N6: RTM-004 | O6: RTM-001..RTM-003 | P6: OK | Q6: TBD | V6: =IF(Q6="TBD","",H6*R6*IF(Q6="OK",1,IF(Q6="OK/Minor",0.85,IF(Q6="Minor disc.",0.7,IF(Q6="Major disc.",0.45,IF(Q6="MISS",0.25,0)))))) | W6: TBD | AB6: =IF(W6="TBD","",H6*X6*IF(W6="OK",1,IF(W6="OK/Minor",0.85,IF(W6="Minor disc.",0.7,IF(W6="Major disc.",0.45,IF(W6="MISS",0.25,0)))))) | AC6: =IF(AND(Q6="TBD",W6="TBD"),"Not yet evaluated — awaiting bidder review.",IF(Q6="TBD",CONCATENATE("Bidder B: ",W6," — ",IF(AA6="","(no comment)",AA6)," | Bidder A not yet evaluated."),IF(W6="TBD",CONCATENATE("Bidder A: ",Q6," — ",IF(U6="","(no comment)",U6)," | Bidder B not yet evaluated."),CONCATENATE("Bidder A: ",Q6," — ",IF(U6="","(no comment)",U6)," || Bidder B: ",W6," — ",IF(AA6="","(no comment)",AA6)," | ",IF(Q6=W6,"Comparable disposition.","Diverging disposition — flag for negotiation.")))))
A7: 2 | B7: T0 Gate | C7: OFFER-48 | D7: Detailed Quality Control Procedures | E7: §8.1.3.1 | F7: Compliance / Quality | G7: Safety / Legal | H7: 42.6667 | I7: 97.9592 | J7: Yes | K7: Submit and review the named deliverable with RTM traceability and approval status; Document review, inspection, certification, audit or traceable QC record; Conformity/safety assessment, certification and approved safety evidence | L7: Offer response: Detailed Quality Control Procedures; Quality Assurance Plan (QAP) | M7: L0 Tender / Offer; L1 Conceptual Design; L2 Detailed Design; L3 Procurement & Manufacturing / FAT; L4 Installation; L5 Standalone Commissioning; L6 Site Acceptance Testing | N7: RTM-650..RTM-652 | P7: OK | Q7: TBD | V7: =IF(Q7="TBD","",H7*R7*IF(Q7="OK",1,IF(Q7="OK/Minor",0.85,IF(Q7="Minor disc.",0.7,IF(Q7="Major disc.",0.45,IF(Q7="MISS",0.25,0)))))) | W7: TBD | AB7: =IF(W7="TBD","",H7*X7*IF(W7="OK",1,IF(W7="OK/Minor",0.85,IF(W7="Minor disc.",0.7,IF(W7="Major disc.",0.45,IF(W7="MISS",0.25,0)))))) | AC7: =IF(AND(Q7="TBD",W7="TBD"),"Not yet evaluated — awaiting bidder review.",IF(Q7="TBD",CONCATENATE("Bidder B: ",W7," — ",IF(AA7="","(no comment)",AA7)," | Bidder A not yet evaluated."),IF(W7="TBD",CONCATENATE("Bidder A: ",Q7," — ",IF(U7="","(no comment)",U7)," | Bidder B not yet evaluated."),CONCATENATE("Bidder A: ",Q7," — ",IF(U7="","(no comment)",U7)," || Bidder B: ",W7," — ",IF(AA7="","(no comment)",AA7)," | ",IF(Q7=W7,"Comparable disposition.","Diverging disposition — flag for negotiation.")))))
A8: 3 | B8: T0 Gate | C8: OFFER-01 | D8: Tender Compliance Confirmation | E8: §4.1 | F8: Compliance / Quality | G8: Safety / Legal | H8: 32 | I8: 92.8571 | J8: Yes | K8: Submit and review the named deliverable with RTM traceability and approval status; Document review, inspection, certification, audit or traceable QC record; Conformity/safety assessment, certification and approved safety evidence | L8: Offer response: Tender Compliance Confirmation | M8: L0 Tender / Offer; L1 Conceptual Design; L2 Detailed Design | N8: RTM-001; RTM-003 | O8: RTM-002; RTM-004 | P8: OK | Q8: TBD | V8: =IF(Q8="TBD","",H8*R8*IF(Q8="OK",1,IF(Q8="OK/Minor",0.85,IF(Q8="Minor disc.",0.7,IF(Q8="Major disc.",0.45,IF(Q8="MISS",0.25,0)))))) | W8: TBD | AB8: =IF(W8="TBD","",H8*X8*IF(W8="OK",1,IF(W8="OK/Minor",0.85,IF(W8="Minor disc.",0.7,IF(W8="Major disc.",0.45,IF(W8="MISS",0.25,0)))))) | AC8: =IF(AND(Q8="TBD",W8="TBD"),"Not yet evaluated — awaiting bidder review.",IF(Q8="TBD",CONCATENATE("Bidder B: ",W8," — ",IF(AA8="","(no comment)",AA8)," | Bidder A not yet evaluated."),IF(W8="TBD",CONCATENATE("Bidder A: ",Q8," — ",IF(U8="","(no comment)",U8)," | Bidder B not yet evaluated."),CONCATENATE("Bidder A: ",Q8," — ",IF(U8="","(no comment)",U8)," || Bidder B: ",W8," — ",IF(AA8="","(no comment)",AA8)," | ",IF(Q8=W8,"Comparable disposition.","Diverging disposition — flag for negotiation.")))))
A9: 4 | B9: T0 Gate | C9: OFFER-03 | D9: Integrated Technical Proposal & Execution Strategy | E9: §4.1 | F9: Compliance / Quality | G9: Safety / Legal | H9: 32 | I9: 92.8571 | J9: Yes | K9: Submit and review the named deliverable with RTM traceability and approval status; Document review, inspection, certification, audit or traceable QC record; Conformity/safety assessment, certification and approved safety evidence | L9: Offer response: Integrated Technical Proposal & Execution Strategy | M9: L0 Tender / Offer; L1 Conceptual Design; L2 Detailed Design | N9: RTM-002 | O9: RTM-001; RTM-003..RTM-004 | P9: OK | Q9: TBD | V9: =IF(Q9="TBD","",H9*R9*IF(Q9="OK",1,IF(Q9="OK/Minor",0.85,IF(Q9="Minor disc.",0.7,IF(Q9="Major disc.",0.45,IF(Q9="MISS",0.25,0)))))) | W9: TBD | AB9: =IF(W9="TBD","",H9*X9*IF(W9="OK",1,IF(W9="OK/Minor",0.85,IF(W9="Minor disc.",0.7,IF(W9="Major disc.",0.45,IF(W9="MISS",0.25,0)))))) | AC9: =IF(AND(Q9="TBD",W9="TBD"),"Not yet evaluated — awaiting bidder review.",IF(Q9="TBD",CONCATENATE("Bidder B: ",W9," — ",IF(AA9="","(no comment)",AA9)," | Bidder A not yet evaluated."),IF(W9="TBD",CONCATENATE("Bidder A: ",Q9," — ",IF(U9="","(no comment)",U9)," | Bidder B not yet evaluated."),CONCATENATE("Bidder A: ",Q9," — ",IF(U9="","(no comment)",U9)," || Bidder B: ",W9," — ",IF(AA9="","(no comment)",AA9)," | ",IF(Q9=W9,"Comparable disposition.","Diverging disposition — flag for negotiation.")))))
A10: 5 | B10: T0 Gate | C10: OFFER-47 | D10: Quality Assurance Program (QAP) Definition | E10: §8 | F10: Compliance / Quality | G10: Safety / Legal | H10: 32 | I10: 92.8571 | J10: Yes | K10: Submit and review the named deliverable with RTM traceability and approval status; Document review, inspection, certification, audit or traceable QC record; Conformity/safety assessment, certification and approved safety evidence | L10: Offer response: Quality Assurance Program (QAP) Definition; Quality Assurance Plan (QAP) | M10: L0 Tender / Offer; L1 Conceptual Design; L2 Detailed Design; L3 Procurement & Manufacturing / FAT; L4 Installation; L5 Standalone Commissioning; L6 Site Acceptance Testing | N10: RTM-642 | O10: RTM-648..RTM-652 | P10: OK — Review breadth | Q10: TBD | V10: =IF(Q10="TBD","",H10*R10*IF(Q10="OK",1,IF(Q10="OK/Minor",0.85,IF(Q10="Minor disc.",0.7,IF(Q10="Major disc.",0.45,IF(Q10="MISS",0.25,0)))))) | W10: TBD | AB10: =IF(W10="TBD","",H10*X10*IF(W10="OK",1,IF(W10="OK/Minor",0.85,IF(W10="Minor disc.",0.7,IF(W10="Major disc.",0.45,IF(W10="MISS",0.25,0)))))) | AC10: =IF(AND(Q10="TBD",W10="TBD"),"Not yet evaluated — awaiting bidder review.",IF(Q10="TBD",CONCATENATE("Bidder B: ",W10," — ",IF(AA10="","(no comment)",AA10)," | Bidder A not yet evaluated."),IF(W10="TBD",CONCATENATE("Bidder A: ",Q10," — ",IF(U10="","(no comment)",U10)," | Bidder B not yet evaluated."),CONCATENATE("Bidder A: ",Q10," — ",IF(U10="","(no comment)",U10)," || Bidder B: ",W10," — ",IF(AA10="","(no comment)",AA10)," | ",IF(Q10=W10,"Comparable disposition.","Diverging disposition — flag for negotiation.")))))
A11: 6 | B11: T0 Gate | C11: OFFER-49 | D11: Codes, Standards & Compliance Framework | E11: §9 | F11: Compliance / Quality | G11: Safety / Legal | H11: 32 | I11: 92.8571 | J11: Yes | K11: Submit and review the named deliverable with RTM traceability and approval status; Witnessed FAT/SAT/commissioning test against stated acceptance criteria; Conformity/safety assessment, certification and approved safety evidence | L11: Offer response: Codes, Standards & Compliance Framework; List / register / matrix | M11: L0 Tender / Offer; L3 Procurement & Manufacturing / FAT; L1 Conceptual Design; L2 Detailed Design; L4 Installation; L5 Standalone Commissioning; L6 Site Acceptance Testing | N11: RTM-687..RTM-688 | O11: RTM-689..RTM-705 | P11: OK — Review breadth | Q11: TBD | V11: =IF(Q11="TBD","",H11*R11*IF(Q11="OK",1,IF(Q11="OK/Minor",0.85,IF(Q11="Minor disc.",0.7,IF(Q11="Major disc.",0.45,IF(Q11="MISS",0.25,0)))))) | W11: TBD | AB11: =IF(W11="TBD","",H11*X11*IF(W11="OK",1,IF(W11="OK/Minor",0.85,IF(W11="Minor disc.",0.7,IF(W11="Major disc.",0.45,IF(W11="MISS",0.25,0)))))) | AC11: =IF(AND(Q11="TBD",W11="TBD"),"Not yet evaluated — awaiting bidder review.",IF(Q11="TBD",CONCATENATE("Bidder B: ",W11," — ",IF(AA11="","(no comment)",AA11)," | Bidder A not yet evaluated."),IF(W11="TBD",CONCATENATE("Bidder A: ",Q11," — ",IF(U11="","(no comment)",U11)," | Bidder B not yet evaluated."),CONCATENATE("Bidder A: ",Q11," — ",IF(U11="","(no comment)",U11)," || Bidder B: ",W11," — ",IF(AA11="","(no comment)",AA11)," | ",IF(Q11=W11,"Comparable disposition.","Diverging disposition — flag for negotiation.")))))
A12: 7 | B12: T1 Primary | C12: OFFER-09 | D12: LN2 Techno-Economic Evaluation (CAPEX/OPEX) | E12: §4.2.5 | F12: Performance / Process / Utilities | G12: Reliability | H12: 55.6667 | I12: 87.7551 | J12: No | K12: Submit and review the named deliverable with RTM traceability and approval status; Calculation/model plus calibrated measurement or recorded trend; Functional design/configuration review and sequence/interface demonstration | L12: Offer response: LN2 Techno-Economic Evaluation (CAPEX/OPEX) | M12: L0 Tender / Offer; PAC / Handover; L1 Conceptual Design; L2 Detailed Design | O12: RTM-045..RTM-047 | P12: Review — accept context | Q12: TBD | V12: =IF(Q12="TBD","",H12*R12*IF(Q12="OK",1,IF(Q12="OK/Minor",0.85,IF(Q12="Minor disc.",0.7,IF(Q12="Major disc.",0.45,IF(Q12="MISS",0.25,0)))))) | W12: TBD | AB12: =IF(W12="TBD","",H12*X12*IF(W12="OK",1,IF(W12="OK/Minor",0.85,IF(W12="Minor disc.",0.7,IF(W12="Major disc.",0.45,IF(W12="MISS",0.25,0)))))) | AC12: =IF(AND(Q12="TBD",W12="TBD"),"Not yet evaluated — awaiting bidder review.",IF(Q12="TBD",CONCATENATE("Bidder B: ",W12," — ",IF(AA12="","(no comment)",AA12)," | Bidder A not yet evaluated."),IF(W12="TBD",CONCATENATE("Bidder A: ",Q12," — ",IF(U12="","(no comment)",U12)," | Bidder B not yet evaluated."),CONCATENATE("Bidder A: ",Q12," — ",IF(U12="","(no comment)",U12)," || Bidder B: ",W12," — ",IF(AA12="","(no comment)",AA12)," | ",IF(Q12=W12,"Comparable disposition.","Diverging disposition — flag for negotiation.")))))
A13: 8 | B13: T1 Primary | C13: OFFER-42 | D13: After-Sales Service Organization & Pricing | E13: §4.15 | F13: Reliability / RAM / Service | G13: Reliability | H13: 46.3333 | I13: 85.7143 | J13: No | K13: Submit and review the named deliverable with RTM traceability and approval status; Functional design/configuration review and sequence/interface demonstration; RAM/maintenance substantiation and recovery/failure-response evidence | L13: Offer response: After-Sales Service Organization & Pricing; Procedure / work instruction | M13: L0 Tender / Offer; L1 Conceptual Design; L2 Detailed Design | N13: RTM-563..RTM-565 | P13: OK | Q13: TBD | V13: =IF(Q13="TBD","",H13*R13*IF(Q13="OK",1,IF(Q13="OK/Minor",0.85,IF(Q13="Minor disc.",0.7,IF(Q13="Major disc.",0.45,IF(Q13="MISS",0.25,0)))))) | W13: TBD | AB13: =IF(W13="TBD","",H13*X13*IF(W13="OK",1,IF(W13="OK/Minor",0.85,IF(W13="Minor disc.",0.7,IF(W13="Major disc.",0.45,IF(W13="MISS",0.25,0)))))) | AC13: =IF(AND(Q13="TBD",W13="TBD"),"Not yet evaluated — awaiting bidder review.",IF(Q13="TBD",CONCATENATE("Bidder B: ",W13," — ",IF(AA13="","(no comment)",AA13)," | Bidder A not yet evaluated."),IF(W13="TBD",CONCATENATE("Bidder A: ",Q13," — ",IF(U13="","(no comment)",U13)," | Bidder B not yet evaluated."),CONCATENATE("Bidder A: ",Q13," — ",IF(U13="","(no comment)",U13)," || Bidder B: ",W13," — ",IF(AA13="","(no comment)",AA13)," | ",IF(Q13=W13,"Comparable disposition.","Diverging disposition — flag for negotiation.")))))
A14: 9 | B14: T1 Primary | C14: OFFER-20 | D14: Helium Leak Detection & Loss Management | E14: §4.4.7 | F14: Reliability / RAM / Service | G14: Reliability | H14: 46 | I14: 82.6531 | J14: No | K14: Submit and review the named deliverable with RTM traceability and approval status; Witnessed FAT/SAT/commissioning test against stated acceptance criteria; Functional design/configuration review and sequence/interface demonstration | L14: Offer response: Helium Leak Detection & Loss Management; Test procedure / report; Procedure / work instruction | M14: L0 Tender / Offer; L4 Installation; L1 Conceptual Design; L2 Detailed Design | N14: RTM-252..RTM-257 | O14: RTM-258..RTM-262 | P14: OK — Review breadth | Q14: TBD | V14: =IF(Q14="TBD","",H14*R14*IF(Q14="OK",1,IF(Q14="OK/Minor",0.85,IF(Q14="Minor disc.",0.7,IF(Q14="Major disc.",0.45,IF(Q14="MISS",0.25,0)))))) | W14: TBD | AB14: =IF(W14="TBD","",H14*X14*IF(W14="OK",1,IF(W14="OK/Minor",0.85,IF(W14="Minor disc.",0.7,IF(W14="Major disc.",0.45,IF(W14="MISS",0.25,0)))))) | AC14: =IF(AND(Q14="TBD",W14="TBD"),"Not yet evaluated — awaiting bidder review.",IF(Q14="TBD",CONCATENATE("Bidder B: ",W14," — ",IF(AA14="","(no comment)",AA14)," | Bidder A not yet evaluated."),IF(W14="TBD",CONCATENATE("Bidder A: ",Q14," — ",IF(U14="","(no comment)",U14)," | Bidder B not yet evaluated."),CONCATENATE("Bidder A: ",Q14," — ",IF(U14="","(no comment)",U14)," || Bidder B: ",W14," — ",IF(AA14="","(no comment)",AA14)," | ",IF(Q14=W14,"Comparable disposition.","Diverging disposition — flag for negotiation.")))))
A15: 10 | B15: T1 Primary | C15: OFFER-34 | D15: Cooling Water System Requirements | E15: §4.7.4.3.2 | F15: Performance / Process / Utilities | G15: Reliability | H15: 46 | I15: 82.6531 | J15: No | K15: Submit and review the named deliverable with RTM traceability and approval status; Calculation/model plus calibrated measurement or recorded trend; RAM/maintenance substantiation and recovery/failure-response evidence | L15: Offer response: Cooling Water System Requirements | M15: L0 Tender / Offer; L1 Conceptual Design; L2 Detailed Design | N15: RTM-426..RTM-427 | P15: OK | Q15: TBD | V15: =IF(Q15="TBD","",H15*R15*IF(Q15="OK",1,IF(Q15="OK/Minor",0.85,IF(Q15="Minor disc.",0.7,IF(Q15="Major disc.",0.45,IF(Q15="MISS",0.25,0)))))) | W15: TBD | AB15: =IF(W15="TBD","",H15*X15*IF(W15="OK",1,IF(W15="OK/Minor",0.85,IF(W15="Minor disc.",0.7,IF(W15="Major disc.",0.45,IF(W15="MISS",0.25,0)))))) | AC15: =IF(AND(Q15="TBD",W15="TBD"),"Not yet evaluated — awaiting bidder review.",IF(Q15="TBD",CONCATENATE("Bidder B: ",W15," — ",IF(AA15="","(no comment)",AA15)," | Bidder A not yet evaluated."),IF(W15="TBD",CONCATENATE("Bidder A: ",Q15," — ",IF(U15="","(no comment)",U15)," | Bidder B not yet evaluated."),CONCATENATE("Bidder A: ",Q15," — ",IF(U15="","(no comment)",U15)," || Bidder B: ",W15," — ",IF(AA15="","(no comment)",AA15)," | ",IF(Q15=W15,"Comparable disposition.","Diverging disposition — flag for negotiation.")))))
A16: 11 | B16: T1 Primary | C16: OFFER-29 | D16: Control System Obsolescence Strategy | E16: §4.6.8 | F16: Controls / Software / Management | G16: Reliability | H16: 45 | I16: 79.5918 | J16: No | K16: Submit and review the named deliverable with RTM traceability and approval status; Functional design/configuration review and sequence/interface demonstration; RAM/maintenance substantiation and recovery/failure-response evidence | L16: Offer response: Control System Obsolescence Strategy | M16: L0 Tender / Offer; L1 Conceptual Design; L2 Detailed Design | N16: RTM-346..RTM-367 | P16: OK | Q16: TBD | V16: =IF(Q16="TBD","",H16*R16*IF(Q16="OK",1,IF(Q16="OK/Minor",0.85,IF(Q16="Minor disc.",0.7,IF(Q16="Major disc.",0.45,IF(Q16="MISS",0.25,0)))))) | W16: TBD | AB16: =IF(W16="TBD","",H16*X16*IF(W16="OK",1,IF(W16="OK/Minor",0.85,IF(W16="Minor disc.",0.7,IF(W16="Major disc.",0.45,IF(W16="MISS",0.25,0)))))) | AC16: =IF(AND(Q16="TBD",W16="TBD"),"Not yet evaluated — awaiting bidder review.",IF(Q16="TBD",CONCATENATE("Bidder B: ",W16," — ",IF(AA16="","(no comment)",AA16)," | Bidder A not yet evaluated."),IF(W16="TBD",CONCATENATE("Bidder A: ",Q16," — ",IF(U16="","(no comment)",U16)," | Bidder B not yet evaluated."),CONCATENATE("Bidder A: ",Q16," — ",IF(U16="","(no comment)",U16)," || Bidder B: ",W16," — ",IF(AA16="","(no comment)",AA16)," | ",IF(Q16=W16,"Comparable disposition.","Diverging disposition — flag for negotiation.")))))
A17: 12 | B17: T1 Primary | C17: OFFER-04 | D17: Cooldown & Thermal Performance Modelling | E17: §4.2.2.2 | F17: Performance / Process / Utilities | G17: Performance | H17: 44 | I17: 76.5306 | J17: No | K17: Submit and review the named deliverable with RTM traceability and approval status; Calculation/model plus calibrated measurement or recorded trend; Document review, inspection, certification, audit or traceable QC record | L17: Offer response: Cooldown & Thermal Performance Modelling | M17: L0 Tender / Offer; L1 Conceptual Design; L2 Detailed Design | N17: RTM-019..RTM-022 | P17: OK | Q17: TBD | V17: =IF(Q17="TBD","",H17*R17*IF(Q17="OK",1,IF(Q17="OK/Minor",0.85,IF(Q17="Minor disc.",0.7,IF(Q17="Major disc.",0.45,IF(Q17="MISS",0.25,0)))))) | W17: TBD | AB17: =IF(W17="TBD","",H17*X17*IF(W17="OK",1,IF(W17="OK/Minor",0.85,IF(W17="Minor disc.",0.7,IF(W17="Major disc.",0.45,IF(W17="MISS",0.25,0)))))) | AC17: =IF(AND(Q17="TBD",W17="TBD"),"Not yet evaluated — awaiting bidder review.",IF(Q17="TBD",CONCATENATE("Bidder B: ",W17," — ",IF(AA17="","(no comment)",AA17)," | Bidder A not yet evaluated."),IF(W17="TBD",CONCATENATE("Bidder A: ",Q17," — ",IF(U17="","(no comment)",U17)," | Bidder B not yet evaluated."),CONCATENATE("Bidder A: ",Q17," — ",IF(U17="","(no comment)",U17)," || Bidder B: ",W17," — ",IF(AA17="","(no comment)",AA17)," | ",IF(Q17=W17,"Comparable disposition.","Diverging disposition — flag for negotiation.")))))
A18: 13 | B18: T1 Primary | C18: OFFER-05 | D18: Operational Procedure Strategy (Auto vs Manual) | E18: §4.2.2.4.1 | F18: Controls / Software / Management | G18: Performance | H18: 44 | I18: 76.5306 | J18: No | K18: Submit and review the named deliverable with RTM traceability and approval status; Calculation/model plus calibrated measurement or recorded trend; Functional design/configuration review and sequence/interface demonstration | L18: Offer response: Operational Procedure Strategy (Auto vs Manual); Procedure / work instruction | M18: L0 Tender / Offer; L1 Conceptual Design; L2 Detailed Design | N18: RTM-025..RTM-027 | P18: OK | Q18: TBD | V18: =IF(Q18="TBD","",H18*R18*IF(Q18="OK",1,IF(Q18="OK/Minor",0.85,IF(Q18="Minor disc.",0.7,IF(Q18="Major disc.",0.45,IF(Q18="MISS",0.25,0)))))) | W18: TBD | AB18: =IF(W18="TBD","",H18*X18*IF(W18="OK",1,IF(W18="OK/Minor",0.85,IF(W18="Minor disc.",0.7,IF(W18="Major disc.",0.45,IF(W18="MISS",0.25,0)))))) | AC18: =IF(AND(Q18="TBD",W18="TBD"),"Not yet evaluated — awaiting bidder review.",IF(Q18="TBD",CONCATENATE("Bidder B: ",W18," — ",IF(AA18="","(no comment)",AA18)," | Bidder A not yet evaluated."),IF(W18="TBD",CONCATENATE("Bidder A: ",Q18," — ",IF(U18="","(no comment)",U18)," | Bidder B not yet evaluated."),CONCATENATE("Bidder A: ",Q18," — ",IF(U18="","(no comment)",U18)," || Bidder B: ",W18," — ",IF(AA18="","(no comment)",AA18)," | ",IF(Q18=W18,"Comparable disposition.","Diverging disposition — flag for negotiation.")))))
A19: 14 | B19: T1 Primary | C19: OFFER-27 | D19: Programming Standards & Language Strategy | E19: §4.6.7 | F19: Controls / Software / Management | G19: Functional | H19: 41.3333 | I19: 73.4694 | J19: No | K19: Submit and review the named deliverable with RTM traceability and approval status; Witnessed FAT/SAT/commissioning test against stated acceptance criteria; Functional design/configuration review and sequence/interface demonstration | L19: Offer response: Programming Standards & Language Strategy | M19: L0 Tender / Offer; L1 Conceptual Design; L2 Detailed Design | N19: RTM-340..RTM-341; RTM-343..RTM-344 | O19: RTM-334..RTM-339; RTM-342; RTM-345 | P19: OK | Q19: TBD | V19: =IF(Q19="TBD","",H19*R19*IF(Q19="OK",1,IF(Q19="OK/Minor",0.85,IF(Q19="Minor disc.",0.7,IF(Q19="Major disc.",0.45,IF(Q19="MISS",0.25,0)))))) | W19: TBD | AB19: =IF(W19="TBD","",H19*X19*IF(W19="OK",1,IF(W19="OK/Minor",0.85,IF(W19="Minor disc.",0.7,IF(W19="Major disc.",0.45,IF(W19="MISS",0.25,0)))))) | AC19: =IF(AND(Q19="TBD",W19="TBD"),"Not yet evaluated — awaiting bidder review.",IF(Q19="TBD",CONCATENATE("Bidder B: ",W19," — ",IF(AA19="","(no comment)",AA19)," | Bidder A not yet evaluated."),IF(W19="TBD",CONCATENATE("Bidder A: ",Q19," — ",IF(U19="","(no comment)",U19)," | Bidder B not yet evaluated."),CONCATENATE("Bidder A: ",Q19," — ",IF(U19="","(no comment)",U19)," || Bidder B: ",W19," — ",IF(AA19="","(no comment)",AA19)," | ",IF(Q19=W19,"Comparable disposition.","Diverging disposition — flag for negotiation.")))))
A20: 15 | B20: T1 Primary | C20: OFFER-33 | D20: Electrical System Design & Load Analysis | E20: §4.7.3.1 | F20: Controls / Software / Management | G20: Reliability | H20: 38.6667 | I20: 70.4082 | J20: No | K20: Submit and review the named deliverable with RTM traceability and approval status; Calculation/model plus calibrated measurement or recorded trend; RAM/maintenance substantiation and recovery/failure-response evidence | L20: Offer response: Electrical System Design & Load Analysis; Drawing / diagram; List / register / matrix | M20: L0 Tender / Offer; L1 Conceptual Design; L2 Detailed Design | N20: RTM-401..RTM-402 | P20: OK | Q20: TBD | V20: =IF(Q20="TBD","",H20*R20*IF(Q20="OK",1,IF(Q20="OK/Minor",0.85,IF(Q20="Minor disc.",0.7,IF(Q20="Major disc.",0.45,IF(Q20="MISS",0.25,0)))))) | W20: TBD | AB20: =IF(W20="TBD","",H20*X20*IF(W20="OK",1,IF(W20="OK/Minor",0.85,IF(W20="Minor disc.",0.7,IF(W20="Major disc.",0.45,IF(W20="MISS",0.25,0)))))) | AC20: =IF(AND(Q20="TBD",W20="TBD"),"Not yet evaluated — awaiting bidder review.",IF(Q20="TBD",CONCATENATE("Bidder B: ",W20," — ",IF(AA20="","(no comment)",AA20)," | Bidder A not yet evaluated."),IF(W20="TBD",CONCATENATE("Bidder A: ",Q20," — ",IF(U20="","(no comment)",U20)," | Bidder B not yet evaluated."),CONCATENATE("Bidder A: ",Q20," — ",IF(U20="","(no comment)",U20)," || Bidder B: ",W20," — ",IF(AA20="","(no comment)",AA20)," | ",IF(Q20=W20,"Comparable disposition.","Diverging disposition — flag for negotiation.")))))
A21: 16 | B21: T1 Primary | C21: OFFER-41 | D21: Spare Parts & Critical Components Strategy | E21: §4.14.3 | F21: Reliability / RAM / Service | G21: Reliability | H21: 38.6667 | I21: 70.4082 | J21: No | K21: Submit and review the named deliverable with RTM traceability and approval status; RAM/maintenance substantiation and recovery/failure-response evidence | L21: Offer response: Spare Parts & Critical Components Strategy; List / register / matrix | M21: L0 Tender / Offer; L1 Conceptual Design; L2 Detailed Design | N21: RTM-560..RTM-562 | P21: OK | Q21: TBD | V21: =IF(Q21="TBD","",H21*R21*IF(Q21="OK",1,IF(Q21="OK/Minor",0.85,IF(Q21="Minor disc.",0.7,IF(Q21="Major disc.",0.45,IF(Q21="MISS",0.25,0)))))) | W21: TBD | AB21: =IF(W21="TBD","",H21*X21*IF(W21="OK",1,IF(W21="OK/Minor",0.85,IF(W21="Minor disc.",0.7,IF(W21="Major disc.",0.45,IF(W21="MISS",0.25,0)))))) | AC21: =IF(AND(Q21="TBD",W21="TBD"),"Not yet evaluated — awaiting bidder review.",IF(Q21="TBD",CONCATENATE("Bidder B: ",W21," — ",IF(AA21="","(no comment)",AA21)," | Bidder A not yet evaluated."),IF(W21="TBD",CONCATENATE("Bidder A: ",Q21," — ",IF(U21="","(no comment)",U21)," | Bidder B not yet evaluated."),CONCATENATE("Bidder A: ",Q21," — ",IF(U21="","(no comment)",U21)," || Bidder B: ",W21," — ",IF(AA21="","(no comment)",AA21)," | ",IF(Q21=W21,"Comparable disposition.","Diverging disposition — flag for negotiation.")))))
A22: 17 | B22: T2 Secondary | C22: OFFER-06 | D22: LHe Filling & Emptying Performance | E22: §4.2.2.4.3 | F22: Performance / Process / Utilities | G22: Performance | H22: 36 | I22: 66.3265 | J22: No | K22: Submit and review the named deliverable with RTM traceability and approval status; Calculation/model plus calibrated measurement or recorded trend | L22: Offer response: LHe Filling & Emptying Performance | M22: L0 Tender / Offer; L1 Conceptual Design; L2 Detailed Design | N22: RTM-030..RTM-033 | P22: OK | Q22: TBD | V22: =IF(Q22="TBD","",H22*R22*IF(Q22="OK",1,IF(Q22="OK/Minor",0.85,IF(Q22="Minor disc.",0.7,IF(Q22="Major disc.",0.45,IF(Q22="MISS",0.25,0)))))) | W22: TBD | AB22: =IF(W22="TBD","",H22*X22*IF(W22="OK",1,IF(W22="OK/Minor",0.85,IF(W22="Minor disc.",0.7,IF(W22="Major disc.",0.45,IF(W22="MISS",0.25,0)))))) | AC22: =IF(AND(Q22="TBD",W22="TBD"),"Not yet evaluated — awaiting bidder review.",IF(Q22="TBD",CONCATENATE("Bidder B: ",W22," — ",IF(AA22="","(no comment)",AA22)," | Bidder A not yet evaluated."),IF(W22="TBD",CONCATENATE("Bidder A: ",Q22," — ",IF(U22="","(no comment)",U22)," | Bidder B not yet evaluated."),CONCATENATE("Bidder A: ",Q22," — ",IF(U22="","(no comment)",U22)," || Bidder B: ",W22," — ",IF(AA22="","(no comment)",AA22)," | ",IF(Q22=W22,"Comparable disposition.","Diverging disposition — flag for negotiation.")))))
A23: 18 | B23: T2 Secondary | C23: OFFER-37 | D23: Digital Twin / Simulation Strategy | E23: §4.8.2 | F23: Controls / Software / Management | G23: Functional | H23: 36 | I23: 66.3265 | J23: No | K23: Submit and review the named deliverable with RTM traceability and approval status; Witnessed FAT/SAT/commissioning test against stated acceptance criteria; Document review, inspection, certification, audit or traceable QC record | L23: Offer response: Digital Twin / Simulation Strategy; Digital Process Model / Digital Twin | M23: L0 Tender / Offer; L1 Conceptual Design; L2 Detailed Design | N23: RTM-450..RTM-451 | P23: OK | Q23: TBD | V23: =IF(Q23="TBD","",H23*R23*IF(Q23="OK",1,IF(Q23="OK/Minor",0.85,IF(Q23="Minor disc.",0.7,IF(Q23="Major disc.",0.45,IF(Q23="MISS",0.25,0)))))) | W23: TBD | AB23: =IF(W23="TBD","",H23*X23*IF(W23="OK",1,IF(W23="OK/Minor",0.85,IF(W23="Minor disc.",0.7,IF(W23="Major disc.",0.45,IF(W23="MISS",0.25,0)))))) | AC23: =IF(AND(Q23="TBD",W23="TBD"),"Not yet evaluated — awaiting bidder review.",IF(Q23="TBD",CONCATENATE("Bidder B: ",W23," — ",IF(AA23="","(no comment)",AA23)," | Bidder A not yet evaluated."),IF(W23="TBD",CONCATENATE("Bidder A: ",Q23," — ",IF(U23="","(no comment)",U23)," | Bidder B not yet evaluated."),CONCATENATE("Bidder A: ",Q23," — ",IF(U23="","(no comment)",U23)," || Bidder B: ",W23," — ",IF(AA23="","(no comment)",AA23)," | ",IF(Q23=W23,"Comparable disposition.","Diverging disposition — flag for negotiation.")))))
A24: 19 | B24: T2 Secondary | C24: OFFER-43 | D24: Maintenance Effort & Intervention Estimation | E24: §4.15 | F24: Reliability / RAM / Service | G24: Reliability | H24: 35.6667 | I24: 63.2653 | J24: No | K24: Submit and review the named deliverable with RTM traceability and approval status; RAM/maintenance substantiation and recovery/failure-response evidence | L24: Offer response: Maintenance Effort & Intervention Estimation | M24: L0 Tender / Offer; L1 Conceptual Design; L2 Detailed Design | O24: RTM-563..RTM-565 | P24: Review — accept context | Q24: TBD | V24: =IF(Q24="TBD","",H24*R24*IF(Q24="OK",1,IF(Q24="OK/Minor",0.85,IF(Q24="Minor disc.",0.7,IF(Q24="Major disc.",0.45,IF(Q24="MISS",0.25,0)))))) | W24: TBD | AB24: =IF(W24="TBD","",H24*X24*IF(W24="OK",1,IF(W24="OK/Minor",0.85,IF(W24="Minor disc.",0.7,IF(W24="Major disc.",0.45,IF(W24="MISS",0.25,0)))))) | AC24: =IF(AND(Q24="TBD",W24="TBD"),"Not yet evaluated — awaiting bidder review.",IF(Q24="TBD",CONCATENATE("Bidder B: ",W24," — ",IF(AA24="","(no comment)",AA24)," | Bidder A not yet evaluated."),IF(W24="TBD",CONCATENATE("Bidder A: ",Q24," — ",IF(U24="","(no comment)",U24)," | Bidder B not yet evaluated."),CONCATENATE("Bidder A: ",Q24," — ",IF(U24="","(no comment)",U24)," || Bidder B: ",W24," — ",IF(AA24="","(no comment)",AA24)," | ",IF(Q24=W24,"Comparable disposition.","Diverging disposition — flag for negotiation.")))))
A25: 20 | B25: T2 Secondary | C25: OFFER-21 | D25: LOOP Strategy & Critical Load Management | E25: §4.4.7.1 | F25: Reliability / RAM / Service | G25: Reliability | H25: 32.6667 | I25: 60.2041 | J25: No | K25: Submit and review the named deliverable with RTM traceability and approval status; Functional design/configuration review and sequence/interface demonstration; RAM/maintenance substantiation and recovery/failure-response evidence | L25: Offer response: LOOP Strategy & Critical Load Management | M25: L0 Tender / Offer; L1 Conceptual Design; L2 Detailed Design | N25: RTM-258 | P25: OK | Q25: TBD | V25: =IF(Q25="TBD","",H25*R25*IF(Q25="OK",1,IF(Q25="OK/Minor",0.85,IF(Q25="Minor disc.",0.7,IF(Q25="Major disc.",0.45,IF(Q25="MISS",0.25,0)))))) | W25: TBD | AB25: =IF(W25="TBD","",H25*X25*IF(W25="OK",1,IF(W25="OK/Minor",0.85,IF(W25="Minor disc.",0.7,IF(W25="Major disc.",0.45,IF(W25="MISS",0.25,0)))))) | AC25: =IF(AND(Q25="TBD",W25="TBD"),"Not yet evaluated — awaiting bidder review.",IF(Q25="TBD",CONCATENATE("Bidder B: ",W25," — ",IF(AA25="","(no comment)",AA25)," | Bidder A not yet evaluated."),IF(W25="TBD",CONCATENATE("Bidder A: ",Q25," — ",IF(U25="","(no comment)",U25)," | Bidder B not yet evaluated."),CONCATENATE("Bidder A: ",Q25," — ",IF(U25="","(no comment)",U25)," || Bidder B: ",W25," — ",IF(AA25="","(no comment)",AA25)," | ",IF(Q25=W25,"Comparable disposition.","Diverging disposition — flag for negotiation.")))))
A26: 21 | B26: T2 Secondary | C26: OFFER-22 | D26: Helium Recovery System Design | E26: §4.4.7.3 | F26: Reliability / RAM / Service | G26: Reliability | H26: 32.6667 | I26: 60.2041 | J26: No | K26: Submit and review the named deliverable with RTM traceability and approval status; RAM/maintenance substantiation and recovery/failure-response evidence | L26: Offer response: Helium Recovery System Design | M26: L0 Tender / Offer; L1 Conceptual Design; L2 Detailed Design | N26: RTM-260..RTM-262 | P26: OK | Q26: TBD | V26: =IF(Q26="TBD","",H26*R26*IF(Q26="OK",1,IF(Q26="OK/Minor",0.85,IF(Q26="Minor disc.",0.7,IF(Q26="Major disc.",0.45,IF(Q26="MISS",0.25,0)))))) | W26: TBD | AB26: =IF(W26="TBD","",H26*X26*IF(W26="OK",1,IF(W26="OK/Minor",0.85,IF(W26="Minor disc.",0.7,IF(W26="Major disc.",0.45,IF(W26="MISS",0.25,0)))))) | AC26: =IF(AND(Q26="TBD",W26="TBD"),"Not yet evaluated — awaiting bidder review.",IF(Q26="TBD",CONCATENATE("Bidder B: ",W26," — ",IF(AA26="","(no comment)",AA26)," | Bidder A not yet evaluated."),IF(W26="TBD",CONCATENATE("Bidder A: ",Q26," — ",IF(U26="","(no comment)",U26)," | Bidder B not yet evaluated."),CONCATENATE("Bidder A: ",Q26," — ",IF(U26="","(no comment)",U26)," || Bidder B: ",W26," — ",IF(AA26="","(no comment)",AA26)," | ",IF(Q26=W26,"Comparable disposition.","Diverging disposition — flag for negotiation.")))))
A27: 22 | B27: T2 Secondary | C27: OFFER-10 | D27: LN2 System Functional & Interface Design | E27: §4.2.5 | F27: Performance / Process / Utilities | G27: Performance | H27: 32 | I27: 56.1224 | J27: No | K27: Submit and review the named deliverable with RTM traceability and approval status; Witnessed FAT/SAT/commissioning test against stated acceptance criteria; Calculation/model plus calibrated measurement or recorded trend | L27: Offer response: LN2 System Functional & Interface Design | M27: L0 Tender / Offer; L6 Site Acceptance Testing; L1 Conceptual Design; L2 Detailed Design | N27: RTM-046..RTM-047 | O27: RTM-045 | P27: OK | Q27: TBD | V27: =IF(Q27="TBD","",H27*R27*IF(Q27="OK",1,IF(Q27="OK/Minor",0.85,IF(Q27="Minor disc.",0.7,IF(Q27="Major disc.",0.45,IF(Q27="MISS",0.25,0)))))) | W27: TBD | AB27: =IF(W27="TBD","",H27*X27*IF(W27="OK",1,IF(W27="OK/Minor",0.85,IF(W27="Minor disc.",0.7,IF(W27="Major disc.",0.45,IF(W27="MISS",0.25,0)))))) | AC27: =IF(AND(Q27="TBD",W27="TBD"),"Not yet evaluated — awaiting bidder review.",IF(Q27="TBD",CONCATENATE("Bidder B: ",W27," — ",IF(AA27="","(no comment)",AA27)," | Bidder A not yet evaluated."),IF(W27="TBD",CONCATENATE("Bidder A: ",Q27," — ",IF(U27="","(no comment)",U27)," | Bidder B not yet evaluated."),CONCATENATE("Bidder A: ",Q27," — ",IF(U27="","(no comment)",U27)," || Bidder B: ",W27," — ",IF(AA27="","(no comment)",AA27)," | ",IF(Q27=W27,"Comparable disposition.","Diverging disposition — flag for negotiation.")))))
A28: 23 | B28: T2 Secondary | C28: OFFER-17 | D28: Preliminary 3D Plant Layout Model | E28: §4.4.4.1 | F28: Configuration / Layout / Support | G28: Performance | H28: 32 | I28: 56.1224 | J28: No | K28: Submit and review the named deliverable with RTM traceability and approval status; Calculation/model plus calibrated measurement or recorded trend; Document review, inspection, certification, audit or traceable QC record | L28: Offer response: Preliminary 3D Plant Layout Model; 3D / CAD Model | M28: L0 Tender / Offer; L1 Conceptual Design; L2 Detailed Design | N28: RTM-193..RTM-197 | P28: OK | Q28: TBD | V28: =IF(Q28="TBD","",H28*R28*IF(Q28="OK",1,IF(Q28="OK/Minor",0.85,IF(Q28="Minor disc.",0.7,IF(Q28="Major disc.",0.45,IF(Q28="MISS",0.25,0)))))) | W28: TBD | AB28: =IF(W28="TBD","",H28*X28*IF(W28="OK",1,IF(W28="OK/Minor",0.85,IF(W28="Minor disc.",0.7,IF(W28="Major disc.",0.45,IF(W28="MISS",0.25,0)))))) | AC28: =IF(AND(Q28="TBD",W28="TBD"),"Not yet evaluated — awaiting bidder review.",IF(Q28="TBD",CONCATENATE("Bidder B: ",W28," — ",IF(AA28="","(no comment)",AA28)," | Bidder A not yet evaluated."),IF(W28="TBD",CONCATENATE("Bidder A: ",Q28," — ",IF(U28="","(no comment)",U28)," | Bidder B not yet evaluated."),CONCATENATE("Bidder A: ",Q28," — ",IF(U28="","(no comment)",U28)," || Bidder B: ",W28," — ",IF(AA28="","(no comment)",AA28)," | ",IF(Q28=W28,"Comparable disposition.","Diverging disposition — flag for negotiation.")))))
A29: 24 | B29: T2 Secondary | C29: OFFER-45 | D29: Project Dashboard & Management Processes | E29: §7.4.1 | F29: Controls / Software / Management | G29: Safety / Legal | H29: 31.6667 | I29: 53.0612 | J29: No | K29: Submit and review the named deliverable with RTM traceability and approval status; Witnessed FAT/SAT/commissioning test against stated acceptance criteria; Document review, inspection, certification, audit or traceable QC record | L29: Offer response: Project Dashboard & Management Processes | M29: L0 Tender / Offer; L1 Conceptual Design; L2 Detailed Design; L3 Procurement & Manufacturing / FAT; L4 Installation; L5 Standalone Commissioning; L6 Site Acceptance Testing | N29: RTM-633 | P29: OK | Q29: TBD | V29: =IF(Q29="TBD","",H29*R29*IF(Q29="OK",1,IF(Q29="OK/Minor",0.85,IF(Q29="Minor disc.",0.7,IF(Q29="Major disc.",0.45,IF(Q29="MISS",0.25,0)))))) | W29: TBD | AB29: =IF(W29="TBD","",H29*X29*IF(W29="OK",1,IF(W29="OK/Minor",0.85,IF(W29="Minor disc.",0.7,IF(W29="Major disc.",0.45,IF(W29="MISS",0.25,0)))))) | AC29: =IF(AND(Q29="TBD",W29="TBD"),"Not yet evaluated — awaiting bidder review.",IF(Q29="TBD",CONCATENATE("Bidder B: ",W29," — ",IF(AA29="","(no comment)",AA29)," | Bidder A not yet evaluated."),IF(W29="TBD",CONCATENATE("Bidder A: ",Q29," — ",IF(U29="","(no comment)",U29)," | Bidder B not yet evaluated."),CONCATENATE("Bidder A: ",Q29," — ",IF(U29="","(no comment)",U29)," || Bidder B: ",W29," — ",IF(AA29="","(no comment)",AA29)," | ",IF(Q29=W29,"Comparable disposition.","Diverging disposition — flag for negotiation.")))))
A30: 25 | B30: T2 Secondary | C30: OFFER-39 | D30: FAT/SAT Testing Strategy & Procedures | E30: §4.13.1 | F30: Configuration / Layout / Support | G30: Quality / Verifiability | H30: 29.3333 | I30: 51.0204 | J30: No | K30: Submit and review the named deliverable with RTM traceability and approval status; Witnessed FAT/SAT/commissioning test against stated acceptance criteria | L30: Offer response: FAT/SAT Testing Strategy & Procedures | M30: L0 Tender / Offer; L6 Site Acceptance Testing; L1 Conceptual Design; L2 Detailed Design | N30: RTM-491..RTM-495 | O30: RTM-496..RTM-556 | P30: OK — Review breadth | Q30: TBD | V30: =IF(Q30="TBD","",H30*R30*IF(Q30="OK",1,IF(Q30="OK/Minor",0.85,IF(Q30="Minor disc.",0.7,IF(Q30="Major disc.",0.45,IF(Q30="MISS",0.25,0)))))) | W30: TBD | AB30: =IF(W30="TBD","",H30*X30*IF(W30="OK",1,IF(W30="OK/Minor",0.85,IF(W30="Minor disc.",0.7,IF(W30="Major disc.",0.45,IF(W30="MISS",0.25,0)))))) | AC30: =IF(AND(Q30="TBD",W30="TBD"),"Not yet evaluated — awaiting bidder review.",IF(Q30="TBD",CONCATENATE("Bidder B: ",W30," — ",IF(AA30="","(no comment)",AA30)," | Bidder A not yet evaluated."),IF(W30="TBD",CONCATENATE("Bidder A: ",Q30," — ",IF(U30="","(no comment)",U30)," | Bidder B not yet evaluated."),CONCATENATE("Bidder A: ",Q30," — ",IF(U30="","(no comment)",U30)," || Bidder B: ",W30," — ",IF(AA30="","(no comment)",AA30)," | ",IF(Q30=W30,"Comparable disposition.","Diverging disposition — flag for negotiation.")))))
A31: 26 | B31: T2 Secondary | C31: OFFER-11 | D31: Reliability, MTBF & Recovery Strategy | E31: §4.3.2 | F31: Reliability / RAM / Service | G31: Reliability | H31: 26.6667 | I31: 48.9796 | J31: No | K31: Submit and review the named deliverable with RTM traceability and approval status; RAM/maintenance substantiation and recovery/failure-response evidence | L31: Offer response: Reliability, MTBF & Recovery Strategy | M31: L0 Tender / Offer; L1 Conceptual Design; L2 Detailed Design | N31: RTM-057..RTM-063 | P31: OK | Q31: TBD | V31: =IF(Q31="TBD","",H31*R31*IF(Q31="OK",1,IF(Q31="OK/Minor",0.85,IF(Q31="Minor disc.",0.7,IF(Q31="Major disc.",0.45,IF(Q31="MISS",0.25,0)))))) | W31: TBD | AB31: =IF(W31="TBD","",H31*X31*IF(W31="OK",1,IF(W31="OK/Minor",0.85,IF(W31="Minor disc.",0.7,IF(W31="Major disc.",0.45,IF(W31="MISS",0.25,0)))))) | AC31: =IF(AND(Q31="TBD",W31="TBD"),"Not yet evaluated — awaiting bidder review.",IF(Q31="TBD",CONCATENATE("Bidder B: ",W31," — ",IF(AA31="","(no comment)",AA31)," | Bidder A not yet evaluated."),IF(W31="TBD",CONCATENATE("Bidder A: ",Q31," — ",IF(U31="","(no comment)",U31)," | Bidder B not yet evaluated."),CONCATENATE("Bidder A: ",Q31," — ",IF(U31="","(no comment)",U31)," || Bidder B: ",W31," — ",IF(AA31="","(no comment)",AA31)," | ",IF(Q31=W31,"Comparable disposition.","Diverging disposition — flag for negotiation.")))))
A32: 27 | B32: T2 Secondary | C32: OFFER-15 | D32: Compressor Noise Emission Specification | E32: §4.4.3.1 | F32: Configuration / Layout / Support | G32: Performance | H32: 24 | I32: 41.8367 | J32: No | K32: Submit and review the named deliverable with RTM traceability and approval status; Calculation/model plus calibrated measurement or recorded trend | L32: Offer response: Compressor Noise Emission Specification | M32: L0 Tender / Offer; L1 Conceptual Design; L2 Detailed Design | N32: RTM-141..RTM-147 | P32: OK | Q32: TBD | V32: =IF(Q32="TBD","",H32*R32*IF(Q32="OK",1,IF(Q32="OK/Minor",0.85,IF(Q32="Minor disc.",0.7,IF(Q32="Major disc.",0.45,IF(Q32="MISS",0.25,0)))))) | W32: TBD | AB32: =IF(W32="TBD","",H32*X32*IF(W32="OK",1,IF(W32="OK/Minor",0.85,IF(W32="Minor disc.",0.7,IF(W32="Major disc.",0.45,IF(W32="MISS",0.25,0)))))) | AC32: =IF(AND(Q32="TBD",W32="TBD"),"Not yet evaluated — awaiting bidder review.",IF(Q32="TBD",CONCATENATE("Bidder B: ",W32," — ",IF(AA32="","(no comment)",AA32)," | Bidder A not yet evaluated."),IF(W32="TBD",CONCATENATE("Bidder A: ",Q32," — ",IF(U32="","(no comment)",U32)," | Bidder B not yet evaluated."),CONCATENATE("Bidder A: ",Q32," — ",IF(U32="","(no comment)",U32)," || Bidder B: ",W32," — ",IF(AA32="","(no comment)",AA32)," | ",IF(Q32=W32,"Comparable disposition.","Diverging disposition — flag for negotiation.")))))
A33: 28 | B33: T2 Secondary | C33: OFFER-16 | D33: Compressor Configuration & Operating Limits | E33: §4.4.3.2 | F33: Configuration / Layout / Support | G33: Performance | H33: 24 | I33: 41.8367 | J33: No | K33: Submit and review the named deliverable with RTM traceability and approval status; Calculation/model plus calibrated measurement or recorded trend | L33: Offer response: Compressor Configuration & Operating Limits | M33: L0 Tender / Offer; L1 Conceptual Design; L2 Detailed Design | N33: RTM-148..RTM-152 | P33: OK | Q33: TBD | V33: =IF(Q33="TBD","",H33*R33*IF(Q33="OK",1,IF(Q33="OK/Minor",0.85,IF(Q33="Minor disc.",0.7,IF(Q33="Major disc.",0.45,IF(Q33="MISS",0.25,0)))))) | W33: TBD | AB33: =IF(W33="TBD","",H33*X33*IF(W33="OK",1,IF(W33="OK/Minor",0.85,IF(W33="Minor disc.",0.7,IF(W33="Major disc.",0.45,IF(W33="MISS",0.25,0)))))) | AC33: =IF(AND(Q33="TBD",W33="TBD"),"Not yet evaluated — awaiting bidder review.",IF(Q33="TBD",CONCATENATE("Bidder B: ",W33," — ",IF(AA33="","(no comment)",AA33)," | Bidder A not yet evaluated."),IF(W33="TBD",CONCATENATE("Bidder A: ",Q33," — ",IF(U33="","(no comment)",U33)," | Bidder B not yet evaluated."),CONCATENATE("Bidder A: ",Q33," — ",IF(U33="","(no comment)",U33)," || Bidder B: ",W33," — ",IF(AA33="","(no comment)",AA33)," | ",IF(Q33=W33,"Comparable disposition.","Diverging disposition — flag for negotiation.")))))
A34: 29 | B34: T2 Secondary | C34: OFFER-18 | D34: MPHX Technology Selection | E34: §4.4.4.2.2 | F34: Performance / Process / Utilities | G34: Performance | H34: 24 | I34: 41.8367 | J34: No | K34: Submit and review the named deliverable with RTM traceability and approval status; Calculation/model plus calibrated measurement or recorded trend | L34: Offer response: MPHX Technology Selection | M34: L0 Tender / Offer; L1 Conceptual Design; L2 Detailed Design | N34: RTM-202..RTM-209 | P34: OK | Q34: TBD | V34: =IF(Q34="TBD","",H34*R34*IF(Q34="OK",1,IF(Q34="OK/Minor",0.85,IF(Q34="Minor disc.",0.7,IF(Q34="Major disc.",0.45,IF(Q34="MISS",0.25,0)))))) | W34: TBD | AB34: =IF(W34="TBD","",H34*X34*IF(W34="OK",1,IF(W34="OK/Minor",0.85,IF(W34="Minor disc.",0.7,IF(W34="Major disc.",0.45,IF(W34="MISS",0.25,0)))))) | AC34: =IF(AND(Q34="TBD",W34="TBD"),"Not yet evaluated — awaiting bidder review.",IF(Q34="TBD",CONCATENATE("Bidder B: ",W34," — ",IF(AA34="","(no comment)",AA34)," | Bidder A not yet evaluated."),IF(W34="TBD",CONCATENATE("Bidder A: ",Q34," — ",IF(U34="","(no comment)",U34)," | Bidder B not yet evaluated."),CONCATENATE("Bidder A: ",Q34," — ",IF(U34="","(no comment)",U34)," || Bidder B: ",W34," — ",IF(AA34="","(no comment)",AA34)," | ",IF(Q34=W34,"Comparable disposition.","Diverging disposition — flag for negotiation.")))))
A35: 30 | B35: T2 Secondary | C35: OFFER-19 | D35: Warm Storage Heater (WSH) Design & Layout | E35: §4.4.5.2 | F35: Performance / Process / Utilities | G35: Performance | H35: 24 | I35: 41.8367 | J35: No | K35: Submit and review the named deliverable with RTM traceability and approval status; Calculation/model plus calibrated measurement or recorded trend | L35: Offer response: Warm Storage Heater (WSH) Design & Layout | M35: L0 Tender / Offer; L1 Conceptual Design; L2 Detailed Design | N35: RTM-239..RTM-248 | P35: OK | Q35: TBD | V35: =IF(Q35="TBD","",H35*R35*IF(Q35="OK",1,IF(Q35="OK/Minor",0.85,IF(Q35="Minor disc.",0.7,IF(Q35="Major disc.",0.45,IF(Q35="MISS",0.25,0)))))) | W35: TBD | AB35: =IF(W35="TBD","",H35*X35*IF(W35="OK",1,IF(W35="OK/Minor",0.85,IF(W35="Minor disc.",0.7,IF(W35="Major disc.",0.45,IF(W35="MISS",0.25,0)))))) | AC35: =IF(AND(Q35="TBD",W35="TBD"),"Not yet evaluated — awaiting bidder review.",IF(Q35="TBD",CONCATENATE("Bidder B: ",W35," — ",IF(AA35="","(no comment)",AA35)," | Bidder A not yet evaluated."),IF(W35="TBD",CONCATENATE("Bidder A: ",Q35," — ",IF(U35="","(no comment)",U35)," | Bidder B not yet evaluated."),CONCATENATE("Bidder A: ",Q35," — ",IF(U35="","(no comment)",U35)," || Bidder B: ",W35," — ",IF(AA35="","(no comment)",AA35)," | ",IF(Q35=W35,"Comparable disposition.","Diverging disposition — flag for negotiation.")))))
A36: 31 | B36: T2 Secondary | C36: OFFER-24 | D36: Helium Purity Acceptance Criteria | E36: §4.4.8.2 | F36: Performance / Process / Utilities | G36: Safety / Legal | H36: 24 | I36: 41.8367 | J36: No | K36: Submit and review the named deliverable with RTM traceability and approval status | L36: Offer response: Helium Purity Acceptance Criteria | M36: L0 Tender / Offer; L1 Conceptual Design; L2 Detailed Design | N36: RTM-273..RTM-280 | P36: OK | Q36: TBD | V36: =IF(Q36="TBD","",H36*R36*IF(Q36="OK",1,IF(Q36="OK/Minor",0.85,IF(Q36="Minor disc.",0.7,IF(Q36="Major disc.",0.45,IF(Q36="MISS",0.25,0)))))) | W36: TBD | AB36: =IF(W36="TBD","",H36*X36*IF(W36="OK",1,IF(W36="OK/Minor",0.85,IF(W36="Minor disc.",0.7,IF(W36="Major disc.",0.45,IF(W36="MISS",0.25,0)))))) | AC36: =IF(AND(Q36="TBD",W36="TBD"),"Not yet evaluated — awaiting bidder review.",IF(Q36="TBD",CONCATENATE("Bidder B: ",W36," — ",IF(AA36="","(no comment)",AA36)," | Bidder A not yet evaluated."),IF(W36="TBD",CONCATENATE("Bidder A: ",Q36," — ",IF(U36="","(no comment)",U36)," | Bidder B not yet evaluated."),CONCATENATE("Bidder A: ",Q36," — ",IF(U36="","(no comment)",U36)," || Bidder B: ",W36," — ",IF(AA36="","(no comment)",AA36)," | ",IF(Q36=W36,"Comparable disposition.","Diverging disposition — flag for negotiation.")))))
A37: 32 | B37: T2 Secondary | C37: OFFER-35 | D37: Heat Rejection & HVAC Interface Design | E37: §4.7.6 | F37: Performance / Process / Utilities | G37: Performance | H37: 24 | I37: 41.8367 | J37: No | K37: Submit and review the named deliverable with RTM traceability and approval status; Calculation/model plus calibrated measurement or recorded trend; Functional design/configuration review and sequence/interface demonstration | L37: Offer response: Heat Rejection & HVAC Interface Design | M37: L0 Tender / Offer; L1 Conceptual Design; L2 Detailed Design | N37: RTM-434..RTM-435 | P37: OK | Q37: TBD | V37: =IF(Q37="TBD","",H37*R37*IF(Q37="OK",1,IF(Q37="OK/Minor",0.85,IF(Q37="Minor disc.",0.7,IF(Q37="Major disc.",0.45,IF(Q37="MISS",0.25,0)))))) | W37: TBD | AB37: =IF(W37="TBD","",H37*X37*IF(W37="OK",1,IF(W37="OK/Minor",0.85,IF(W37="Minor disc.",0.7,IF(W37="Major disc.",0.45,IF(W37="MISS",0.25,0)))))) | AC37: =IF(AND(Q37="TBD",W37="TBD"),"Not yet evaluated — awaiting bidder review.",IF(Q37="TBD",CONCATENATE("Bidder B: ",W37," — ",IF(AA37="","(no comment)",AA37)," | Bidder A not yet evaluated."),IF(W37="TBD",CONCATENATE("Bidder A: ",Q37," — ",IF(U37="","(no comment)",U37)," | Bidder B not yet evaluated."),CONCATENATE("Bidder A: ",Q37," — ",IF(U37="","(no comment)",U37)," || Bidder B: ",W37," — ",IF(AA37="","(no comment)",AA37)," | ",IF(Q37=W37,"Comparable disposition.","Diverging disposition — flag for negotiation.")))))
A38: 33 | B38: T3 Contextual | C38: OFFER-50 | D38: Warranty Extension Commercial Terms | E38: §10.2 | F38: Configuration / Layout / Support | G38: Safety / Legal | H38: 23.3333 | I38: 34.6939 | J38: No | K38: Submit and review the named deliverable with RTM traceability and approval status | L38: Offer response: Warranty Extension Commercial Terms | M38: L0 Tender / Offer; Warranty; PAC / Handover; FAC | N38: RTM-708 | O38: RTM-709..RTM-710 | P38: OK | Q38: TBD | V38: =IF(Q38="TBD","",H38*R38*IF(Q38="OK",1,IF(Q38="OK/Minor",0.85,IF(Q38="Minor disc.",0.7,IF(Q38="Major disc.",0.45,IF(Q38="MISS",0.25,0)))))) | W38: TBD | AB38: =IF(W38="TBD","",H38*X38*IF(W38="OK",1,IF(W38="OK/Minor",0.85,IF(W38="Minor disc.",0.7,IF(W38="Major disc.",0.45,IF(W38="MISS",0.25,0)))))) | AC38: =IF(AND(Q38="TBD",W38="TBD"),"Not yet evaluated — awaiting bidder review.",IF(Q38="TBD",CONCATENATE("Bidder B: ",W38," — ",IF(AA38="","(no comment)",AA38)," | Bidder A not yet evaluated."),IF(W38="TBD",CONCATENATE("Bidder A: ",Q38," — ",IF(U38="","(no comment)",U38)," | Bidder B not yet evaluated."),CONCATENATE("Bidder A: ",Q38," — ",IF(U38="","(no comment)",U38)," || Bidder B: ",W38," — ",IF(AA38="","(no comment)",AA38)," | ",IF(Q38=W38,"Comparable disposition.","Diverging disposition — flag for negotiation.")))))
A39: 34 | B39: T3 Contextual | C39: OFFER-14 | D39: Expansion Joint Design & Risk Justification | E39: §4.4.1.1 | F39: Configuration / Layout / Support | G39: Quality / Verifiability | H39: 22.6667 | I39: 32.6531 | J39: No | K39: Submit and review the named deliverable with RTM traceability and approval status; Document review, inspection, certification, audit or traceable QC record | L39: Offer response: Expansion Joint Design & Risk Justification; Quality Assurance Plan (QAP); Risk Assessment / HAZOP / FMECA | M39: L0 Tender / Offer; L1 Conceptual Design; L2 Detailed Design | N39: RTM-079 | P39: OK | Q39: TBD | V39: =IF(Q39="TBD","",H39*R39*IF(Q39="OK",1,IF(Q39="OK/Minor",0.85,IF(Q39="Minor disc.",0.7,IF(Q39="Major disc.",0.45,IF(Q39="MISS",0.25,0)))))) | W39: TBD | AB39: =IF(W39="TBD","",H39*X39*IF(W39="OK",1,IF(W39="OK/Minor",0.85,IF(W39="Minor disc.",0.7,IF(W39="Major disc.",0.45,IF(W39="MISS",0.25,0)))))) | AC39: =IF(AND(Q39="TBD",W39="TBD"),"Not yet evaluated — awaiting bidder review.",IF(Q39="TBD",CONCATENATE("Bidder B: ",W39," — ",IF(AA39="","(no comment)",AA39)," | Bidder A not yet evaluated."),IF(W39="TBD",CONCATENATE("Bidder A: ",Q39," — ",IF(U39="","(no comment)",U39)," | Bidder B not yet evaluated."),CONCATENATE("Bidder A: ",Q39," — ",IF(U39="","(no comment)",U39)," || Bidder B: ",W39," — ",IF(AA39="","(no comment)",AA39)," | ",IF(Q39=W39,"Comparable disposition.","Diverging disposition — flag for negotiation.")))))
A40: 35 | B40: T3 Contextual | C40: OFFER-07 | D40: Header Design Pressure & Temperature Definition | E40: §4.2.4 | F40: Performance / Process / Utilities | G40: Performance | H40: 20 | I40: 27.551 | J40: No | K40: Submit and review the named deliverable with RTM traceability and approval status; Calculation/model plus calibrated measurement or recorded trend | L40: Offer response: Header Design Pressure & Temperature Definition | M40: L0 Tender / Offer; L1 Conceptual Design; L2 Detailed Design | N40: RTM-040..RTM-044 | P40: OK | Q40: TBD | V40: =IF(Q40="TBD","",H40*R40*IF(Q40="OK",1,IF(Q40="OK/Minor",0.85,IF(Q40="Minor disc.",0.7,IF(Q40="Major disc.",0.45,IF(Q40="MISS",0.25,0)))))) | W40: TBD | AB40: =IF(W40="TBD","",H40*X40*IF(W40="OK",1,IF(W40="OK/Minor",0.85,IF(W40="Minor disc.",0.7,IF(W40="Major disc.",0.45,IF(W40="MISS",0.25,0)))))) | AC40: =IF(AND(Q40="TBD",W40="TBD"),"Not yet evaluated — awaiting bidder review.",IF(Q40="TBD",CONCATENATE("Bidder B: ",W40," — ",IF(AA40="","(no comment)",AA40)," | Bidder A not yet evaluated."),IF(W40="TBD",CONCATENATE("Bidder A: ",Q40," — ",IF(U40="","(no comment)",U40)," | Bidder B not yet evaluated."),CONCATENATE("Bidder A: ",Q40," — ",IF(U40="","(no comment)",U40)," || Bidder B: ",W40," — ",IF(AA40="","(no comment)",AA40)," | ",IF(Q40=W40,"Comparable disposition.","Diverging disposition — flag for negotiation.")))))
A41: 36 | B41: T3 Contextual | C41: OFFER-08 | D41: LN2 Precooling Design Decision | E41: §4.2.5 | F41: Performance / Process / Utilities | G41: Performance | H41: 20 | I41: 27.551 | J41: No | K41: Submit and review the named deliverable with RTM traceability and approval status; Calculation/model plus calibrated measurement or recorded trend | L41: Offer response: LN2 Precooling Design Decision | M41: L0 Tender / Offer; L1 Conceptual Design; L2 Detailed Design | N41: RTM-045 | O41: RTM-046..RTM-047 | P41: OK | Q41: TBD | V41: =IF(Q41="TBD","",H41*R41*IF(Q41="OK",1,IF(Q41="OK/Minor",0.85,IF(Q41="Minor disc.",0.7,IF(Q41="Major disc.",0.45,IF(Q41="MISS",0.25,0)))))) | W41: TBD | AB41: =IF(W41="TBD","",H41*X41*IF(W41="OK",1,IF(W41="OK/Minor",0.85,IF(W41="Minor disc.",0.7,IF(W41="Major disc.",0.45,IF(W41="MISS",0.25,0)))))) | AC41: =IF(AND(Q41="TBD",W41="TBD"),"Not yet evaluated — awaiting bidder review.",IF(Q41="TBD",CONCATENATE("Bidder B: ",W41," — ",IF(AA41="","(no comment)",AA41)," | Bidder A not yet evaluated."),IF(W41="TBD",CONCATENATE("Bidder A: ",Q41," — ",IF(U41="","(no comment)",U41)," | Bidder B not yet evaluated."),CONCATENATE("Bidder A: ",Q41," — ",IF(U41="","(no comment)",U41)," || Bidder B: ",W41," — ",IF(AA41="","(no comment)",AA41)," | ",IF(Q41=W41,"Comparable disposition.","Diverging disposition — flag for negotiation.")))))
A42: 37 | B42: T3 Contextual | C42: OFFER-12 | D42: Performance Efficiency (invCOP) Declaration | E42: §4.3.4 | F42: Performance / Process / Utilities | G42: Performance | H42: 20 | I42: 27.551 | J42: No | K42: Submit and review the named deliverable with RTM traceability and approval status; Calculation/model plus calibrated measurement or recorded trend | L42: Offer response: Performance Efficiency (invCOP) Declaration | M42: L0 Tender / Offer; L1 Conceptual Design; L2 Detailed Design | N42: RTM-069..RTM-072 | O42: RTM-073..RTM-077 | P42: OK — Review breadth | Q42: TBD | V42: =IF(Q42="TBD","",H42*R42*IF(Q42="OK",1,IF(Q42="OK/Minor",0.85,IF(Q42="Minor disc.",0.7,IF(Q42="Major disc.",0.45,IF(Q42="MISS",0.25,0)))))) | W42: TBD | AB42: =IF(W42="TBD","",H42*X42*IF(W42="OK",1,IF(W42="OK/Minor",0.85,IF(W42="Minor disc.",0.7,IF(W42="Major disc.",0.45,IF(W42="MISS",0.25,0)))))) | AC42: =IF(AND(Q42="TBD",W42="TBD"),"Not yet evaluated — awaiting bidder review.",IF(Q42="TBD",CONCATENATE("Bidder B: ",W42," — ",IF(AA42="","(no comment)",AA42)," | Bidder A not yet evaluated."),IF(W42="TBD",CONCATENATE("Bidder A: ",Q42," — ",IF(U42="","(no comment)",U42)," | Bidder B not yet evaluated."),CONCATENATE("Bidder A: ",Q42," — ",IF(U42="","(no comment)",U42)," || Bidder B: ",W42," — ",IF(AA42="","(no comment)",AA42)," | ",IF(Q42=W42,"Comparable disposition.","Diverging disposition — flag for negotiation.")))))
A43: 38 | B43: T3 Contextual | C43: OFFER-23 | D43: User Configuration Filling Performance | E43: §4.4.8.1 | F43: Performance / Process / Utilities | G43: Functional | H43: 20 | I43: 27.551 | J43: No | K43: Submit and review the named deliverable with RTM traceability and approval status; Calculation/model plus calibrated measurement or recorded trend; Functional design/configuration review and sequence/interface demonstration | L43: Offer response: User Configuration Filling Performance | M43: L0 Tender / Offer; L1 Conceptual Design; L2 Detailed Design | N43: RTM-268..RTM-272 | P43: OK | Q43: TBD | V43: =IF(Q43="TBD","",H43*R43*IF(Q43="OK",1,IF(Q43="OK/Minor",0.85,IF(Q43="Minor disc.",0.7,IF(Q43="Major disc.",0.45,IF(Q43="MISS",0.25,0)))))) | W43: TBD | AB43: =IF(W43="TBD","",H43*X43*IF(W43="OK",1,IF(W43="OK/Minor",0.85,IF(W43="Minor disc.",0.7,IF(W43="Major disc.",0.45,IF(W43="MISS",0.25,0)))))) | AC43: =IF(AND(Q43="TBD",W43="TBD"),"Not yet evaluated — awaiting bidder review.",IF(Q43="TBD",CONCATENATE("Bidder B: ",W43," — ",IF(AA43="","(no comment)",AA43)," | Bidder A not yet evaluated."),IF(W43="TBD",CONCATENATE("Bidder A: ",Q43," — ",IF(U43="","(no comment)",U43)," | Bidder B not yet evaluated."),CONCATENATE("Bidder A: ",Q43," — ",IF(U43="","(no comment)",U43)," || Bidder B: ",W43," — ",IF(AA43="","(no comment)",AA43)," | ",IF(Q43=W43,"Comparable disposition.","Diverging disposition — flag for negotiation.")))))
A44: 39 | B44: T3 Contextual | C44: OFFER-36 | D44: 3D Model Platform & CAD Delivery | E44: §4.8.1.2 | F44: Configuration / Layout / Support | G44: Functional | H44: 18.6667 | I44: 21.4286 | J44: No | K44: Submit and review the named deliverable with RTM traceability and approval status; Document review, inspection, certification, audit or traceable QC record | L44: Offer response: 3D Model Platform & CAD Delivery; 3D / CAD Model | M44: L0 Tender / Offer; L1 Conceptual Design; L2 Detailed Design | N44: RTM-445..RTM-449 | P44: OK | Q44: TBD | V44: =IF(Q44="TBD","",H44*R44*IF(Q44="OK",1,IF(Q44="OK/Minor",0.85,IF(Q44="Minor disc.",0.7,IF(Q44="Major disc.",0.45,IF(Q44="MISS",0.25,0)))))) | W44: TBD | AB44: =IF(W44="TBD","",H44*X44*IF(W44="OK",1,IF(W44="OK/Minor",0.85,IF(W44="Minor disc.",0.7,IF(W44="Major disc.",0.45,IF(W44="MISS",0.25,0)))))) | AC44: =IF(AND(Q44="TBD",W44="TBD"),"Not yet evaluated — awaiting bidder review.",IF(Q44="TBD",CONCATENATE("Bidder B: ",W44," — ",IF(AA44="","(no comment)",AA44)," | Bidder A not yet evaluated."),IF(W44="TBD",CONCATENATE("Bidder A: ",Q44," — ",IF(U44="","(no comment)",U44)," | Bidder B not yet evaluated."),CONCATENATE("Bidder A: ",Q44," — ",IF(U44="","(no comment)",U44)," || Bidder B: ",W44," — ",IF(AA44="","(no comment)",AA44)," | ",IF(Q44=W44,"Comparable disposition.","Diverging disposition — flag for negotiation.")))))
A45: 40 | B45: T3 Contextual | C45: OFFER-40 | D45: Electrical Power Measurement Methodology | E45: §4.13.3.3.7 | F45: Performance / Process / Utilities | G45: Quality / Verifiability | H45: 18.6667 | I45: 21.4286 | J45: No | K45: Submit and review the named deliverable with RTM traceability and approval status; Document review, inspection, certification, audit or traceable QC record | L45: Offer response: Electrical Power Measurement Methodology | M45: L0 Tender / Offer; L1 Conceptual Design; L2 Detailed Design | N45: RTM-542..RTM-544 | P45: OK | Q45: TBD | V45: =IF(Q45="TBD","",H45*R45*IF(Q45="OK",1,IF(Q45="OK/Minor",0.85,IF(Q45="Minor disc.",0.7,IF(Q45="Major disc.",0.45,IF(Q45="MISS",0.25,0)))))) | W45: TBD | AB45: =IF(W45="TBD","",H45*X45*IF(W45="OK",1,IF(W45="OK/Minor",0.85,IF(W45="Minor disc.",0.7,IF(W45="Major disc.",0.45,IF(W45="MISS",0.25,0)))))) | AC45: =IF(AND(Q45="TBD",W45="TBD"),"Not yet evaluated — awaiting bidder review.",IF(Q45="TBD",CONCATENATE("Bidder B: ",W45," — ",IF(AA45="","(no comment)",AA45)," | Bidder A not yet evaluated."),IF(W45="TBD",CONCATENATE("Bidder A: ",Q45," — ",IF(U45="","(no comment)",U45)," | Bidder B not yet evaluated."),CONCATENATE("Bidder A: ",Q45," — ",IF(U45="","(no comment)",U45)," || Bidder B: ",W45," — ",IF(AA45="","(no comment)",AA45)," | ",IF(Q45=W45,"Comparable disposition.","Diverging disposition — flag for negotiation.")))))
A46: 41 | B46: T3 Contextual | C46: OFFER-31 | D46: Cold Box Environmental Requirements | E46: §4.7.1 | F46: Configuration / Layout / Support | G46: Functional | H46: 17.3333 | I46: 17.3469 | J46: No | K46: Submit and review the named deliverable with RTM traceability and approval status | L46: Offer response: Cold Box Environmental Requirements | M46: L0 Tender / Offer; L1 Conceptual Design; L2 Detailed Design | N46: RTM-386..RTM-387 | P46: OK | Q46: TBD | V46: =IF(Q46="TBD","",H46*R46*IF(Q46="OK",1,IF(Q46="OK/Minor",0.85,IF(Q46="Minor disc.",0.7,IF(Q46="Major disc.",0.45,IF(Q46="MISS",0.25,0)))))) | W46: TBD | AB46: =IF(W46="TBD","",H46*X46*IF(W46="OK",1,IF(W46="OK/Minor",0.85,IF(W46="Minor disc.",0.7,IF(W46="Major disc.",0.45,IF(W46="MISS",0.25,0)))))) | AC46: =IF(AND(Q46="TBD",W46="TBD"),"Not yet evaluated — awaiting bidder review.",IF(Q46="TBD",CONCATENATE("Bidder B: ",W46," — ",IF(AA46="","(no comment)",AA46)," | Bidder A not yet evaluated."),IF(W46="TBD",CONCATENATE("Bidder A: ",Q46," — ",IF(U46="","(no comment)",U46)," | Bidder B not yet evaluated."),CONCATENATE("Bidder A: ",Q46," — ",IF(U46="","(no comment)",U46)," || Bidder B: ",W46," — ",IF(AA46="","(no comment)",AA46)," | ",IF(Q46=W46,"Comparable disposition.","Diverging disposition — flag for negotiation.")))))
A47: 42 | B47: T3 Contextual | C47: OFFER-32 | D47: Equipment Transport & Installation Constraints | E47: §4.7.2 | F47: Configuration / Layout / Support | G47: Functional | H47: 17.3333 | I47: 17.3469 | J47: No | K47: Submit and review the named deliverable with RTM traceability and approval status | L47: Offer response: Equipment Transport & Installation Constraints | M47: L0 Tender / Offer; L1 Conceptual Design; L2 Detailed Design | N47: RTM-388..RTM-394 | P47: OK | Q47: TBD | V47: =IF(Q47="TBD","",H47*R47*IF(Q47="OK",1,IF(Q47="OK/Minor",0.85,IF(Q47="Minor disc.",0.7,IF(Q47="Major disc.",0.45,IF(Q47="MISS",0.25,0)))))) | W47: TBD | AB47: =IF(W47="TBD","",H47*X47*IF(W47="OK",1,IF(W47="OK/Minor",0.85,IF(W47="Minor disc.",0.7,IF(W47="Major disc.",0.45,IF(W47="MISS",0.25,0)))))) | AC47: =IF(AND(Q47="TBD",W47="TBD"),"Not yet evaluated — awaiting bidder review.",IF(Q47="TBD",CONCATENATE("Bidder B: ",W47," — ",IF(AA47="","(no comment)",AA47)," | Bidder A not yet evaluated."),IF(W47="TBD",CONCATENATE("Bidder A: ",Q47," — ",IF(U47="","(no comment)",U47)," | Bidder B not yet evaluated."),CONCATENATE("Bidder A: ",Q47," — ",IF(U47="","(no comment)",U47)," || Bidder B: ",W47," — ",IF(AA47="","(no comment)",AA47)," | ",IF(Q47=W47,"Comparable disposition.","Diverging disposition — flag for negotiation.")))))
A48: 43 | B48: T3 Contextual | C48: OFFER-25 | D48: Supplier Experience & Reference Justification | E48: §4.6.4.5 | F48: Controls / Software / Management | G48: Functional | H48: 16 | I48: 11.2245 | J48: No | K48: Submit and review the named deliverable with RTM traceability and approval status | L48: Offer response: Supplier Experience & Reference Justification | M48: L0 Tender / Offer; L1 Conceptual Design; L2 Detailed Design | N48: RTM-321..RTM-327 | P48: OK | Q48: TBD | V48: =IF(Q48="TBD","",H48*R48*IF(Q48="OK",1,IF(Q48="OK/Minor",0.85,IF(Q48="Minor disc.",0.7,IF(Q48="Major disc.",0.45,IF(Q48="MISS",0.25,0)))))) | W48: TBD | AB48: =IF(W48="TBD","",H48*X48*IF(W48="OK",1,IF(W48="OK/Minor",0.85,IF(W48="Minor disc.",0.7,IF(W48="Major disc.",0.45,IF(W48="MISS",0.25,0)))))) | AC48: =IF(AND(Q48="TBD",W48="TBD"),"Not yet evaluated — awaiting bidder review.",IF(Q48="TBD",CONCATENATE("Bidder B: ",W48," — ",IF(AA48="","(no comment)",AA48)," | Bidder A not yet evaluated."),IF(W48="TBD",CONCATENATE("Bidder A: ",Q48," — ",IF(U48="","(no comment)",U48)," | Bidder B not yet evaluated."),CONCATENATE("Bidder A: ",Q48," — ",IF(U48="","(no comment)",U48)," || Bidder B: ",W48," — ",IF(AA48="","(no comment)",AA48)," | ",IF(Q48=W48,"Comparable disposition.","Diverging disposition — flag for negotiation.")))))
A49: 44 | B49: T3 Contextual | C49: OFFER-26 | D49: Software Architecture & Development Scope | E49: §4.6.7 | F49: Controls / Software / Management | G49: Functional | H49: 16 | I49: 11.2245 | J49: No | K49: Submit and review the named deliverable with RTM traceability and approval status; Functional design/configuration review and sequence/interface demonstration | L49: Offer response: Software Architecture & Development Scope | M49: L0 Tender / Offer; L1 Conceptual Design; L2 Detailed Design | N49: RTM-334..RTM-339 | O49: RTM-340..RTM-345 | P49: OK | Q49: TBD | V49: =IF(Q49="TBD","",H49*R49*IF(Q49="OK",1,IF(Q49="OK/Minor",0.85,IF(Q49="Minor disc.",0.7,IF(Q49="Major disc.",0.45,IF(Q49="MISS",0.25,0)))))) | W49: TBD | AB49: =IF(W49="TBD","",H49*X49*IF(W49="OK",1,IF(W49="OK/Minor",0.85,IF(W49="Minor disc.",0.7,IF(W49="Major disc.",0.45,IF(W49="MISS",0.25,0)))))) | AC49: =IF(AND(Q49="TBD",W49="TBD"),"Not yet evaluated — awaiting bidder review.",IF(Q49="TBD",CONCATENATE("Bidder B: ",W49," — ",IF(AA49="","(no comment)",AA49)," | Bidder A not yet evaluated."),IF(W49="TBD",CONCATENATE("Bidder A: ",Q49," — ",IF(U49="","(no comment)",U49)," | Bidder B not yet evaluated."),CONCATENATE("Bidder A: ",Q49," — ",IF(U49="","(no comment)",U49)," || Bidder B: ",W49," — ",IF(AA49="","(no comment)",AA49)," | ",IF(Q49=W49,"Comparable disposition.","Diverging disposition — flag for negotiation.")))))
A50: 45 | B50: T3 Contextual | C50: OFFER-28 | D50: Functional Analysis & Control Sequences | E50: §4.6.7 | F50: Controls / Software / Management | G50: Functional | H50: 16 | I50: 11.2245 | J50: No | K50: Submit and review the named deliverable with RTM traceability and approval status; Functional design/configuration review and sequence/interface demonstration | L50: Offer response: Functional Analysis & Control Sequences | M50: L0 Tender / Offer; L1 Conceptual Design; L2 Detailed Design | N50: RTM-342; RTM-345 | O50: RTM-334..RTM-341; RTM-343..RTM-344 | P50: OK | Q50: TBD | V50: =IF(Q50="TBD","",H50*R50*IF(Q50="OK",1,IF(Q50="OK/Minor",0.85,IF(Q50="Minor disc.",0.7,IF(Q50="Major disc.",0.45,IF(Q50="MISS",0.25,0)))))) | W50: TBD | AB50: =IF(W50="TBD","",H50*X50*IF(W50="OK",1,IF(W50="OK/Minor",0.85,IF(W50="Minor disc.",0.7,IF(W50="Major disc.",0.45,IF(W50="MISS",0.25,0)))))) | AC50: =IF(AND(Q50="TBD",W50="TBD"),"Not yet evaluated — awaiting bidder review.",IF(Q50="TBD",CONCATENATE("Bidder B: ",W50," — ",IF(AA50="","(no comment)",AA50)," | Bidder A not yet evaluated."),IF(W50="TBD",CONCATENATE("Bidder A: ",Q50," — ",IF(U50="","(no comment)",U50)," | Bidder B not yet evaluated."),CONCATENATE("Bidder A: ",Q50," — ",IF(U50="","(no comment)",U50)," || Bidder B: ",W50," — ",IF(AA50="","(no comment)",AA50)," | ",IF(Q50=W50,"Comparable disposition.","Diverging disposition — flag for negotiation.")))))
A51: 46 | B51: T3 Contextual | C51: OFFER-30 | D51: Software Change Management Process | E51: §4.6.9 | F51: Controls / Software / Management | G51: Functional | H51: 16 | I51: 11.2245 | J51: No | K51: Submit and review the named deliverable with RTM traceability and approval status; Functional design/configuration review and sequence/interface demonstration | L51: Offer response: Software Change Management Process | M51: L0 Tender / Offer; L1 Conceptual Design; L2 Detailed Design | N51: RTM-368..RTM-370 | P51: OK | Q51: TBD | V51: =IF(Q51="TBD","",H51*R51*IF(Q51="OK",1,IF(Q51="OK/Minor",0.85,IF(Q51="Minor disc.",0.7,IF(Q51="Major disc.",0.45,IF(Q51="MISS",0.25,0)))))) | W51: TBD | AB51: =IF(W51="TBD","",H51*X51*IF(W51="OK",1,IF(W51="OK/Minor",0.85,IF(W51="Minor disc.",0.7,IF(W51="Major disc.",0.45,IF(W51="MISS",0.25,0)))))) | AC51: =IF(AND(Q51="TBD",W51="TBD"),"Not yet evaluated — awaiting bidder review.",IF(Q51="TBD",CONCATENATE("Bidder B: ",W51," — ",IF(AA51="","(no comment)",AA51)," | Bidder A not yet evaluated."),IF(W51="TBD",CONCATENATE("Bidder A: ",Q51," — ",IF(U51="","(no comment)",U51)," | Bidder B not yet evaluated."),CONCATENATE("Bidder A: ",Q51," — ",IF(U51="","(no comment)",U51)," || Bidder B: ",W51," — ",IF(AA51="","(no comment)",AA51)," | ",IF(Q51=W51,"Comparable disposition.","Diverging disposition — flag for negotiation.")))))
A52: 47 | B52: T3 Contextual | C52: OFFER-38 | D52: Training Program & Competency Definition | E52: §4.12.1 | F52: Configuration / Layout / Support | G52: Safety / Legal | H52: 14.3333 | I52: 6.1224 | J52: No | K52: Submit and review the named deliverable with RTM traceability and approval status | L52: Offer response: Training Program & Competency Definition; Training Programme / Materials | M52: L0 Tender / Offer; L1 Conceptual Design; L2 Detailed Design | N52: RTM-483..RTM-490 | P52: OK | Q52: TBD | V52: =IF(Q52="TBD","",H52*R52*IF(Q52="OK",1,IF(Q52="OK/Minor",0.85,IF(Q52="Minor disc.",0.7,IF(Q52="Major disc.",0.45,IF(Q52="MISS",0.25,0)))))) | W52: TBD | AB52: =IF(W52="TBD","",H52*X52*IF(W52="OK",1,IF(W52="OK/Minor",0.85,IF(W52="Minor disc.",0.7,IF(W52="Major disc.",0.45,IF(W52="MISS",0.25,0)))))) | AC52: =IF(AND(Q52="TBD",W52="TBD"),"Not yet evaluated — awaiting bidder review.",IF(Q52="TBD",CONCATENATE("Bidder B: ",W52," — ",IF(AA52="","(no comment)",AA52)," | Bidder A not yet evaluated."),IF(W52="TBD",CONCATENATE("Bidder A: ",Q52," — ",IF(U52="","(no comment)",U52)," | Bidder B not yet evaluated."),CONCATENATE("Bidder A: ",Q52," — ",IF(U52="","(no comment)",U52)," || Bidder B: ",W52," — ",IF(AA52="","(no comment)",AA52)," | ",IF(Q52=W52,"Comparable disposition.","Diverging disposition — flag for negotiation.")))))
A53: 48 | B53: T3 Contextual | C53: OFFER-46 | D53: Risk Assessment & Mitigation Strategy | E53: §7.5 | F53: Reliability / RAM / Service | G53: Safety / Legal | H53: 12 | I53: 4.0816 | J53: No | K53: Submit and review the named deliverable with RTM traceability and approval status | L53: Offer response: Risk Assessment & Mitigation Strategy; Risk Assessment / HAZOP / FMECA | M53: L0 Tender / Offer; L1 Conceptual Design; L2 Detailed Design; L3 Procurement & Manufacturing / FAT; L4 Installation; L5 Standalone Commissioning; L6 Site Acceptance Testing | N53: RTM-640 | P53: OK | Q53: TBD | V53: =IF(Q53="TBD","",H53*R53*IF(Q53="OK",1,IF(Q53="OK/Minor",0.85,IF(Q53="Minor disc.",0.7,IF(Q53="Major disc.",0.45,IF(Q53="MISS",0.25,0)))))) | W53: TBD | AB53: =IF(W53="TBD","",H53*X53*IF(W53="OK",1,IF(W53="OK/Minor",0.85,IF(W53="Minor disc.",0.7,IF(W53="Major disc.",0.45,IF(W53="MISS",0.25,0)))))) | AC53: =IF(AND(Q53="TBD",W53="TBD"),"Not yet evaluated — awaiting bidder review.",IF(Q53="TBD",CONCATENATE("Bidder B: ",W53," — ",IF(AA53="","(no comment)",AA53)," | Bidder A not yet evaluated."),IF(W53="TBD",CONCATENATE("Bidder A: ",Q53," — ",IF(U53="","(no comment)",U53)," | Bidder B not yet evaluated."),CONCATENATE("Bidder A: ",Q53," — ",IF(U53="","(no comment)",U53)," || Bidder B: ",W53," — ",IF(AA53="","(no comment)",AA53)," | ",IF(Q53=W53,"Comparable disposition.","Diverging disposition — flag for negotiation.")))))
A54: 49 | B54: T3 Contextual | C54: OFFER-13 | D54: Main Equipment Technical Specifications | E54: §4.4 | F54: Performance / Process / Utilities | G54: Functional | H54: 10.6667 | I54: 2.0408 | J54: No | K54: Submit and review the named deliverable with RTM traceability and approval status | L54: Offer response: Main Equipment Technical Specifications | M54: L0 Tender / Offer; L1 Conceptual Design; L2 Detailed Design | O54: RTM-141..RTM-152; RTM-193..RTM-197; RTM-236..RTM-257; RTM-263..RTM-267 | P54: Review — breadth | Q54: TBD | V54: =IF(Q54="TBD","",H54*R54*IF(Q54="OK",1,IF(Q54="OK/Minor",0.85,IF(Q54="Minor disc.",0.7,IF(Q54="Major disc.",0.45,IF(Q54="MISS",0.25,0)))))) | W54: TBD | AB54: =IF(W54="TBD","",H54*X54*IF(W54="OK",1,IF(W54="OK/Minor",0.85,IF(W54="Minor disc.",0.7,IF(W54="Major disc.",0.45,IF(W54="MISS",0.25,0)))))) | AC54: =IF(AND(Q54="TBD",W54="TBD"),"Not yet evaluated — awaiting bidder review.",IF(Q54="TBD",CONCATENATE("Bidder B: ",W54," — ",IF(AA54="","(no comment)",AA54)," | Bidder A not yet evaluated."),IF(W54="TBD",CONCATENATE("Bidder A: ",Q54," — ",IF(U54="","(no comment)",U54)," | Bidder B not yet evaluated."),CONCATENATE("Bidder A: ",Q54," — ",IF(U54="","(no comment)",U54)," || Bidder B: ",W54," — ",IF(AA54="","(no comment)",AA54)," | ",IF(Q54=W54,"Comparable disposition.","Diverging disposition — flag for negotiation.")))))
A55: 50 | B55: T3 Contextual | C55: OFFER-44 | D55: Project Schedule & Milestone Definition | E55: §6.2 | F55: Configuration / Layout / Support | G55: Functional | H55: 6.3333 | I55: 0 | J55: No | K55: Submit and review the named deliverable with RTM traceability and approval status | L55: Offer response: Project Schedule & Milestone Definition; Schedule / milestone plan | M55: L0 Tender / Offer; L1 Conceptual Design; L2 Detailed Design; L3 Procurement & Manufacturing / FAT; L4 Installation; L5 Standalone Commissioning; L6 Site Acceptance Testing | O55: RTM-614..RTM-620 | P55: OK — non-RTM source | Q55: TBD | V55: =IF(Q55="TBD","",H55*R55*IF(Q55="OK",1,IF(Q55="OK/Minor",0.85,IF(Q55="Minor disc.",0.7,IF(Q55="Major disc.",0.45,IF(Q55="MISS",0.25,0)))))) | W55: TBD | AB55: =IF(W55="TBD","",H55*X55*IF(W55="OK",1,IF(W55="OK/Minor",0.85,IF(W55="Minor disc.",0.7,IF(W55="Major disc.",0.45,IF(W55="MISS",0.25,0)))))) | AC55: =IF(AND(Q55="TBD",W55="TBD"),"Not yet evaluated — awaiting bidder review.",IF(Q55="TBD",CONCATENATE("Bidder B: ",W55," — ",IF(AA55="","(no comment)",AA55)," | Bidder A not yet evaluated."),IF(W55="TBD",CONCATENATE("Bidder A: ",Q55," — ",IF(U55="","(no comment)",U55)," | Bidder B not yet evaluated."),CONCATENATE("Bidder A: ",Q55," — ",IF(U55="","(no comment)",U55)," || Bidder B: ",W55," — ",IF(AA55="","(no comment)",AA55)," | ",IF(Q55=W55,"Comparable disposition.","Diverging disposition — flag for negotiation.")))))

Sheet OFFER_CANONICAL
A1: Canonical OFFER register
A2: Canonical contract wording, RTM anchors, standards, evidence and phases.
A3: =HYPERLINK("#START_HERE!A1","Start") | B3: =HYPERLINK("#DASHBOARD!A1","Dashboard") | C3: =HYPERLINK("#OFFER_RANKING!A1","Ranking") | D3: =HYPERLINK("#EVALUATION_INPUT!A1","Evaluate") | E3: =HYPERLINK("#OFFER_CANONICAL!A1","Canonical") | F3: =HYPERLINK("#RTM_CROSSWALK!A1","Crosswalk") | G3: =HYPERLINK("#WEIGHTS_METHOD!A1","Method")
A5: offer_id | B5: title | C5: page_start_pdf | D5: section_number | E5: section_title | F5: Applicant_DocList_Item | G5: EPIC | H5: Category | I5: offer_statement_verbatim | J5: full_verbatim_offer | K5: primary_rtm_ids | L5: supporting_context_rtm_ids | M5: total_link_count | N5: link_basis_summary | O5: review_flag | P5: canonical_source | Q5: Reference Code / Standard | R5: Actual Explicit Code / Standard | S5: Fulfilment / Evidence / Measurability | T5: Explicit Deliverable / Proof | U5: Applicable Phase(s) | V5: Evidence Basis / Review
A6: OFFER-01 | B6: Tender Compliance Confirmation | C6: 24 | D6: 4.1 | E6: General Requirements | F6: 8.4 | G6: COMMERCIAL | H6: Governance | I6: In the offer, the Applicant shall explicitly confirm that: | J6: In the offer, the Applicant shall explicitly confirm that: • All SCK CEN’s Tender Documents have been duly analysed • The information provided therein is considered sufficient to allow the Applicant to submit a compliant proposal ensuring that the supplied items meet the specified requirements. • Any missing or insufficient information identified has been formally notified to SCK CEN without undue delay, in accordance with §1.13 of the Main Tender Document. | K6: RTM-001; RTM-003 | L6: RTM-002; RTM-004 | M6: 4 | N6: Exact canonical section, with child/supporting RTMs classified separately where applicable. | O6: OK | P6: SCK CEN/90508872 PDF+DOCX (08-Apr-2026) | Q6: SCK CEN/90508872 §4.1; no named external code in OFFER text | R6: None explicitly named in the OFFER text | S6: Submit and review the named deliverable with RTM traceability and approval status; Document review, inspection, certification, audit or traceable QC record; Conformity/safety assessment, certification and approved safety evidence | T6: Offer response: Tender Compliance Confirmation | U6: L0 Tender / Offer; L1 Conceptual Design; L2 Detailed Design | V6: OFFER-stage evidence; linked standards are contextual; does not prove full RTM compliance
A7: OFFER-02 | B7: Assumptions, Deviations & Additions Register | C7: 24 | D7: 4.1 | E7: General Requirements | F7: 8.5 | G7: PROJECT_EXECUTION | H7: Deliverables | I7: In the offer, the Applicant shall submit separate and explicit lists for each of the following cases. Each item listed shall be supported by a clear description and duly justification in the offer. | J7: In the offer, the Applicant shall submit separate and explicit lists for each of the following cases. Each item listed shall be supported by a clear description and duly justification in the offer. • Any additional requirements defined by the Applicant (beyond those specified by SCK CEN), which are considered necessary to fulfil the intended function, performance, or integration of the proposed solution. • Any assumptions which have been defined by the Applicant, which are considered necessary to evaluate the offer. • Any deviation of the specified technical requirements, including the proposed alternative solution. This shall include, but is not limited to, any deviations from requested norms, standards, or preferred process parameters. • Any suggested modifications vis-à-vis the technical requirements as imposed by SCK CEN; such suggestions shall be presented for consideration only and shall not be treated as deviations. Suggested modifications should, in the Applicant’s opinion, constitute an improvement in terms of cost, reliability, safety, ease of use, or other functional aspects of the QPS. Each suggested modification shall be supported by an assessment of its advantages and drawbacks. | K7: RTM-004 | L7: RTM-001..RTM-003 | M7: 4 | N7: Exact canonical section, with child/supporting RTMs classified separately where applicable. | O7: OK | P7: SCK CEN/90508872 PDF+DOCX (08-Apr-2026) | Q7: SCK CEN/90508872 §4.1; no named external code in OFFER text | R7: None explicitly named in the OFFER text | S7: Submit and review the named deliverable with RTM traceability and approval status; RAM/maintenance substantiation and recovery/failure-response evidence; Document review, inspection, certification, audit or traceable QC record | T7: Offer response: Assumptions, Deviations & Additions Register | U7: L0 Tender / Offer; L1 Conceptual Design; L2 Detailed Design | V7: OFFER-stage evidence; linked standards are contextual; does not prove full RTM compliance
A8: OFFER-03 | B8: Integrated Technical Proposal & Execution Strategy | C8: 25 | D8: 4.1 | E8: General Requirements | F8: 8.6 | G8: PROJECT_EXECUTION | H8: Planning & Scheduling | I8: In the offer, the Applicant shall: | J8: In the offer, the Applicant shall: • Submit a single, consolidated proposal, inclusive of all proposed deviations, representing the most optimal solution compliant with all conditions and requirements of the Contract. Multiple alternatives shall not be permitted. • Provide a clear overview of the (sequence of) activities that shall constitute the Contract performance. For each step in the sequence, the Applicant is to provide information regarding i.e. how the applicable requirements shall be met, the chosen process(es) and technique(s) that shall be implemented, etc. • Provide, as a minimum, the level of detail explicitly requested in the present document. Where no level of detail is specified, the Applicant shall determine and provide an appropriate level of detail based on its experience, proportionate to the criticality and/or complexity of the activity. | K8: RTM-002 | L8: RTM-001; RTM-003..RTM-004 | M8: 4 | N8: Exact canonical section, with child/supporting RTMs classified separately where applicable. | O8: OK | P8: SCK CEN/90508872 PDF+DOCX (08-Apr-2026) | Q8: SCK CEN/90508872 §4.1; no named external code in OFFER text | R8: None explicitly named in the OFFER text | S8: Submit and review the named deliverable with RTM traceability and approval status; Document review, inspection, certification, audit or traceable QC record; Conformity/safety assessment, certification and approved safety evidence | T8: Offer response: Integrated Technical Proposal & Execution Strategy | U8: L0 Tender / Offer; L1 Conceptual Design; L2 Detailed Design | V8: OFFER-stage evidence; linked standards are contextual; does not prove full RTM compliance
A9: OFFER-04 | B9: Cooldown & Thermal Performance Modelling | C9: 29 | D9: 4.2.2.2 | E9: Transient Operational Scenarios | F9: 8.7 | G9: SYSTEM_PERFORMANCE | H9: Cooldown Performance | I9: In their offer the Applicant shall indicate and substantiate using the Cryogenic User Transient Model: | J9: In their offer the Applicant shall indicate and substantiate using the Cryogenic User Transient Model: • the expected overall cooldown time from 300 K to 2 K. • the expected duration for each cool-down Scenario Transition. • the expected duration of each warm-up Scenario Transition, and the resulting constraints on the warm-up rate and mass flow of the users. • the expected maximum refrigeration power the QPS can sustain at discrete temperature levels between 250 K and 4.5 K (e.g. 250 K, 200 K, 150 K, 100 K, 50 K, 4.5 K). | K9: RTM-019..RTM-022 | M9: 4 | N9: Exact canonical section, with child/supporting RTMs classified separately where applicable. | O9: OK | P9: SCK CEN/90508872 PDF+DOCX (08-Apr-2026) | Q9: SCK CEN/90508872 §4.2.2.2; no named external code in OFFER text | R9: None explicitly named in the OFFER text | S9: Submit and review the named deliverable with RTM traceability and approval status; Calculation/model plus calibrated measurement or recorded trend; Document review, inspection, certification, audit or traceable QC record | T9: Offer response: Cooldown & Thermal Performance Modelling | U9: L0 Tender / Offer; L1 Conceptual Design; L2 Detailed Design | V9: OFFER-stage evidence; linked standards are contextual; does not prove full RTM compliance
A10: OFFER-05 | B10: Operational Procedure Strategy (Auto vs Manual) | C10: 31 | D10: 4.2.2.4.1 | E10: Purging and Conditioning | F10: 8.8 | G10: OPERATIONS_MAINTENANCE | H10: Operations Strategy | I10: In their offer, the Applicant shall state the type of procedure (automatic vs manual) they will implement. | J10: In their offer, the Applicant shall state the type of procedure (automatic vs manual) they will implement. | K10: RTM-025..RTM-027 | M10: 3 | N10: Exact canonical section, with child/supporting RTMs classified separately where applicable. | O10: OK | P10: SCK CEN/90508872 PDF+DOCX (08-Apr-2026) | Q10: SCK CEN/90508872 §4.2.2.4.1; no named external code in OFFER text | R10: None explicitly named in the OFFER text | S10: Submit and review the named deliverable with RTM traceability and approval status; Calculation/model plus calibrated measurement or recorded trend; Functional design/configuration review and sequence/interface demonstration | T10: Offer response: Operational Procedure Strategy (Auto vs Manual); Procedure / work instruction | U10: L0 Tender / Offer; L1 Conceptual Design; L2 Detailed Design | V10: OFFER-stage evidence; linked standards are contextual; does not prove full RTM compliance
A11: OFFER-06 | B11: LHe Filling & Emptying Performance | C11: 31 | D11: 4.2.2.4.3 | E11: LHe Filling / Emptying | F11: 8.9 | G11: SYSTEM_PERFORMANCE | H11: Filling/Emptying Performance | I11: In their offer, the Applicant shall state: | J11: In their offer, the Applicant shall state: • the expected duration of the LHe filling phase and the maximum continuous LHe filling rate the QPS can produce. • the expected duration of the LHe emptying phase and the maximum continuous emptying flow rate the QPS will be able to accommodate while preserving the helium inventory. | K11: RTM-030..RTM-033 | M11: 4 | N11: Exact canonical section, with child/supporting RTMs classified separately where applicable. | O11: OK | P11: SCK CEN/90508872 PDF+DOCX (08-Apr-2026) | Q11: SCK CEN/90508872 §4.2.2.4.3; no named external code in OFFER text | R11: None explicitly named in the OFFER text | S11: Submit and review the named deliverable with RTM traceability and approval status; Calculation/model plus calibrated measurement or recorded trend | T11: Offer response: LHe Filling & Emptying Performance | U11: L0 Tender / Offer; L1 Conceptual Design; L2 Detailed Design | V11: OFFER-stage evidence; linked standards are contextual; does not prove full RTM compliance
A12: OFFER-07 | B12: Header Design Pressure & Temperature Definition | C12: 34 | D12: 4.2.4 | E12: Cooling Capacity | F12: 8.10 | G12: PROCESS_DESIGN | H12: Thermodynamic Design | I12: In the offer, the Applicant shall: | J12: In the offer, the Applicant shall: • Indicate the design temperature and pressure on headers D and E. | K12: RTM-040..RTM-044 | M12: 5 | N12: Exact canonical section, with child/supporting RTMs classified separately where applicable. | O12: OK | P12: SCK CEN/90508872 PDF+DOCX (08-Apr-2026) | Q12: SCK CEN/90508872 §4.2.4; no named external code in OFFER text | R12: None explicitly named in the OFFER text | S12: Submit and review the named deliverable with RTM traceability and approval status; Calculation/model plus calibrated measurement or recorded trend | T12: Offer response: Header Design Pressure & Temperature Definition | U12: L0 Tender / Offer; L1 Conceptual Design; L2 Detailed Design | V12: OFFER-stage evidence; linked standards are contextual; does not prove full RTM compliance
A13: OFFER-08 | B13: LN2 Precooling Design Decision | C13: 35 | D13: 4.2.5 | E13: Liquid Nitrogen Precooling (Optional) | F13: 8.11 | G13: PROCESS_DESIGN | H13: LN2 Integration | I13: In the offer, the Applicant shall explicitly state whether LN2 Precooling will be part of the QPS design. | J13: In the offer, the Applicant shall explicitly state whether LN2 Precooling will be part of the QPS design. | K13: RTM-045 | L13: RTM-046..RTM-047 | M13: 3 | N13: Exact canonical section, with child/supporting RTMs classified separately where applicable. | O13: OK | P13: SCK CEN/90508872 PDF+DOCX (08-Apr-2026) | Q13: SCK CEN/90508872 §4.2.5; no named external code in OFFER text | R13: None explicitly named in the OFFER text | S13: Submit and review the named deliverable with RTM traceability and approval status; Calculation/model plus calibrated measurement or recorded trend | T13: Offer response: LN2 Precooling Design Decision | U13: L0 Tender / Offer; L1 Conceptual Design; L2 Detailed Design | V13: OFFER-stage evidence; linked standards are contextual; does not prove full RTM compliance
A14: OFFER-09 | B14: LN2 Techno-Economic Evaluation (CAPEX/OPEX) | C14: 35 | D14: 4.2.5 | E14: Liquid Nitrogen Precooling (Optional) | F14: 8.12 | G14: COMMERCIAL | H14: Cost Model | I14: In the offer, if LN2 Precooling will be implemented, the Applicant shall submit a quantified techno-economic justification substantiating the benefit of implementing LN2 precooling compared to an equivalent configuration without LN2 precooling. The justification shall, at minimum, include: | J14: In the offer, if LN2 Precooling will be implemented, the Applicant shall submit a quantified techno-economic justification substantiating the benefit of implementing LN2 precooling compared to an equivalent configuration without LN2 precooling. The justification shall, at minimum, include: • Capital cost (CAPEX) comparison and identification of the main cost drivers, including equipment, infrastructure, and integration costs. • Operating cost (OPEX) comparison (expressed in EUR for 10 years of operation) and identification of the main cost drivers, including LN2 consumption (average and peak), electricity consumption, and maintenance costs. • The logistics impact associated to the LN2 Precooling, including the expected delivery frequency, storage autonomy, and operational constraints of the LN2 supply. • The impact on the operational reliability and availability of the QPS. • The impact on the overall performance of the QPS. | L14: RTM-045..RTM-047 | M14: 3 | N14: Comparative techno-economic evidence is OFFER-only; RTMs are contextual. | O14: Review — accept context | P14: SCK CEN/90508872 PDF+DOCX (08-Apr-2026) | Q14: SCK CEN/90508872 §4.2.5; no named external code in OFFER text | R14: None explicitly named in the OFFER text | S14: Submit and review the named deliverable with RTM traceability and approval status; Calculation/model plus calibrated measurement or recorded trend; Functional design/configuration review and sequence/interface demonstration | T14: Offer response: LN2 Techno-Economic Evaluation (CAPEX/OPEX) | U14: L0 Tender / Offer; PAC / Handover; L1 Conceptual Design; L2 Detailed Design | V14: OFFER-stage evidence; linked standards are contextual; does not prove full RTM compliance
A15: OFFER-10 | B15: LN2 System Functional & Interface Design | C15: 35 | D15: 4.2.5 | E15: Liquid Nitrogen Precooling (Optional) | F15: 8.13 | G15: PROCESS_DESIGN | H15: LN2 Integration | I15: In the offer, if LN2 Precooling will be implemented, the Applicant shall: | J15: In the offer, if LN2 Precooling will be implemented, the Applicant shall: • describe its functional role within the refrigeration cycle. • identify all required LN2 interfaces with the site infrastructure. • specify the required LN2 flow rate and operating envelope (pressure and temperature). • specify the expected LN2 consumption, including average, peak, and transient demand, for planning of LN2 supply and replenishment logistics. • specify the QSN storage capacity (tank volume), including the operational autonomy between LN2 deliveries under nominal consumption. • confirming that all contractual performance requirements remain satisfied. | K15: RTM-046..RTM-047 | L15: RTM-045 | M15: 3 | N15: Exact canonical section, with child/supporting RTMs classified separately where applicable. | O15: OK | P15: SCK CEN/90508872 PDF+DOCX (08-Apr-2026) | Q15: SCK CEN/90508872 §4.2.5; no named external code in OFFER text | R15: None explicitly named in the OFFER text | S15: Submit and review the named deliverable with RTM traceability and approval status; Witnessed FAT/SAT/commissioning test against stated acceptance criteria; Calculation/model plus calibrated measurement or recorded trend | T15: Offer response: LN2 System Functional & Interface Design | U15: L0 Tender / Offer; L6 Site Acceptance Testing; L1 Conceptual Design; L2 Detailed Design | V15: OFFER-stage evidence; linked standards are contextual; does not prove full RTM compliance
A16: OFFER-11 | B16: Reliability, MTBF & Recovery Strategy | C16: 39 | D16: 4.3.2 | E16: Availability & Reliability | F16: 8.14 | G16: OPERATIONS_MAINTENANCE | H16: Reliability | I16: In the offer, the Applicant shall provide and thoroughly substantiate the expected MTBF values and associated recovery times. The substantiation shall include, at minimum: | J16: In the offer, the Applicant shall provide and thoroughly substantiate the expected MTBF values and associated recovery times. The substantiation shall include, at minimum: • The replacement philosophy (e.g. cartridge-based or modular replacement). • The capability for in-situ replacement without requiring Warm Stop, where claimed. • The isolation and serviceability concept (e.g. bayonet or valve-based isolation), where applied. • The maintenance intervention strategy supporting the assumed recovery times for Failure Classes A, B, and C. | K16: RTM-057..RTM-063 | M16: 7 | N16: Exact canonical section, with child/supporting RTMs classified separately where applicable. | O16: OK | P16: SCK CEN/90508872 PDF+DOCX (08-Apr-2026) | Q16: SCK CEN/90508872 §4.3.2; no named external code in OFFER text | R16: None explicitly named in the OFFER text | S16: Submit and review the named deliverable with RTM traceability and approval status; RAM/maintenance substantiation and recovery/failure-response evidence | T16: Offer response: Reliability, MTBF & Recovery Strategy | U16: L0 Tender / Offer; L1 Conceptual Design; L2 Detailed Design | V16: OFFER-stage evidence; linked standards are contextual; does not prove full RTM compliance
A17: OFFER-12 | B17: Performance Efficiency (invCOP) Declaration | C17: 40 | D17: 4.3.4 | E17: Energy-efficiency | F17: 8.15 | G17: SYSTEM_PERFORMANCE | H17: Efficiency | I17: In the offer, the Applicant shall state and substantiate the invCOP_contract. | J17: In the offer, the Applicant shall state and substantiate the invCOP_contract. | K17: RTM-069..RTM-072 | L17: RTM-073..RTM-077 | M17: 9 | N17: Exact canonical section, with child/supporting RTMs classified separately where applicable. | O17: OK — Review breadth | P17: SCK CEN/90508872 PDF+DOCX (08-Apr-2026) | Q17: SCK CEN/90508872 §4.3.4; no named external code in OFFER text | R17: None explicitly named in the OFFER text | S17: Submit and review the named deliverable with RTM traceability and approval status; Calculation/model plus calibrated measurement or recorded trend | T17: Offer response: Performance Efficiency (invCOP) Declaration | U17: L0 Tender / Offer; L1 Conceptual Design; L2 Detailed Design | V17: OFFER-stage evidence; linked standards are contextual; does not prove full RTM compliance
A18: OFFER-13 | B18: Main Equipment Technical Specifications | C18: 42 | D18: 4.4 | E18: Subsystem Requirements | F18: 8.16 | G18: MECHANICAL_DESIGN | H18: Equipment Design | I18: In the offer, the Applicant shall provide the key specifications of the main components. | J18: In the offer, the Applicant shall provide the key specifications of the main components. | L18: RTM-141..RTM-152; RTM-193..RTM-197; RTM-236..RTM-257; RTM-263..RTM-267 | M18: 44 | N18: Broad key-component request; selected top-level component RTMs only, not all §4.4 requirements. | O18: Review — breadth | P18: SCK CEN/90508872 PDF+DOCX (08-Apr-2026) | Q18: Linked canonical RTM/section: ISO 2372; ISO 20816; ISO 2954; ISO 2151; API 671; ISO 10441; EN 13185:2001 | R18: None explicitly named in the OFFER text | S18: Submit and review the named deliverable with RTM traceability and approval status | T18: Offer response: Main Equipment Technical Specifications | U18: L0 Tender / Offer; L1 Conceptual Design; L2 Detailed Design | V18: OFFER-stage evidence; linked standards are contextual; does not prove full RTM compliance
A19: OFFER-14 | B19: Expansion Joint Design & Risk Justification | C19: 42 | D19: 4.4.1.1 | E19: Bellows, joints, and seals | F19: 8.17 | G19: MECHANICAL_DESIGN | H19: Piping & Layout | I19: In their offer, the Applicants shall | J19: In their offer, the Applicants shall • Indicate the quantity and location of expansion joints (if any) that are foreseen to be implemented in the cryogenic process piping. • If the use of (an) expansion joint(s) is anticipated, the Applicants shall provide for each type of expansion joint a (one) representative example of its implementation, including the aforementioned documentation (justification, risk assessment, QAP, and intervention plan). | K19: RTM-079 | M19: 1 | N19: Exact canonical section, with child/supporting RTMs classified separately where applicable. | O19: OK | P19: SCK CEN/90508872 PDF+DOCX (08-Apr-2026) | Q19: SCK CEN/90508872 §4.4.1.1; no named external code in OFFER text | R19: None explicitly named in the OFFER text | S19: Submit and review the named deliverable with RTM traceability and approval status; Document review, inspection, certification, audit or traceable QC record | T19: Offer response: Expansion Joint Design & Risk Justification; Quality Assurance Plan (QAP); Risk Assessment / HAZOP / FMECA | U19: L0 Tender / Offer; L1 Conceptual Design; L2 Detailed Design | V19: OFFER-stage evidence; linked standards are contextual; does not prove full RTM compliance
A20: OFFER-15 | B20: Compressor Noise Emission Specification | C20: 49 | D20: 4.4.3.1 | E20: General Requirements | F20: 8.18 | G20: MECHANICAL_DESIGN | H20: Noise & Vibrations | I20: In the offer, the Applicant shall state and substantiate the expected noise levels at 1 m from each compressor. | J20: In the offer, the Applicant shall state and substantiate the expected noise levels at 1 m from each compressor. | K20: RTM-141..RTM-147 | M20: 7 | N20: Exact canonical section, with child/supporting RTMs classified separately where applicable. | O20: OK | P20: SCK CEN/90508872 PDF+DOCX (08-Apr-2026) | Q20: Linked canonical RTM/section: ISO 2372; ISO 20816; ISO 2954; ISO 2151 | R20: None explicitly named in the OFFER text | S20: Submit and review the named deliverable with RTM traceability and approval status; Calculation/model plus calibrated measurement or recorded trend | T20: Offer response: Compressor Noise Emission Specification | U20: L0 Tender / Offer; L1 Conceptual Design; L2 Detailed Design | V20: OFFER-stage evidence; linked standards are contextual; does not prove full RTM compliance
A21: OFFER-16 | B21: Compressor Configuration & Operating Limits | C21: 50 | D21: 4.4.3.2 | E21: Compressors requirements | F21: 8.19 | G21: MECHANICAL_DESIGN | H21: Equipment Design | I21: In the offer, the Applicant shall: | J21: In the offer, the Applicant shall: • State the number of LP compressors (PVPS units) and HP compressors • Confirm the long term sustainable operating frequency. | K21: RTM-148..RTM-152 | M21: 5 | N21: Exact canonical section, with child/supporting RTMs classified separately where applicable. | O21: OK | P21: SCK CEN/90508872 PDF+DOCX (08-Apr-2026) | Q21: Linked canonical RTM/section: API 671; ISO 10441 | R21: None explicitly named in the OFFER text | S21: Submit and review the named deliverable with RTM traceability and approval status; Calculation/model plus calibrated measurement or recorded trend | T21: Offer response: Compressor Configuration & Operating Limits | U21: L0 Tender / Offer; L1 Conceptual Design; L2 Detailed Design | V21: OFFER-stage evidence; linked standards are contextual; does not prove full RTM compliance
A22: OFFER-17 | B22: Preliminary 3D Plant Layout Model | C22: 55 | D22: 4.4.4.1 | E22: General Requirements | F22: 8.20 | G22: INFRASTRUCTURE | H22: Buildings & Layout | I22: In the offer, the Applicant shall provide a preliminary 3D MODEL including the terminal points for the A, B, E and D lines. | J22: In the offer, the Applicant shall provide a preliminary 3D MODEL including the terminal points for the A, B, E and D lines. | K22: RTM-193..RTM-197 | M22: 5 | N22: Exact canonical section, with child/supporting RTMs classified separately where applicable. | O22: OK | P22: SCK CEN/90508872 PDF+DOCX (08-Apr-2026) | Q22: SCK CEN/90508872 §4.4.4.1; no named external code in OFFER text | R22: None explicitly named in the OFFER text | S22: Submit and review the named deliverable with RTM traceability and approval status; Calculation/model plus calibrated measurement or recorded trend; Document review, inspection, certification, audit or traceable QC record | T22: Offer response: Preliminary 3D Plant Layout Model; 3D / CAD Model | U22: L0 Tender / Offer; L1 Conceptual Design; L2 Detailed Design | V22: OFFER-stage evidence; linked standards are contextual; does not prove full RTM compliance
A23: OFFER-18 | B23: MPHX Technology Selection | C23: 56 | D23: 4.4.4.2.2 | E23: Main Process Heat Exchangers (MPHX) | F23: 8.21 | G23: PROCESS_DESIGN | H23: Thermodynamic Design | I23: In the offer, the Applicant shall describe the selected type of MPHX that will be used. | J23: In the offer, the Applicant shall describe the selected type of MPHX that will be used. | K23: RTM-202..RTM-209 | M23: 8 | N23: Exact canonical section, with child/supporting RTMs classified separately where applicable. | O23: OK | P23: SCK CEN/90508872 PDF+DOCX (08-Apr-2026) | Q23: SCK CEN/90508872 §4.4.4.2.2; no named external code in OFFER text | R23: None explicitly named in the OFFER text | S23: Submit and review the named deliverable with RTM traceability and approval status; Calculation/model plus calibrated measurement or recorded trend | T23: Offer response: MPHX Technology Selection | U23: L0 Tender / Offer; L1 Conceptual Design; L2 Detailed Design | V23: OFFER-stage evidence; linked standards are contextual; does not prove full RTM compliance
A24: OFFER-19 | B24: Warm Storage Heater (WSH) Design & Layout | C24: 62 | D24: 4.4.5.2 | E24: WSH Requirements | F24: 8.22 | G24: PROCESS_DESIGN | H24: Process Interfaces | I24: In the offer, Applicant shall describe the WSH implementation. At minimum, the offer shall include | J24: In the offer, Applicant shall describe the WSH implementation. At minimum, the offer shall include • The minimum total storage capacity • The minimum quantity of storage vessels • A conceptual layout of the WSH • A confirmation that the available space provisions at the outside Storage Area are sufficient for the proposed configuration | K24: RTM-239..RTM-248 | M24: 10 | N24: Exact canonical section, with child/supporting RTMs classified separately where applicable. | O24: OK | P24: SCK CEN/90508872 PDF+DOCX (08-Apr-2026) | Q24: SCK CEN/90508872 §4.4.5.2; no named external code in OFFER text | R24: None explicitly named in the OFFER text | S24: Submit and review the named deliverable with RTM traceability and approval status; Calculation/model plus calibrated measurement or recorded trend | T24: Offer response: Warm Storage Heater (WSH) Design & Layout | U24: L0 Tender / Offer; L1 Conceptual Design; L2 Detailed Design | V24: OFFER-stage evidence; linked standards are contextual; does not prove full RTM compliance
A25: OFFER-20 | B25: Helium Leak Detection & Loss Management | C25: 63 | D25: 4.4.7 | E25: Helium Inventory Management | F25: 8.23 | G25: QUALITY_RISK | H25: Risk Management | I25: In the offer, the Applicant shall quantify and substantiate: | J25: In the offer, the Applicant shall quantify and substantiate: • The expected leak rates, expressed as annual helium loss percentage, per leak type and in total, including diffusive losses. • The helium leak-detection methods, pressure-hold test procedures, vacuum-decay or pressure-rise methodologies, and long-term monitoring techniques, including the corresponding acceptance criteria. • The post-installation and operational monitoring strategy, including thresholds and monitoring frequency. • The expected helium loss during conventional pump-down, purge, and conditioning operations for the QPS. | K25: RTM-252..RTM-257 | L25: RTM-258..RTM-262 | M25: 11 | N25: Exact canonical section, with child/supporting RTMs classified separately where applicable. | O25: OK — Review breadth | P25: SCK CEN/90508872 PDF+DOCX (08-Apr-2026) | Q25: Linked canonical RTM/section: EN 13185:2001 | R25: None explicitly named in the OFFER text | S25: Submit and review the named deliverable with RTM traceability and approval status; Witnessed FAT/SAT/commissioning test against stated acceptance criteria; Functional design/configuration review and sequence/interface demonstration | T25: Offer response: Helium Leak Detection & Loss Management; Test procedure / report; Procedure / work instruction | U25: L0 Tender / Offer; L4 Installation; L1 Conceptual Design; L2 Detailed Design | V25: OFFER-stage evidence; linked standards are contextual; does not prove full RTM compliance
A26: OFFER-21 | B26: LOOP Strategy & Critical Load Management | C26: 63 | D26: 4.4.7.1 | E26: LOOP | F26: 8.24 | G26: PROCESS_DESIGN | H26: LOOP Strategy | I26: In the offer, the Applicant shall provide an indicative design of the LOOP strategy, including: | J26: In the offer, the Applicant shall provide an indicative design of the LOOP strategy, including: • The identification of the critical loads to be maintained under LOOP conditions. • The enveloping assumptions for the internal distribution logic, including switching, prioritization, and load-control schemes. • The configuration and internal routing of the limited utility supplies. | K26: RTM-258 | M26: 1 | N26: Exact canonical section, with child/supporting RTMs classified separately where applicable. | O26: OK | P26: SCK CEN/90508872 PDF+DOCX (08-Apr-2026) | Q26: SCK CEN/90508872 §4.4.7.1; no named external code in OFFER text | R26: None explicitly named in the OFFER text | S26: Submit and review the named deliverable with RTM traceability and approval status; Functional design/configuration review and sequence/interface demonstration; RAM/maintenance substantiation and recovery/failure-response evidence | T26: Offer response: LOOP Strategy & Critical Load Management | U26: L0 Tender / Offer; L1 Conceptual Design; L2 Detailed Design | V26: OFFER-stage evidence; linked standards are contextual; does not prove full RTM compliance
A27: OFFER-22 | B27: Helium Recovery System Design | C27: 64 | D27: 4.4.7.3 | E27: Abnormal conditions | F27: 8.25 | G27: PROCESS_DESIGN | H27: Helium Management | I27: In the offer, the Applicant shall present a high-level description of the helium recovery strategy including but not limited to | J27: In the offer, the Applicant shall present a high-level description of the helium recovery strategy including but not limited to • A Bill of Materials (BoM) of all recovery components (e.g. low-pressure gas balloon storage and/or high-pressure compressor-driven recovery and/or dedicated purification system). • The maximum flow that the QPS can accept from the S line. | K27: RTM-260..RTM-262 | M27: 3 | N27: Exact canonical section, with child/supporting RTMs classified separately where applicable. | O27: OK | P27: SCK CEN/90508872 PDF+DOCX (08-Apr-2026) | Q27: SCK CEN/90508872 §4.4.7.3; no named external code in OFFER text | R27: None explicitly named in the OFFER text | S27: Submit and review the named deliverable with RTM traceability and approval status; RAM/maintenance substantiation and recovery/failure-response evidence | T27: Offer response: Helium Recovery System Design | U27: L0 Tender / Offer; L1 Conceptual Design; L2 Detailed Design | V27: OFFER-stage evidence; linked standards are contextual; does not prove full RTM compliance
A28: OFFER-23 | B28: User Configuration Filling Performance | C28: 65 | D28: 4.4.8.1 | E28: Dewar Filling Station | F28: 8.26 | G28: SYSTEM_PERFORMANCE | H28: Filling/Emptying Performance | I28: In the offer, the Applicant shall indicate the maximum filling rate that QPS can provide for each of the two user configurations (LINAC_24 and LINAC_30). The values shall be specified for the operational scenarios 2K-OP, 2K-SB, and 4K-SB. | J28: In the offer, the Applicant shall indicate the maximum filling rate that QPS can provide for each of the two user configurations (LINAC_24 and LINAC_30). The values shall be specified for the operational scenarios 2K-OP, 2K-SB, and 4K-SB. | K28: RTM-268..RTM-272 | M28: 5 | N28: Exact canonical section, with child/supporting RTMs classified separately where applicable. | O28: OK | P28: SCK CEN/90508872 PDF+DOCX (08-Apr-2026) | Q28: SCK CEN/90508872 §4.4.8.1; no named external code in OFFER text | R28: None explicitly named in the OFFER text | S28: Submit and review the named deliverable with RTM traceability and approval status; Calculation/model plus calibrated measurement or recorded trend; Functional design/configuration review and sequence/interface demonstration | T28: Offer response: User Configuration Filling Performance | U28: L0 Tender / Offer; L1 Conceptual Design; L2 Detailed Design | V28: OFFER-stage evidence; linked standards are contextual; does not prove full RTM compliance
A29: OFFER-24 | B29: Helium Purity Acceptance Criteria | C29: 66 | D29: 4.4.8.2 | E29: Warm GHe Recovery from WGR-MAC | F29: 8.27 | G29: PROCESS_DESIGN | H29: Helium Management | I29: In the offer, the Applicant shall define the helium purity acceptance criteria for the GHe returning via line QRB.G20. | J29: In the offer, the Applicant shall define the helium purity acceptance criteria for the GHe returning via line QRB.G20. | K29: RTM-273..RTM-280 | M29: 8 | N29: Exact canonical section, with child/supporting RTMs classified separately where applicable. | O29: OK | P29: SCK CEN/90508872 PDF+DOCX (08-Apr-2026) | Q29: SCK CEN/90508872 §4.4.8.2; no named external code in OFFER text | R29: None explicitly named in the OFFER text | S29: Submit and review the named deliverable with RTM traceability and approval status | T29: Offer response: Helium Purity Acceptance Criteria | U29: L0 Tender / Offer; L1 Conceptual Design; L2 Detailed Design | V29: OFFER-stage evidence; linked standards are contextual; does not prove full RTM compliance
A30: OFFER-25 | B30: Supplier Experience & Reference Justification | C30: 74 | D30: 4.6.4.5 | E30: Security | F30: 8.28 | G30: COMMERCIAL | H30: Qualification | I30: In the offer, the Applicant shall indicate and substantiate their level of experience in providing such information. | J30: In the offer, the Applicant shall indicate and substantiate their level of experience in providing such information. | K30: RTM-321..RTM-327 | M30: 7 | N30: Exact canonical section, with child/supporting RTMs classified separately where applicable. | O30: OK | P30: SCK CEN/90508872 PDF+DOCX (08-Apr-2026) | Q30: Linked canonical RTM/section: ISO 27001; IEC 62443-3-3; EU Cyber Resilience Act (CRA); CE marking | R30: None explicitly named in the OFFER text | S30: Submit and review the named deliverable with RTM traceability and approval status | T30: Offer response: Supplier Experience & Reference Justification | U30: L0 Tender / Offer; L1 Conceptual Design; L2 Detailed Design | V30: OFFER-stage evidence; linked standards are contextual; does not prove full RTM compliance
A31: OFFER-26 | B31: Software Architecture & Development Scope | C31: 76 | D31: 4.6.7 | E31: Software development | F31: 8.29 | G31: SOFTWARE | H31: Software Architecture | I31: In the offer, the Applicant shall provide sufficient detail deemed representative of the anticipated software development scope, including assumptions, planned methodologies, and architectural breakdown. | J31: In the offer, the Applicant shall provide sufficient detail deemed representative of the anticipated software development scope, including assumptions, planned methodologies, and architectural breakdown. | K31: RTM-334..RTM-339 | L31: RTM-340..RTM-345 | M31: 12 | N31: Exact canonical section, with child/supporting RTMs classified separately where applicable. | O31: OK | P31: SCK CEN/90508872 PDF+DOCX (08-Apr-2026) | Q31: Linked canonical RTM/section: IEC 61131-3 | R31: None explicitly named in the OFFER text | S31: Submit and review the named deliverable with RTM traceability and approval status; Functional design/configuration review and sequence/interface demonstration | T31: Offer response: Software Architecture & Development Scope | U31: L0 Tender / Offer; L1 Conceptual Design; L2 Detailed Design | V31: OFFER-stage evidence; linked standards are contextual; does not prove full RTM compliance
A32: OFFER-27 | B32: Programming Standards & Language Strategy | C32: 76 | D32: 4.6.7 | E32: Software development | F32: 8.30 | G32: SOFTWARE | H32: Programming Standards | I32: In the offer, the Applicant shall: | J32: In the offer, the Applicant shall: • Declare the programming languages to be used per functional block. • Justify any deviation from ST and including retained IL-based implementations. • Demonstrate software structuring practices that favour maintainability, reuse, and modular design. • Proposals will be evaluated with preference given to Applicants demonstrating disciplined use of structured IEC 61131-3 languages and long-term maintainability strategies. | K32: RTM-340..RTM-341; RTM-343..RTM-344 | L32: RTM-334..RTM-339; RTM-342; RTM-345 | M32: 12 | N32: Exact canonical section, with child/supporting RTMs classified separately where applicable. | O32: OK | P32: SCK CEN/90508872 PDF+DOCX (08-Apr-2026) | Q32: Linked canonical RTM/section: IEC 61131-3 | R32: IEC 61131-3 | S32: Submit and review the named deliverable with RTM traceability and approval status; Witnessed FAT/SAT/commissioning test against stated acceptance criteria; Functional design/configuration review and sequence/interface demonstration | T32: Offer response: Programming Standards & Language Strategy | U32: L0 Tender / Offer; L1 Conceptual Design; L2 Detailed Design | V32: OFFER-stage evidence; linked standards are contextual; does not prove full RTM compliance
A33: OFFER-28 | B33: Functional Analysis & Control Sequences | C33: 77 | D33: 4.6.7 | E33: Software development | F33: 8.31 | G33: SOFTWARE | H33: Functional Analysis | I33: In the offer, the Applicant shall provide a preliminary functional analysis and indicative control sequence plan, representative of the anticipated implementation. This shall include key functions, procedural steps, and interface interactions necessary to support evaluation of scope, architecture complexity, and design maturity. | J33: In the offer, the Applicant shall provide a preliminary functional analysis and indicative control sequence plan, representative of the anticipated implementation. This shall include key functions, procedural steps, and interface interactions necessary to support evaluation of scope, architecture complexity, and design maturity. | K33: RTM-342; RTM-345 | L33: RTM-334..RTM-341; RTM-343..RTM-344 | M33: 12 | N33: Exact canonical section, with child/supporting RTMs classified separately where applicable. | O33: OK | P33: SCK CEN/90508872 PDF+DOCX (08-Apr-2026) | Q33: Linked canonical RTM/section: IEC 61131-3 | R33: None explicitly named in the OFFER text | S33: Submit and review the named deliverable with RTM traceability and approval status; Functional design/configuration review and sequence/interface demonstration | T33: Offer response: Functional Analysis & Control Sequences | U33: L0 Tender / Offer; L1 Conceptual Design; L2 Detailed Design | V33: OFFER-stage evidence; linked standards are contextual; does not prove full RTM compliance
A34: OFFER-29 | B34: Control System Obsolescence Strategy | C34: 78 | D34: 4.6.8 | E34: SCADA, HMI, and Data Historian Infrastructure | F34: 8.32 | G34: CONTROL_SYSTEM | H34: Lifecycle Management | I34: In the offer, the Applicant shall explicitly address the obsolescence management strategy for the proposed PLC or control system platform, considering the anticipated forty (40) year operational lifetime of QPS. This shall include: | J34: In the offer, the Applicant shall explicitly address the obsolescence management strategy for the proposed PLC or control system platform, considering the anticipated forty (40) year operational lifetime of QPS. This shall include: • Manufacturer support lifecycle documentation • Spare part availability forecasts and migration plans • Platform evolution roadmap (e.g., upgrade compatibility or virtualization strategy) • Technical or commercial approach to sustaining software and hardware support beyond the guaranteed 20-year update period (e.g., stockpiling, long-term service contracts, emulation layers). | K34: RTM-346..RTM-367 | M34: 22 | N34: Exact canonical section, with child/supporting RTMs classified separately where applicable. | O34: OK | P34: SCK CEN/90508872 PDF+DOCX (08-Apr-2026) | Q34: SCK CEN/90508872 §4.6.8; no named external code in OFFER text | R34: None explicitly named in the OFFER text | S34: Submit and review the named deliverable with RTM traceability and approval status; Functional design/configuration review and sequence/interface demonstration; RAM/maintenance substantiation and recovery/failure-response evidence | T34: Offer response: Control System Obsolescence Strategy | U34: L0 Tender / Offer; L1 Conceptual Design; L2 Detailed Design | V34: OFFER-stage evidence; linked standards are contextual; does not prove full RTM compliance
A35: OFFER-30 | B35: Software Change Management Process | C35: 79 | D35: 4.6.9 | E35: Software Change Management | F35: 8.33 | G35: SOFTWARE | H35: Change Management | I35: In the offer, the Applicant shall detail how he shall implement the software change management. | J35: In the offer, the Applicant shall detail how he shall implement the software change management. | K35: RTM-368..RTM-370 | M35: 3 | N35: Exact canonical section, with child/supporting RTMs classified separately where applicable. | O35: OK | P35: SCK CEN/90508872 PDF+DOCX (08-Apr-2026) | Q35: SCK CEN/90508872 §4.6.9; no named external code in OFFER text | R35: None explicitly named in the OFFER text | S35: Submit and review the named deliverable with RTM traceability and approval status; Functional design/configuration review and sequence/interface demonstration | T35: Offer response: Software Change Management Process | U35: L0 Tender / Offer; L1 Conceptual Design; L2 Detailed Design | V35: OFFER-stage evidence; linked standards are contextual; does not prove full RTM compliance
A36: OFFER-31 | B36: Cold Box Environmental Requirements | C36: 80 | D36: 4.7.1 | E36: Site environmental conditions | F36: 8.34 | G36: INFRASTRUCTURE | H36: Buildings & Layout | I36: In the offer, the Applicants shall indicate any required deviation from the specified Cold Box Room temperature range. | J36: In the offer, the Applicants shall indicate any required deviation from the specified Cold Box Room temperature range. | K36: RTM-386..RTM-387 | M36: 2 | N36: Exact canonical section, with child/supporting RTMs classified separately where applicable. | O36: OK | P36: SCK CEN/90508872 PDF+DOCX (08-Apr-2026) | Q36: SCK CEN/90508872 §4.7.1; no named external code in OFFER text | R36: None explicitly named in the OFFER text | S36: Submit and review the named deliverable with RTM traceability and approval status | T36: Offer response: Cold Box Environmental Requirements | U36: L0 Tender / Offer; L1 Conceptual Design; L2 Detailed Design | V36: OFFER-stage evidence; linked standards are contextual; does not prove full RTM compliance
A37: OFFER-32 | B37: Equipment Transport & Installation Constraints | C37: 82 | D37: 4.7.2 | E37: Building | F37: 8.35 | G37: INFRASTRUCTURE | H37: Structural Constraints | I37: In the offer, the Applicant shall identify the relevant equipment and specify: | J37: In the offer, the Applicant shall identify the relevant equipment and specify: • enveloping dimensions • lifting mass • clearances • floor loads • transportation loads (road loads) • the minimal size of the roof opening | K37: RTM-388..RTM-394 | M37: 7 | N37: Exact canonical section, with child/supporting RTMs classified separately where applicable. | O37: OK | P37: SCK CEN/90508872 PDF+DOCX (08-Apr-2026) | Q37: SCK CEN/90508872 §4.7.2; no named external code in OFFER text | R37: None explicitly named in the OFFER text | S37: Submit and review the named deliverable with RTM traceability and approval status | T37: Offer response: Equipment Transport & Installation Constraints | U37: L0 Tender / Offer; L1 Conceptual Design; L2 Detailed Design | V37: OFFER-stage evidence; linked standards are contextual; does not prove full RTM compliance
A38: OFFER-33 | B38: Electrical System Design & Load Analysis | C38: 83 | D38: 4.7.3.1 | E38: LOOP event | F38: 8.36 | G38: CONTROL_SYSTEM | H38: Electrical Systems | I38: In the Offer, the Applicant shall: | J38: In the Offer, the Applicant shall: • Provide the total and per-building load assessments (normal and peak demand). • Submit Single Line Diagram (One Line Diagrams) aligned to the ‘spatial split’ (2 rooms in 2 different buildings and terminal point logic described above. • Include a risk analysis and list safety functions to be served by a UPS backup. • Declare isolation strategies for embedded electronics in HV environments and list any required auxiliary supplies. | K38: RTM-401..RTM-402 | M38: 2 | N38: Exact canonical section, with child/supporting RTMs classified separately where applicable. | O38: OK | P38: SCK CEN/90508872 PDF+DOCX (08-Apr-2026) | Q38: SCK CEN/90508872 §4.7.3.1; no named external code in OFFER text | R38: None explicitly named in the OFFER text | S38: Submit and review the named deliverable with RTM traceability and approval status; Calculation/model plus calibrated measurement or recorded trend; RAM/maintenance substantiation and recovery/failure-response evidence | T38: Offer response: Electrical System Design & Load Analysis; Drawing / diagram; List / register / matrix | U38: L0 Tender / Offer; L1 Conceptual Design; L2 Detailed Design | V38: OFFER-stage evidence; linked standards are contextual; does not prove full RTM compliance
A39: OFFER-34 | B39: Cooling Water System Requirements | C39: 86 | D39: 4.7.4.3.2 | E39: Process Heat Exchanger | F39: 8.37 | G39: INFRASTRUCTURE | H39: Utilities | I39: In the Offer, the Applicant shall specify the minimum cooling water flow required at the heat exchangers during normal, partial-load, and heat-recovery operating conditions. | J39: In the Offer, the Applicant shall specify the minimum cooling water flow required at the heat exchangers during normal, partial-load, and heat-recovery operating conditions. | K39: RTM-426..RTM-427 | M39: 2 | N39: Exact canonical section, with child/supporting RTMs classified separately where applicable. | O39: OK | P39: SCK CEN/90508872 PDF+DOCX (08-Apr-2026) | Q39: SCK CEN/90508872 §4.7.4.3.2; no named external code in OFFER text | R39: None explicitly named in the OFFER text | S39: Submit and review the named deliverable with RTM traceability and approval status; Calculation/model plus calibrated measurement or recorded trend; RAM/maintenance substantiation and recovery/failure-response evidence | T39: Offer response: Cooling Water System Requirements | U39: L0 Tender / Offer; L1 Conceptual Design; L2 Detailed Design | V39: OFFER-stage evidence; linked standards are contextual; does not prove full RTM compliance
A40: OFFER-35 | B40: Heat Rejection & HVAC Interface Design | C40: 87 | D40: 4.7.6 | E40: Interfaces with HVAC | F40: 8.38 | G40: INFRASTRUCTURE | H40: HVAC & Heat Rejection | I40: In the offer, the Applicant shall provide all relevant information on: | J40: In the offer, the Applicant shall provide all relevant information on: • The heat dissipated to the ambient air. • The interface of the ducts to the compressors, including at minimum the size, flow rate, and allowable pressure drop. | K40: RTM-434..RTM-435 | M40: 2 | N40: Exact canonical section, with child/supporting RTMs classified separately where applicable. | O40: OK | P40: SCK CEN/90508872 PDF+DOCX (08-Apr-2026) | Q40: SCK CEN/90508872 §4.7.6; no named external code in OFFER text | R40: None explicitly named in the OFFER text | S40: Submit and review the named deliverable with RTM traceability and approval status; Calculation/model plus calibrated measurement or recorded trend; Functional design/configuration review and sequence/interface demonstration | T40: Offer response: Heat Rejection & HVAC Interface Design | U40: L0 Tender / Offer; L1 Conceptual Design; L2 Detailed Design | V40: OFFER-stage evidence; linked standards are contextual; does not prove full RTM compliance
A41: OFFER-36 | B41: 3D Model Platform & CAD Delivery | C41: 89 | D41: 4.8.1.2 | E41: CAD Models with Intellectual Property | F41: 8.39 | G41: INFRASTRUCTURE | H41: Buildings & Layout | I41: In the offer, the Applicant shall | J41: In the offer, the Applicant shall • indicate the 3D-model management platform they shall use • Provide a preliminary CAD model of the QPS with at least LoR 20 in format STEP AP242. | K41: RTM-445..RTM-449 | M41: 5 | N41: Exact canonical section, with child/supporting RTMs classified separately where applicable. | O41: OK | P41: SCK CEN/90508872 PDF+DOCX (08-Apr-2026) | Q41: SCK CEN/90508872 §4.8.1.2; no named external code in OFFER text | R41: None explicitly named in the OFFER text | S41: Submit and review the named deliverable with RTM traceability and approval status; Document review, inspection, certification, audit or traceable QC record | T41: Offer response: 3D Model Platform & CAD Delivery; 3D / CAD Model | U41: L0 Tender / Offer; L1 Conceptual Design; L2 Detailed Design | V41: OFFER-stage evidence; linked standards are contextual; does not prove full RTM compliance
A42: OFFER-37 | B42: Digital Twin / Simulation Strategy | C42: 89 | D42: 4.8.2 | E42: Digital Process Model and Digital Twin | F42: 8.40 | G42: SOFTWARE | H42: Software Architecture | I42: In the Offer, the Applicant shall explicitly state whether a Digital Process Model and/or a Digital Twin will be supplied. | J42: In the Offer, the Applicant shall explicitly state whether a Digital Process Model and/or a Digital Twin will be supplied. • If supplied, the Offer shall include a description the proposed modelling approach and toolset • If not supplied, the Offer shall describe the approach to commissioning support, fault simulation, diagnostics, and operator training. | K42: RTM-450..RTM-451 | M42: 2 | N42: Exact canonical section, with child/supporting RTMs classified separately where applicable. | O42: OK | P42: SCK CEN/90508872 PDF+DOCX (08-Apr-2026) | Q42: SCK CEN/90508872 §4.8.2; no named external code in OFFER text | R42: None explicitly named in the OFFER text | S42: Submit and review the named deliverable with RTM traceability and approval status; Witnessed FAT/SAT/commissioning test against stated acceptance criteria; Document review, inspection, certification, audit or traceable QC record | T42: Offer response: Digital Twin / Simulation Strategy; Digital Process Model / Digital Twin | U42: L0 Tender / Offer; L1 Conceptual Design; L2 Detailed Design | V42: OFFER-stage evidence; linked standards are contextual; does not prove full RTM compliance
A43: OFFER-38 | B43: Training Program & Competency Definition | C43: 95 | D43: 4.12.1 | E43: Training and Competence Transfer | F43: 8.41 | G43: OPERATIONS_MAINTENANCE | H43: Training | I43: In the offer, the Applicant shall include: | J43: In the offer, the Applicant shall include: • The Training Plan, including the proposed training modules and their intended scope. • The total price for the Training. • The expected personnel profile, including the number, and minimum entry competencies of the SCK CEN personnel (operators and technicians) required to successfully fulfil their duties after completion of the training. | K43: RTM-483..RTM-490 | M43: 8 | N43: Exact canonical section, with child/supporting RTMs classified separately where applicable. | O43: OK | P43: SCK CEN/90508872 PDF+DOCX (08-Apr-2026) | Q43: SCK CEN/90508872 §4.12.1; no named external code in OFFER text | R43: None explicitly named in the OFFER text | S43: Submit and review the named deliverable with RTM traceability and approval status | T43: Offer response: Training Program & Competency Definition; Training Programme / Materials | U43: L0 Tender / Offer; L1 Conceptual Design; L2 Detailed Design | V43: OFFER-stage evidence; linked standards are contextual; does not prove full RTM compliance
A44: OFFER-39 | B44: FAT/SAT Testing Strategy & Procedures | C44: 97 | D44: 4.13.1 | E44: General Requirements | F44: 8.42 | G44: QUALITY_RISK | H44: Testing | I44: In their offer, the Applicant shall provide a concise description of the inspections, FAT test and SAT tests that will be performed, including: | J44: In their offer, the Applicant shall provide a concise description of the inspections, FAT test and SAT tests that will be performed, including: • How each test shall be performed • Which equipment, tools, and instrumentation shall be used | K44: RTM-491..RTM-495 | L44: RTM-496..RTM-556 | M44: 66 | N44: Exact canonical section, with child/supporting RTMs classified separately where applicable. | O44: OK — Review breadth | P44: SCK CEN/90508872 PDF+DOCX (08-Apr-2026) | Q44: SCK CEN/90508872 §4.13.1; no named external code in OFFER text | R44: None explicitly named in the OFFER text | S44: Submit and review the named deliverable with RTM traceability and approval status; Witnessed FAT/SAT/commissioning test against stated acceptance criteria | T44: Offer response: FAT/SAT Testing Strategy & Procedures | U44: L0 Tender / Offer; L6 Site Acceptance Testing; L1 Conceptual Design; L2 Detailed Design | V44: OFFER-stage evidence; linked standards are contextual; does not prove full RTM compliance
A45: OFFER-40 | B45: Electrical Power Measurement Methodology | C45: 107 | D45: 4.13.3.3.7 | E45: Energy-Efficiency demonstration | F45: 8.43 | G45: CONTROL_SYSTEM | H45: Instrumentation | I45: In the offer, the Applicant shall | J45: In the offer, the Applicant shall • Describe the electrical power measurement method they will apply within the QPS, including the electrical boundary (e.g. total plant consumption including auxiliaries, compressors, and control systems) and the associated measurement uncertainty. • Explicitly state whether any SCK CEN measurements are assumed. | K45: RTM-542..RTM-544 | M45: 3 | N45: Exact canonical section, with child/supporting RTMs classified separately where applicable. | O45: OK | P45: SCK CEN/90508872 PDF+DOCX (08-Apr-2026) | Q45: SCK CEN/90508872 §4.13.3.3.7; no named external code in OFFER text | R45: None explicitly named in the OFFER text | S45: Submit and review the named deliverable with RTM traceability and approval status; Document review, inspection, certification, audit or traceable QC record | T45: Offer response: Electrical Power Measurement Methodology | U45: L0 Tender / Offer; L1 Conceptual Design; L2 Detailed Design | V45: OFFER-stage evidence; linked standards are contextual; does not prove full RTM compliance
A46: OFFER-41 | B46: Spare Parts & Critical Components Strategy | C46: 109 | D46: 4.14.3 | E46: Spare Parts | F46: 8.44 | G46: OPERATIONS_MAINTENANCE | H46: Spare Parts | I46: In their Offer, the Applicant shall provide the following lists: | J46: In their Offer, the Applicant shall provide the following lists: • Strategic Spare Parts List, indicating all spare parts included in Contingent Part 1, and specifying for each item: • unit price • procurement lead time. • Critical Components List, specifying the unit price, procurement lead time, and shelf life for all cost-relevant and/or operationally critical items that meet any of the following criteria: • a mean time between failures (MTBF) of less than ten (10) years, or • a projected replacement rate of two (2) or more times within the QPSs lifetime (RTM-055). | K46: RTM-560..RTM-562 | M46: 3 | N46: Exact canonical section, with child/supporting RTMs classified separately where applicable. | O46: OK | P46: SCK CEN/90508872 PDF+DOCX (08-Apr-2026) | Q46: SCK CEN/90508872 §4.14.3; no named external code in OFFER text | R46: None explicitly named in the OFFER text | S46: Submit and review the named deliverable with RTM traceability and approval status; RAM/maintenance substantiation and recovery/failure-response evidence | T46: Offer response: Spare Parts & Critical Components Strategy; List / register / matrix | U46: L0 Tender / Offer; L1 Conceptual Design; L2 Detailed Design | V46: OFFER-stage evidence; linked standards are contextual; does not prove full RTM compliance
A47: OFFER-42 | B47: After-Sales Service Organization & Pricing | C47: 110 | D47: 4.15 | E47: After-Sales Services | F47: 8.45 | G47: COMMERCIAL | H47: Warranty | I47: In the offer, the Applicant shall provide the following information as regards the after-sales service: | J47: In the offer, the Applicant shall provide the following information as regards the after-sales service: • Organization of the after-sales service – at least a concise description of the approach to handling customers’ requests and an overview of the available staff must be given. • Procedure to be followed for requesting after-sales service – at least a comprehensive description of how the helpdesk can be contacted (including all relevant information such as contact data (telephone, email or equivalent) and availability) must be given. | K47: RTM-563..RTM-565 | M47: 3 | N47: Exact canonical section, with child/supporting RTMs classified separately where applicable. | O47: OK | P47: SCK CEN/90508872 PDF+DOCX (08-Apr-2026) | Q47: SCK CEN/90508872 §4.15; no named external code in OFFER text | R47: None explicitly named in the OFFER text | S47: Submit and review the named deliverable with RTM traceability and approval status; Functional design/configuration review and sequence/interface demonstration; RAM/maintenance substantiation and recovery/failure-response evidence | T47: Offer response: After-Sales Service Organization & Pricing; Procedure / work instruction | U47: L0 Tender / Offer; L1 Conceptual Design; L2 Detailed Design | V47: OFFER-stage evidence; linked standards are contextual; does not prove full RTM compliance
A48: OFFER-43 | B48: Maintenance Effort & Intervention Estimation | C48: 110 | D48: 4.15 | E48: After-Sales Services | F48: 8.46 | G48: OPERATIONS_MAINTENANCE | H48: Maintenance Strategy | I48: In the offer, the Application shall provide estimates of typical expected hours for typical maintenance activities. | J48: In the offer, the Application shall provide estimates of typical expected hours for typical maintenance activities. | L48: RTM-563..RTM-565 | M48: 3 | N48: Maintenance-hour estimate is OFFER-only; service RTMs are contextual. | O48: Review — accept context | P48: SCK CEN/90508872 PDF+DOCX (08-Apr-2026) | Q48: SCK CEN/90508872 §4.15; no named external code in OFFER text | R48: None explicitly named in the OFFER text | S48: Submit and review the named deliverable with RTM traceability and approval status; RAM/maintenance substantiation and recovery/failure-response evidence | T48: Offer response: Maintenance Effort & Intervention Estimation | U48: L0 Tender / Offer; L1 Conceptual Design; L2 Detailed Design | V48: OFFER-stage evidence; linked standards are contextual; does not prove full RTM compliance
A49: OFFER-44 | B49: Project Schedule & Milestone Definition | C49: 119 | D49: 6.2 | E49: Provisional Schedule | F49: 8.47 | G49: PROJECT_EXECUTION | H49: Planning & Scheduling | I49: In their x, the Applicant shall submit a detailed schedule following these phases according to its own expertise and experience and propose. In doing so, the Applicant shall take into consideration the preliminary schedule in Table 22. The Applicant may add (to a reasonable extent) additional milestones as they think appropriate. | J49: In their x, the Applicant shall submit a detailed schedule following these phases according to its own expertise and experience and propose. In doing so, the Applicant shall take into consideration the preliminary schedule in Table 22. The Applicant may add (to a reasonable extent) additional milestones as they think appropriate. | L49: RTM-614..RTM-620 | M49: 7 | N49: Direct source: Table 22 in §6.2; linked RTMs are supporting phase requirements. | O49: OK — non-RTM source | P49: SCK CEN/90508872 PDF+DOCX (08-Apr-2026) | Q49: SCK CEN/90508872 §6.2; no named external code in OFFER text | R49: None explicitly named in the OFFER text | S49: Submit and review the named deliverable with RTM traceability and approval status | T49: Offer response: Project Schedule & Milestone Definition; Schedule / milestone plan | U49: L0 Tender / Offer; L1 Conceptual Design; L2 Detailed Design; L3 Procurement & Manufacturing / FAT; L4 Installation; L5 Standalone Commissioning; L6 Site Acceptance Testing | V49: OFFER-stage evidence; linked standards are contextual; does not prove full RTM compliance
A50: OFFER-45 | B50: Project Dashboard & Management Processes | C50: 122 | D50: 7.4.1 | E50: Progress Dashboard | F50: 8.48 | G50: PROJECT_EXECUTION | H50: Governance | I50: In the offer, the Applicant shall include a concise description of the dashboard as well as the underlying management processes. This description shall include sufficient detail to demonstrate compliance with the requirements. | J50: In the offer, the Applicant shall include a concise description of the dashboard as well as the underlying management processes. This description shall include sufficient detail to demonstrate compliance with the requirements. | K50: RTM-633 | M50: 1 | N50: Exact canonical section, with child/supporting RTMs classified separately where applicable. | O50: OK | P50: SCK CEN/90508872 PDF+DOCX (08-Apr-2026) | Q50: SCK CEN/90508872 §7.4.1; no named external code in OFFER text | R50: None explicitly named in the OFFER text | S50: Submit and review the named deliverable with RTM traceability and approval status; Witnessed FAT/SAT/commissioning test against stated acceptance criteria; Document review, inspection, certification, audit or traceable QC record | T50: Offer response: Project Dashboard & Management Processes | U50: L0 Tender / Offer; L1 Conceptual Design; L2 Detailed Design; L3 Procurement & Manufacturing / FAT; L4 Installation; L5 Standalone Commissioning; L6 Site Acceptance Testing | V50: OFFER-stage evidence; linked standards are contextual; does not prove full RTM compliance
A51: OFFER-46 | B51: Risk Assessment & Mitigation Strategy | C51: 123 | D51: 7.5 | E51: Risk Assessment & Management Plan | F51: 8.49 | G51: QUALITY_RISK | H51: Risk Management | I51: In the offer, the Applicant shall submit a preliminary Risk Assessment & Management Plan. It shall contain all risks with a severity that are bound to compromise the successful completion of the Contract either in terms of schedule, budget, or technical requirements, irrespective of probability. It shall present a top-level view of the mitigation strategy that the Applicant shall implement during contract execution, for all the risks that have been identified as unacceptable. | J51: In the offer, the Applicant shall submit a preliminary Risk Assessment & Management Plan. It shall contain all risks with a severity that are bound to compromise the successful completion of the Contract either in terms of schedule, budget, or technical requirements, irrespective of probability. It shall present a top-level view of the mitigation strategy that the Applicant shall implement during contract execution, for all the risks that have been identified as unacceptable. | K51: RTM-640 | M51: 1 | N51: Exact canonical section, with child/supporting RTMs classified separately where applicable. | O51: OK | P51: SCK CEN/90508872 PDF+DOCX (08-Apr-2026) | Q51: SCK CEN/90508872 §7.5; no named external code in OFFER text | R51: None explicitly named in the OFFER text | S51: Submit and review the named deliverable with RTM traceability and approval status | T51: Offer response: Risk Assessment & Mitigation Strategy; Risk Assessment / HAZOP / FMECA | U51: L0 Tender / Offer; L1 Conceptual Design; L2 Detailed Design; L3 Procurement & Manufacturing / FAT; L4 Installation; L5 Standalone Commissioning; L6 Site Acceptance Testing | V51: OFFER-stage evidence; linked standards are contextual; does not prove full RTM compliance
A52: OFFER-47 | B52: Quality Assurance Program (QAP) Definition | C52: 124 | D52: 8 | E52: General Quality Assurance and Control | F52: 8.50 | G52: QUALITY_RISK | H52: QAP | I52: In the offer, the Applicant shall: | J52: In the offer, the Applicant shall: • submit a preliminary version of the QAP outlining the quality control process that will be implemented during Contract execution. | K52: RTM-642 | L52: RTM-648..RTM-652 | M52: 6 | N52: Exact canonical section, with child/supporting RTMs classified separately where applicable. | O52: OK — Review breadth | P52: SCK CEN/90508872 PDF+DOCX (08-Apr-2026) | Q52: SCK CEN/90508872 §8; no named external code in OFFER text | R52: None explicitly named in the OFFER text | S52: Submit and review the named deliverable with RTM traceability and approval status; Document review, inspection, certification, audit or traceable QC record; Conformity/safety assessment, certification and approved safety evidence | T52: Offer response: Quality Assurance Program (QAP) Definition; Quality Assurance Plan (QAP) | U52: L0 Tender / Offer; L1 Conceptual Design; L2 Detailed Design; L3 Procurement & Manufacturing / FAT; L4 Installation; L5 Standalone Commissioning; L6 Site Acceptance Testing | V52: OFFER-stage evidence; linked standards are contextual; does not prove full RTM compliance
A53: OFFER-48 | B53: Detailed Quality Control Procedures | C53: 125 | D53: 8.1.3.1 | E53: Quality Assurance Plan (QAP) | F53: 8.51 | G53: QUALITY_RISK | H53: QAP | I53: In their offer, the Applicant shall include a preliminary version of this QAP. | J53: In their offer, the Applicant shall include a preliminary version of this QAP. | K53: RTM-650..RTM-652 | M53: 3 | N53: Exact canonical section, with child/supporting RTMs classified separately where applicable. | O53: OK | P53: SCK CEN/90508872 PDF+DOCX (08-Apr-2026) | Q53: SCK CEN/90508872 §8.1.3.1; no named external code in OFFER text | R53: None explicitly named in the OFFER text | S53: Submit and review the named deliverable with RTM traceability and approval status; Document review, inspection, certification, audit or traceable QC record; Conformity/safety assessment, certification and approved safety evidence | T53: Offer response: Detailed Quality Control Procedures; Quality Assurance Plan (QAP) | U53: L0 Tender / Offer; L1 Conceptual Design; L2 Detailed Design; L3 Procurement & Manufacturing / FAT; L4 Installation; L5 Standalone Commissioning; L6 Site Acceptance Testing | V53: OFFER-stage evidence; linked standards are contextual; does not prove full RTM compliance
A54: OFFER-49 | B54: Codes, Standards & Compliance Framework | C54: 129 | D54: 9 | E54: Applicable legislation, Codes and Standards | F54: 8.52 | G54: QUALITY_RISK | H54: Compliance | I54: In the offer, the Applicant shall include a list of the applied codes, rules and standard for the design, manufacturing, and testing of the QPS. | J54: In the offer, the Applicant shall include a list of the applied codes, rules and standard for the design, manufacturing, and testing of the QPS. | K54: RTM-687..RTM-688 | L54: RTM-689..RTM-705 | M54: 19 | N54: Exact canonical section, with child/supporting RTMs classified separately where applicable. | O54: OK — Review breadth | P54: SCK CEN/90508872 PDF+DOCX (08-Apr-2026) | Q54: Linked canonical RTM/section: ISO 9001; EN 13480; EN 13445; PED; EU declaration of conformity; CE marking; Low Voltage Directive 2014/35/EU; Machinery Directive 2006/42/EC; EMC Directive 2014/30/EU; Pressure Equipment Directive 2014/68/EU; EU Eco-design Directive 2009/125/EC; VLAREM II; IEC 60300-3-3 (Reliability-Centered Maintenance); ISO 20815; IEC 60300-3-11; IEC 60300-3-12 (Life-cycle costing); ISO 55000 / 55001 / 55002 (Asset Management); ISO 14224 (Reliability & maintenance data); EN 61000-6-2; EN 61000-6-4; PED 2014/68/EU; ASME VIII-1; API 520/521; EN ISO 4126; ISO 21013-1/2; IEC 61508; IEC 61511; IEC 60204-1 / 61439; IEC 60300-3-3; IEC 62061; ISO 13849-1; ISO 8573-1 Class 0; ASTM D5464 | R54: No individual standard named; Applicant must submit the complete applied list | S54: Submit and review the named deliverable with RTM traceability and approval status; Witnessed FAT/SAT/commissioning test against stated acceptance criteria; Conformity/safety assessment, certification and approved safety evidence | T54: Offer response: Codes, Standards & Compliance Framework; List / register / matrix | U54: L0 Tender / Offer; L3 Procurement & Manufacturing / FAT; L1 Conceptual Design; L2 Detailed Design; L4 Installation; L5 Standalone Commissioning; L6 Site Acceptance Testing | V54: OFFER-stage evidence; linked standards are contextual; does not prove full RTM compliance
A55: OFFER-50 | B55: Warranty Extension Commercial Terms | C55: 132 | D55: 10.2 | E55: Warranty Period | F55: 8.53 | G55: COMMERCIAL | H55: Warranty | I55: In the offer, the Applicant shall put forward the price per year to extend the Warranty Period with (an) extra year(s) beyond this minimum of 3 years up to a maximum of 6 years in aggregate (initial Warranty Period + extensions). SCK CEN shall be entitled to impose such additional Warranty Period by issuing a separate purchase order to that extent. | J55: In the offer, the Applicant shall put forward the price per year to extend the Warranty Period with (an) extra year(s) beyond this minimum of 3 years up to a maximum of 6 years in aggregate (initial Warranty Period + extensions). SCK CEN shall be entitled to impose such additional Warranty Period by issuing a separate purchase order to that extent. | K55: RTM-708 | L55: RTM-709..RTM-710 | M55: 3 | N55: Warranty-extension price is OFFER-only; warranty RTMs are context. | O55: OK | P55: SCK CEN/90508872 PDF+DOCX (08-Apr-2026) | Q55: SCK CEN/90508872 §10.2; no named external code in OFFER text | R55: None explicitly named in the OFFER text | S55: Submit and review the named deliverable with RTM traceability and approval status | T55: Offer response: Warranty Extension Commercial Terms | U55: L0 Tender / Offer; Warranty; PAC / Handover; FAC | V55: OFFER-stage evidence; linked standards are contextual; does not prove full RTM compliance

Sheet RTM_CROSSWALK
A1: OFFER ↔ RTM crosswalk
A2: Direct, supporting, contextual and broad-scope relationships remain explicitly classified. Column L ('Allocation basis') methodology (this phase): where the source text only restated the section number or said 'subject-specific primary allocation' with no further detail, it was rebuilt from fields already on the row (Relation type, RTM Category, OFFER Category, Section) so it names the actual pairing and reason, shown in italic blue like other rule-derived fields in this workbook. Columns M ('QC check') and N ('Source basis') previously had data but no header at all.
A3: =HYPERLINK("#START_HERE!A1","Start") | B3: =HYPERLINK("#DASHBOARD!A1","Dashboard") | C3: =HYPERLINK("#OFFER_RANKING!A1","Ranking") | D3: =HYPERLINK("#EVALUATION_INPUT!A1","Evaluate") | E3: =HYPERLINK("#OFFER_CANONICAL!A1","Canonical") | F3: =HYPERLINK("#RTM_CROSSWALK!A1","Crosswalk") | G3: =HYPERLINK("#WEIGHTS_METHOD!A1","Method")
A4: OFFER ID | B4: OFFER Title | C4: OFFER Rank | D4: OFFER Section | E4: RTM ID | F4: RTM Rank | G4: RTM Section | H4: RTM Category | I4: RTM Shall statement | J4: Relation type | K4: Coverage note | L4: Allocation basis | M4: QC check | N4: Source basis
A5: OFFER-01 | B5: Tender Compliance Confirmation | C5: 24 | D5: 4.1 | E5: RTM-001 | F5: 242 | G5: 4.13 | H5: General Requirements | I5: The Contractor shall be fully responsible for ensuring that the Deliverables and Services provided fully meet the specified requirements for the Contract. | J5: Direct — primary evidence anchor | K5: Partial evidence: OFFER response supports evaluation; it does not replace full RTM compliance. | L5: RTM-001 (General Requirements) is OFFER-01's (Compliance / Quality) primary technical anchor in §4.13 — the direct classification means this is the main clause being evidenced here, not one of several equally-weighted section-mates. | M5: OK | N5: Canonical PDF/DOCX.
A6: OFFER-01 | B6: Tender Compliance Confirmation | C6: 24 | D6: 4.1 | E6: RTM-002 | F6: 24 | G6: 4.1 | H6: General Requirements | I6: The Contractor shall be fully responsible for the correct definition and execution of all activities (including, but not limited to, engineering, manufacturing, packaging, transportation, delivery, installation, testing, commissioning, QC, QA) necessary to duly perform the Contract and to ensure that (each item in) the Contractor’s scope of supply and (each activity in) the Contractor’s scope of work duly meet the requirements imposed on them. | J6: Supporting — shared section | K6: Partial evidence: OFFER response supports evaluation; it does not replace full RTM compliance. | L6: RTM-002 (General Requirements) and OFFER-01 (Compliance / Quality) are linked only because both sit in §4.1 — a supporting (shared-section) link, not a dedicated cross-reference to this specific clause. | M6: OK | N6: Canonical PDF/DOCX.
A7: OFFER-01 | B7: Tender Compliance Confirmation | C7: 24 | D7: 4.1 | E7: RTM-003 | F7: 24 | G7: 4.1 | H7: General Requirements | I7: The Contractor shall be responsible to obtain the corresponding documents for referenced norms, standards, etc. | J7: Direct — primary evidence anchor | K7: Partial evidence: OFFER response supports evaluation; it does not replace full RTM compliance. | L7: RTM-003 (General Requirements) is OFFER-01's (Compliance / Quality) primary technical anchor in §4.1 — the direct classification means this is the main clause being evidenced here, not one of several equally-weighted section-mates. | M7: OK | N7: Canonical PDF/DOCX.
A8: OFFER-01 | B8: Tender Compliance Confirmation | C8: 24 | D8: 4.1 | E8: RTM-004 | F8: 25 | G8: 4.1 | H8: General Requirements | I8: Any deviations or modifications shall require prior written approval by SCK CEN to be implemented. | J8: Supporting — shared section | K8: Partial evidence: OFFER response supports evaluation; it does not replace full RTM compliance. | L8: RTM-004 (General Requirements) and OFFER-01 (Compliance / Quality) are linked only because both sit in §4.1 — a supporting (shared-section) link, not a dedicated cross-reference to this specific clause. | M8: OK | N8: Canonical PDF/DOCX.
A9: OFFER-02 | B9: Assumptions, Deviations & Additions Register | C9: 24 | D9: 4.1 | E9: RTM-001 | F9: 24 | G9: 4.1 | H9: General Requirements | I9: The Contractor shall be fully responsible for ensuring that the Deliverables and Services provided fully meet the specified requirements for the Contract. | J9: Supporting — shared section | K9: Partial evidence: OFFER response supports evaluation; it does not replace full RTM compliance. | L9: RTM-001 (General Requirements) and OFFER-02 (Compliance / Quality) are linked only because both sit in §4.1 — a supporting (shared-section) link, not a dedicated cross-reference to this specific clause. | M9: OK | N9: Canonical PDF/DOCX.
A10: OFFER-02 | B10: Assumptions, Deviations & Additions Register | C10: 24 | D10: 4.1 | E10: RTM-002 | F10: 24 | G10: 4.1 | H10: General Requirements | I10: The Contractor shall be fully responsible for the correct definition and execution of all activities (including, but not limited to, engineering, manufacturing, packaging, transportation, delivery, installation, testing, commissioning, QC, QA) necessary to duly perform the Contract and to ensure that (each item in) the Contractor’s scope of supply and (each activity in) the Contractor’s scope of work duly meet the requirements imposed on them. | J10: Supporting — shared section | K10: Partial evidence: OFFER response supports evaluation; it does not replace full RTM compliance. | L10: RTM-002 (General Requirements) and OFFER-02 (Compliance / Quality) are linked only because both sit in §4.1 — a supporting (shared-section) link, not a dedicated cross-reference to this specific clause. | M10: OK | N10: Canonical PDF/DOCX.
A11: OFFER-02 | B11: Assumptions, Deviations & Additions Register | C11: 24 | D11: 4.1 | E11: RTM-003 | F11: 24 | G11: 4.1 | H11: General Requirements | I11: The Contractor shall be responsible to obtain the corresponding documents for referenced norms, standards, etc. | J11: Supporting — shared section | K11: Partial evidence: OFFER response supports evaluation; it does not replace full RTM compliance. | L11: RTM-003 (General Requirements) and OFFER-02 (Compliance / Quality) are linked only because both sit in §4.1 — a supporting (shared-section) link, not a dedicated cross-reference to this specific clause. | M11: OK | N11: Canonical PDF/DOCX.
A12: OFFER-02 | B12: Assumptions, Deviations & Additions Register | C12: 24 | D12: 4.1 | E12: RTM-004 | F12: 25 | G12: 4.1 | H12: General Requirements | I12: Any deviations or modifications shall require prior written approval by SCK CEN to be implemented. | J12: Direct — primary evidence anchor | K12: Partial evidence: OFFER response supports evaluation; it does not replace full RTM compliance. | L12: RTM-004 (General Requirements) is OFFER-02's (Compliance / Quality) primary technical anchor in §4.1 — the direct classification means this is the main clause being evidenced here, not one of several equally-weighted section-mates. | M12: OK | N12: Canonical PDF/DOCX.
A13: OFFER-03 | B13: Integrated Technical Proposal & Execution Strategy | C13: 25 | D13: 4.1 | E13: RTM-001 | F13: 24 | G13: 4.1 | H13: General Requirements | I13: The Contractor shall be fully responsible for ensuring that the Deliverables and Services provided fully meet the specified requirements for the Contract. | J13: Supporting — shared section | K13: Partial evidence: OFFER response supports evaluation; it does not replace full RTM compliance. | L13: RTM-001 (General Requirements) and OFFER-03 (Compliance / Quality) are linked only because both sit in §4.1 — a supporting (shared-section) link, not a dedicated cross-reference to this specific clause. | M13: OK | N13: Canonical PDF/DOCX.
A14: OFFER-03 | B14: Integrated Technical Proposal & Execution Strategy | C14: 25 | D14: 4.1 | E14: RTM-002 | F14: 24 | G14: 4.1 | H14: General Requirements | I14: The Contractor shall be fully responsible for the correct definition and execution of all activities (including, but not limited to, engineering, manufacturing, packaging, transportation, delivery, installation, testing, commissioning, QC, QA) necessary to duly perform the Contract and to ensure that (each item in) the Contractor’s scope of supply and (each activity in) the Contractor’s scope of work duly meet the requirements imposed on them. | J14: Direct — primary evidence anchor | K14: Partial evidence: OFFER response supports evaluation; it does not replace full RTM compliance. | L14: RTM-002 (General Requirements) is OFFER-03's (Compliance / Quality) primary technical anchor in §4.1 — the direct classification means this is the main clause being evidenced here, not one of several equally-weighted section-mates. | M14: OK | N14: Canonical PDF/DOCX.
A15: OFFER-03 | B15: Integrated Technical Proposal & Execution Strategy | C15: 25 | D15: 4.1 | E15: RTM-003 | F15: 24 | G15: 4.1 | H15: General Requirements | I15: The Contractor shall be responsible to obtain the corresponding documents for referenced norms, standards, etc. | J15: Supporting — shared section | K15: Partial evidence: OFFER response supports evaluation; it does not replace full RTM compliance. | L15: RTM-003 (General Requirements) and OFFER-03 (Compliance / Quality) are linked only because both sit in §4.1 — a supporting (shared-section) link, not a dedicated cross-reference to this specific clause. | M15: OK | N15: Canonical PDF/DOCX.
A16: OFFER-03 | B16: Integrated Technical Proposal & Execution Strategy | C16: 25 | D16: 4.1 | E16: RTM-004 | F16: 25 | G16: 4.1 | H16: General Requirements | I16: Any deviations or modifications shall require prior written approval by SCK CEN to be implemented. | J16: Supporting — shared section | K16: Partial evidence: OFFER response supports evaluation; it does not replace full RTM compliance. | L16: RTM-004 (General Requirements) and OFFER-03 (Compliance / Quality) are linked only because both sit in §4.1 — a supporting (shared-section) link, not a dedicated cross-reference to this specific clause. | M16: OK | N16: Canonical PDF/DOCX.
A17: OFFER-04 | B17: Cooldown & Thermal Performance Modelling | C17: 29 | D17: 4.2.2.2 | E17: RTM-019 | F17: 28 | G17: 4.2.2.2 | H17: Transient Operational Scenarios | I17: The QPS shall implement the Transient Operational Scenarios defined in Table 4. | J17: Direct — exact contract section | K17: Partial evidence: OFFER response supports evaluation; it does not replace full RTM compliance. | L17: RTM-019 (Transient Operational Scenarios) and OFFER-04 (Performance / Process / Utilities) are linked only because both sit in §4.2.2.2 — a direct (shared-section) link, not a dedicated cross-reference to this specific clause. | M17: OK | N17: Canonical PDF/DOCX.
... A381: OFFER-50 | B381: Warranty Extension Commercial Terms | C381: 132 | D381: 10.2 | E381: RTM-710 | F381: 132 | G381: 10.2 | H381: Warranty Period | I381: If the Contractor fails to fulfil its obligations under the warranty, so that final acceptance cannot take place at the scheduled time, the Warranty Period shall be automatically extended, without any right to compensation for the Contractor, until final acceptance takes place. | J381: Supporting warranty context | K381: The extension price is an OFFER-only commercial input; these RTMs define warranty operation and extension consequences. | L381: RTM-710 (Warranty Period) and OFFER-50 (Configuration / Layout / Support) are linked only because both sit in §10.2 — a supporting warranty context (shared-section) link, not a dedicated cross-reference to this specific clause. | M381: OK | N381: Canonical PDF/DOCX.

Sheet OFFER_RANKING
A1: OFFER static BT ranking — recalculated from scratch
A2: Old frozen ranks and old BT Weight are omitted. Gate status plus frozen dimension weights determine the order.
A3: =HYPERLINK("#START_HERE!A1","Start") | B3: =HYPERLINK("#DASHBOARD!A1","Dashboard") | C3: =HYPERLINK("#OFFER_RANKING!A1","Ranking") | D3: =HYPERLINK("#EVALUATION_INPUT!A1","Evaluate") | E3: =HYPERLINK("#OFFER_CANONICAL!A1","Canonical") | F3: =HYPERLINK("#RTM_CROSSWALK!A1","Crosswalk") | G3: =HYPERLINK("#WEIGHTS_METHOD!A1","Method")
A5: Rank | B5: OFFER ID | C5: Title | D5: Gate | E5: Tier | F5: Category | G5: Section | H5: L | I5: R | J5: P | K5: F | L5: Q | M5: LC | N5: C | O5: Weighted S | P5: BT Win % | Q5: BT λ index | R5: Primary dimension | S5: Interpretation | T5: Actual explicit code / standard | U5: Reference code / standard | V5: Evidence / measurability | W5: Explicit deliverable / proof | X5: Applicable phase(s) | Y5: Primary RTMs | Z5: Supporting RTMs | AA5: Review flag
A6: 1 | B6: OFFER-02 | C6: Assumptions, Deviations & Additions Register | D6: Yes | E6: T0 Gate | F6: Compliance / Quality | G6: §4.1 | H6: 3 | I6: 3 | J6: 0 | K6: 0 | L6: 3 | M6: 0 | N6: 0 | O6: 54 | P6: 100 | Q6: 100 | R6: Reliability | S6: Gate precedence; within T0 ordered by Weighted S. | T6: None explicitly named in the OFFER text | U6: SCK CEN/90508872 §4.1; no named external code in OFFER text | V6: Submit and review the named deliverable with RTM traceability and approval status; RAM/maintenance substantiation and recovery/failure-response evidence; Document review, inspection, certification, audit or traceable QC record | W6: Offer response: Assumptions, Deviations & Additions Register | X6: L0 Tender / Offer; L1 Conceptual Design; L2 Detailed Design | Y6: RTM-004 | Z6: RTM-001..RTM-003 | AA6: OK
A7: 2 | B7: OFFER-48 | C7: Detailed Quality Control Procedures | D7: Yes | E7: T0 Gate | F7: Compliance / Quality | G7: §8.1.3.1 | H7: 3 | I7: 0 | J7: 0 | K7: 2 | L7: 3 | M7: 0 | N7: 0 | O7: 42.6667 | P7: 97.9592 | Q7: 79.4369 | R7: Safety / Legal | S7: Gate precedence; within T0 ordered by Weighted S. | T7: None explicitly named in the OFFER text | U7: SCK CEN/90508872 §8.1.3.1; no named external code in OFFER text | V7: Submit and review the named deliverable with RTM traceability and approval status; Document review, inspection, certification, audit or traceable QC record; Conformity/safety assessment, certification and approved safety evidence | W7: Offer response: Detailed Quality Control Procedures; Quality Assurance Plan (QAP) | X7: L0 Tender / Offer; L1 Conceptual Design; L2 Detailed Design; L3 Procurement & Manufacturing / FAT; L4 Installation; L5 Standalone Commissioning; L6 Site Acceptance Testing | Y7: RTM-650..RTM-652 | AA7: OK
A8: 3 | B8: OFFER-01 | C8: Tender Compliance Confirmation | D8: Yes | E8: T0 Gate | F8: Compliance / Quality | G8: §4.1 | H8: 3 | I8: 0 | J8: 0 | K8: 0 | L8: 3 | M8: 0 | N8: 0 | O8: 32 | P8: 92.8571 | Q8: 48.9107 | R8: Safety / Legal | S8: Gate precedence; within T0 ordered by Weighted S. | T8: None explicitly named in the OFFER text | U8: SCK CEN/90508872 §4.1; no named external code in OFFER text | V8: Submit and review the named deliverable with RTM traceability and approval status; Document review, inspection, certification, audit or traceable QC record; Conformity/safety assessment, certification and approved safety evidence | W8: Offer response: Tender Compliance Confirmation | X8: L0 Tender / Offer; L1 Conceptual Design; L2 Detailed Design | Y8: RTM-001; RTM-003 | Z8: RTM-002; RTM-004 | AA8: OK
A9: 4 | B9: OFFER-03 | C9: Integrated Technical Proposal & Execution Strategy | D9: Yes | E9: T0 Gate | F9: Compliance / Quality | G9: §4.1 | H9: 3 | I9: 0 | J9: 0 | K9: 0 | L9: 3 | M9: 0 | N9: 0 | O9: 32 | P9: 92.8571 | Q9: 48.9107 | R9: Safety / Legal | S9: Gate precedence; within T0 ordered by Weighted S. | T9: None explicitly named in the OFFER text | U9: SCK CEN/90508872 §4.1; no named external code in OFFER text | V9: Submit and review the named deliverable with RTM traceability and approval status; Document review, inspection, certification, audit or traceable QC record; Conformity/safety assessment, certification and approved safety evidence | W9: Offer response: Integrated Technical Proposal & Execution Strategy | X9: L0 Tender / Offer; L1 Conceptual Design; L2 Detailed Design | Y9: RTM-002 | Z9: RTM-001; RTM-003..RTM-004 | AA9: OK
A10: 5 | B10: OFFER-47 | C10: Quality Assurance Program (QAP) Definition | D10: Yes | E10: T0 Gate | F10: Compliance / Quality | G10: §8 | H10: 3 | I10: 0 | J10: 0 | K10: 0 | L10: 3 | M10: 0 | N10: 0 | O10: 32 | P10: 92.8571 | Q10: 48.9107 | R10: Safety / Legal | S10: Gate precedence; within T0 ordered by Weighted S. | T10: None explicitly named in the OFFER text | U10: SCK CEN/90508872 §8; no named external code in OFFER text | V10: Submit and review the named deliverable with RTM traceability and approval status; Document review, inspection, certification, audit or traceable QC record; Conformity/safety assessment, certification and approved safety evidence | W10: Offer response: Quality Assurance Program (QAP) Definition; Quality Assurance Plan (QAP) | X10: L0 Tender / Offer; L1 Conceptual Design; L2 Detailed Design; L3 Procurement & Manufacturing / FAT; L4 Installation; L5 Standalone Commissioning; L6 Site Acceptance Testing | Y10: RTM-642 | Z10: RTM-648..RTM-652 | AA10: OK — Review breadth
A11: 6 | B11: OFFER-49 | C11: Codes, Standards & Compliance Framework | D11: Yes | E11: T0 Gate | F11: Compliance / Quality | G11: §9 | H11: 3 | I11: 0 | J11: 0 | K11: 0 | L11: 3 | M11: 0 | N11: 0 | O11: 32 | P11: 92.8571 | Q11: 48.9107 | R11: Safety / Legal | S11: Gate precedence; within T0 ordered by Weighted S. | T11: No individual standard named; Applicant must submit the complete applied list | U11: Linked canonical RTM/section: ISO 9001; EN 13480; EN 13445; PED; EU declaration of conformity; CE marking; Low Voltage Directive 2014/35/EU; Machinery Directive 2006/42/EC; EMC Directive 2014/30/EU; Pressure Equipment Directive 2014/68/EU; EU Eco-design Directive 2009/125/EC; VLAREM II; IEC 60300-3-3 (Reliability-Centered Maintenance); ISO 20815; IEC 60300-3-11; IEC 60300-3-12 (Life-cycle costing); ISO 55000 / 55001 / 55002 (Asset Management); ISO 14224 (Reliability & maintenance data); EN 61000-6-2; EN 61000-6-4; PED 2014/68/EU; ASME VIII-1; API 520/521; EN ISO 4126; ISO 21013-1/2; IEC 61508; IEC 61511; IEC 60204-1 / 61439; IEC 60300-3-3; IEC 62061; ISO 13849-1; ISO 8573-1 Class 0; ASTM D5464 | V11: Submit and review the named deliverable with RTM traceability and approval status; Witnessed FAT/SAT/commissioning test against stated acceptance criteria; Conformity/safety assessment, certification and approved safety evidence | W11: Offer response: Codes, Standards & Compliance Framework; List / register / matrix | X11: L0 Tender / Offer; L3 Procurement & Manufacturing / FAT; L1 Conceptual Design; L2 Detailed Design; L4 Installation; L5 Standalone Commissioning; L6 Site Acceptance Testing | Y11: RTM-687..RTM-688 | Z11: RTM-689..RTM-705 | AA11: OK — Review breadth
A12: 7 | B12: OFFER-09 | C12: LN2 Techno-Economic Evaluation (CAPEX/OPEX) | D12: No | E12: T1 Primary | F12: Performance / Process / Utilities | G12: §4.2.5 | H12: 0 | I12: 3 | J12: 3 | K12: 2 | L12: 0 | M12: 0 | N12: 3 | O12: 55.6667 | P12: 87.7551 | Q12: 32.5551 | R12: Reliability | S12: Frozen-weight composite; strongest contribution: Reliability. | T12: None explicitly named in the OFFER text | U12: SCK CEN/90508872 §4.2.5; no named external code in OFFER text | V12: Submit and review the named deliverable with RTM traceability and approval status; Calculation/model plus calibrated measurement or recorded trend; Functional design/configuration review and sequence/interface demonstration | W12: Offer response: LN2 Techno-Economic Evaluation (CAPEX/OPEX) | X12: L0 Tender / Offer; PAC / Handover; L1 Conceptual Design; L2 Detailed Design | Z12: RTM-045..RTM-047 | AA12: Review — accept context
A13: 8 | B13: OFFER-42 | C13: After-Sales Service Organization & Pricing | D13: No | E13: T1 Primary | F13: Reliability / RAM / Service | G13: §4.15 | H13: 1 | I13: 3 | J13: 0 | K13: 2 | L13: 0 | M13: 3 | N13: 0 | O13: 46.3333 | P13: 85.7143 | Q13: 28.0529 | R13: Reliability | S13: Frozen-weight composite; strongest contribution: Reliability. | T13: None explicitly named in the OFFER text | U13: SCK CEN/90508872 §4.15; no named external code in OFFER text | V13: Submit and review the named deliverable with RTM traceability and approval status; Functional design/configuration review and sequence/interface demonstration; RAM/maintenance substantiation and recovery/failure-response evidence | W13: Offer response: After-Sales Service Organization & Pricing; Procedure / work instruction | X13: L0 Tender / Offer; L1 Conceptual Design; L2 Detailed Design | Y13: RTM-563..RTM-565 | AA13: OK
A14: 9 | B14: OFFER-20 | C14: Helium Leak Detection & Loss Management | D14: No | E14: T1 Primary | F14: Reliability / RAM / Service | G14: §4.4.7 | H14: 2 | I14: 3 | J14: 0 | K14: 2 | L14: 0 | M14: 0 | N14: 0 | O14: 46 | P14: 82.6531 | Q14: 22.6876 | R14: Reliability | S14: Frozen-weight composite; strongest contribution: Reliability. | T14: None explicitly named in the OFFER text | U14: Linked canonical RTM/section: EN 13185:2001 | V14: Submit and review the named deliverable with RTM traceability and approval status; Witnessed FAT/SAT/commissioning test against stated acceptance criteria; Functional design/configuration review and sequence/interface demonstration | W14: Offer response: Helium Leak Detection & Loss Management; Test procedure / report; Procedure / work instruction | X14: L0 Tender / Offer; L4 Installation; L1 Conceptual Design; L2 Detailed Design | Y14: RTM-252..RTM-257 | Z14: RTM-258..RTM-262 | AA14: OK — Review breadth
A15: 10 | B15: OFFER-34 | C15: Cooling Water System Requirements | D15: No | E15: T1 Primary | F15: Performance / Process / Utilities | G15: §4.7.4.3.2 | H15: 0 | I15: 3 | J15: 2 | K15: 2 | L15: 0 | M15: 0 | N15: 0 | O15: 46 | P15: 82.6531 | Q15: 22.6876 | R15: Reliability | S15: Frozen-weight composite; strongest contribution: Reliability. | T15: None explicitly named in the OFFER text | U15: SCK CEN/90508872 §4.7.4.3.2; no named external code in OFFER text | V15: Submit and review the named deliverable with RTM traceability and approval status; Calculation/model plus calibrated measurement or recorded trend; RAM/maintenance substantiation and recovery/failure-response evidence | W15: Offer response: Cooling Water System Requirements | X15: L0 Tender / Offer; L1 Conceptual Design; L2 Detailed Design | Y15: RTM-426..RTM-427 | AA15: OK
A16: 11 | B16: OFFER-29 | C16: Control System Obsolescence Strategy | D16: No | E16: T1 Primary | F16: Controls / Software / Management | G16: §4.6.8 | H16: 0 | I16: 3 | J16: 0 | K16: 3 | L16: 0 | M16: 3 | N16: 0 | O16: 45 | P16: 79.5918 | Q16: 18.5439 | R16: Reliability | S16: Frozen-weight composite; strongest contribution: Reliability. | T16: None explicitly named in the OFFER text | U16: SCK CEN/90508872 §4.6.8; no named external code in OFFER text | V16: Submit and review the named deliverable with RTM traceability and approval status; Functional design/configuration review and sequence/interface demonstration; RAM/maintenance substantiation and recovery/failure-response evidence | W16: Offer response: Control System Obsolescence Strategy | X16: L0 Tender / Offer; L1 Conceptual Design; L2 Detailed Design | Y16: RTM-346..RTM-367 | AA16: OK
A17: 12 | B17: OFFER-04 | C17: Cooldown & Thermal Performance Modelling | D17: No | E17: T1 Primary | F17: Performance / Process / Utilities | G17: §4.2.2.2 | H17: 0 | I17: 0 | J17: 3 | K17: 3 | L17: 2 | M17: 0 | N17: 0 | O17: 44 | P17: 76.5306 | Q17: 15.2851 | R17: Performance | S17: Frozen-weight composite; strongest contribution: Performance. | T17: None explicitly named in the OFFER text | U17: SCK CEN/90508872 §4.2.2.2; no named external code in OFFER text | V17: Submit and review the named deliverable with RTM traceability and approval status; Calculation/model plus calibrated measurement or recorded trend; Document review, inspection, certification, audit or traceable QC record | W17: Offer response: Cooldown & Thermal Performance Modelling | X17: L0 Tender / Offer; L1 Conceptual Design; L2 Detailed Design | Y17: RTM-019..RTM-022 | AA17: OK
A18: 13 | B18: OFFER-05 | C18: Operational Procedure Strategy (Auto vs Manual) | D18: No | E18: T1 Primary | F18: Controls / Software / Management | G18: §4.2.2.4.1 | H18: 0 | I18: 0 | J18: 3 | K18: 3 | L18: 2 | M18: 0 | N18: 0 | O18: 44 | P18: 76.5306 | Q18: 15.2851 | R18: Performance | S18: Frozen-weight composite; strongest contribution: Performance. | T18: None explicitly named in the OFFER text | U18: SCK CEN/90508872 §4.2.2.4.1; no named external code in OFFER text | V18: Submit and review the named deliverable with RTM traceability and approval status; Calculation/model plus calibrated measurement or recorded trend; Functional design/configuration review and sequence/interface demonstration | W18: Offer response: Operational Procedure Strategy (Auto vs Manual); Procedure / work instruction | X18: L0 Tender / Offer; L1 Conceptual Design; L2 Detailed Design | Y18: RTM-025..RTM-027 | AA18: OK
A19: 14 | B19: OFFER-27 | C19: Programming Standards & Language Strategy | D19: No | E19: T1 Primary | F19: Controls / Software / Management | G19: §4.6.7 | H19: 2 | I19: 0 | J19: 0 | K19: 3 | L19: 3 | M19: 0 | N19: 0 | O19: 41.3333 | P19: 73.4694 | Q19: 12.6844 | R19: Functional | S19: Frozen-weight composite; strongest contribution: Functional. | T19: IEC 61131-3 | U19: Linked canonical RTM/section: IEC 61131-3 | V19: Submit and review the named deliverable with RTM traceability and approval status; Witnessed FAT/SAT/commissioning test against stated acceptance criteria; Functional design/configuration review and sequence/interface demonstration | W19: Offer response: Programming Standards & Language Strategy | X19: L0 Tender / Offer; L1 Conceptual Design; L2 Detailed Design | Y19: RTM-340..RTM-341; RTM-343..RTM-344 | Z19: RTM-334..RTM-339; RTM-342; RTM-345 | AA19: OK
